Workbook

Sheet Detailed Requirements
A1: Sequence as per user Flow | B1: High Level FR | C1: FR | D1: Screen | E1: CTA Button | F1: Task # | G1: Task Details | H1: Description / Scope | I1: Acceptance Criteria | J1: Task Type | K1: Dependent On | L1: Effort (w/o AI) | M1: Effort (w/ AI) | N1: Effort w/ AI + Buffer (days) | O1: AI Stack | P1: Standard Stack | Q1: DB Operation | R1: Store | S1: Tables / Measurements | T1: Key fields written / read | U1: API Contract | V1: Handoff Output → Next FR
A2: 1 | B2: Uploading requirements | C2: FR-001 | D2: Design & Author | E2: Drop file or click | F2: BE-01 | G2: Defines and stores the allowed file formats (PDF, DOCX, XLSX, CSV) as a centralised whitelist configurable via environment variables without code redeployment. | H2: • Defines the allowed file formats (PDF, DOCX, XLSX, CSV) as a centralized whitelist stored in a config/enum. • Configuration is injectable via environment variables without requiring code deployment. • MIME types and file extensions are stored together for validation purposes. | I2: • Must return exactly 4 entries: application/pdf, .docx, .xlsx, text/csv • Must allow adding a new type via environment variable configuration • Must apply configuration changes without requiring code redeployment • Must store MIME types and file extensions together in the whitelist | J2: Backend Dev | L2: 2 | M2: 0.5 | N2: =MAX(ROUND(M2*1.2/0.25,0)*0.25,0.25) -> 0.5 | O2: GitHub Copilot — generate enum + YAML config boilerplate Claude — design MIME whitelist logic & edge cases | P2: Spring Boot · Java Enum · AWS SSM Parameter Store · Spring @ConfigurationProperties | Q2: WRITE (session) | R2: Redis (session only) | S2: session.checkpoint_data [in-memory pool] | T2: No test_case / test_step write. File bytes + parsed TCs held in session only. Pool is client-side state. | U2: INTERNAL CONFIG: Whitelist constant — no HTTP endpoint. Config: application.yml allowed-mime-types: - application/pdf - application/vnd.openxmlformats-officedocument .wordprocessingml.document - application/vnd.openxmlformats-officedocument .spreadsheetml.sheet - text/csv Used by: FR-001 BE-10 (Upload API) for validation.
A3: 1 | B3: Uploading requirements | C3: FR-001 | D3: Design & Author | E3: Drop file or click | F3: BE-02 | G3: Enforces a configurable maximum file size limit (default 20 MB) at tenant level, rejecting uploads that exceed the threshold before any processing begins. | H3: • Enforces a configurable maximum file size limit (default 20 MB) at tenant level, stored in the tenant_config table. • Platform enforces a hard cap (e.g. 200 MB) via AWS SSM that tenants cannot exceed. • Tenant admins adjust their limit through Settings → General, and the value is read at runtime per tenant without restart. • Uploads exceeding the threshold are rejected before any processing begins. | I3: • Must default to 20 MB for all new tenants on provisioning • Must allow tenant admin to update the limit via Settings → General up to the platform hard cap • Must apply the updated limit on the next upload attempt without service restart • Must reject values of 0, negative numbers, or values above the platform hard cap with a clear error • Must never allow tenant-configured limits to exceed the platform hard cap enforced via AWS SSM | J3: Backend Dev | K3: FR-001 BE-01 · Settings → General (tenant_config write) | L3: 2 | M3: 0.5 | N3: =MAX(ROUND(M3*1.2/0.25,0)*0.25,0.25) -> 0.5 | O3: GitHub Copilot — scaffold @ConfigurationProperties class + unit tests | P3: Spring Boot · application.yml · AWS SSM Parameter Store · Spring @ConfigurationProperties | Q3: WRITE (session) | R3: Redis (session only) | S3: session.checkpoint_data [in-memory pool] | T3: No test_case / test_step write. File bytes + parsed TCs held in session only. Pool is client-side state. | U3: INTERNAL CONFIG: No HTTP endpoint. Config: application.yml max-upload-size-mb: 20 Runtime-injectable via env var ICE_MAX_UPLOAD_MB. Used by: FR-001 BE-10 (Upload API) for size check.
A4: 1 | B4: Uploading requirements | C4: FR-001 | D4: Design & Author | E4: Drop file or click | F4: BE-03 | G4: Maintains a registry of structured error codes and human-readable messages for all upload rejection scenarios, ensuring consistent error responses across clients. | H4: • Maintains a registry of structured error codes for all upload rejection scenarios (ERR-001-FORMAT, ERR-001-SIZE, ERR-001-CORRUPT, ERR-001-EMPTY, ERR-002-FORMAT, ERR-002-SIZE). • Each error code has a corresponding human-readable message string stored as a Java enum. • Registry is referenced by BE-04, BE-05, BE-06, and all tests to ensure consistent error responses. | I4: • Must contain all 6 error codes with corresponding message strings: ERR-001-FORMAT, ERR-001-SIZE, ERR-001-CORRUPT, ERR-001-EMPTY, ERR-002-FORMAT, ERR-002-SIZE • Must map each error code to exactly one failure scenario with no ambiguity • Must allow adding a new error code via enum update only, requiring no other code changes • Must document all error codes in OpenAPI spec with message and HTTP status | J4: Backend Dev | L4: 1 | M4: 0.25 | N4: =MAX(ROUND(M4*1.2/0.25,0)*0.25,0.25) -> 0.25 | O4: GitHub Copilot — generate error code enum + exception handler Claude — define error taxonomy & priority order | P4: Java Enum · OpenAPI / Swagger annotations · Spring Boot | Q4: WRITE (session) | R4: Redis (session only) | S4: session.checkpoint_data [in-memory pool] | T4: No test_case / test_step write. File bytes + parsed TCs held in session only. Pool is client-side state. | U4: INTERNAL — Error code enum, no HTTP endpoint. Codes returned inside Upload API response body: ERR-001-FORMAT — wrong file type ERR-001-SIZE — exceeds max size ERR-001-CORRUPT — unreadable file ERR-001-EMPTY — zero-byte file Response shape: {code, message, detail}
A5: 1 | B5: Uploading requirements | C5: FR-001 | D5: Design & Author | E5: Drop file or click | F5: BE-04 | G5: Validates the MIME type of each uploaded file against the whitelist, rejecting files whose declared type does not match the allowed set. | H5: • Validates the MIME type of each uploaded file against the whitelist using Apache Tika for server-side enforcement. • Reads actual file bytes to detect real content type, not browser-reported File.type or file extension. • Whitelist configuration is read from FR-001 BE-01 at runtime. • Files whose declared type does not match the allowed set are rejected. | I5: • Must validate MIME type using Apache Tika by reading actual file bytes, not browser-reported File.type or file extension • Must reject .exe file renamed to .pdf after Tika detects application/x-msdownload with ERR-002-FORMAT • Must accept valid PDF files that match whitelist • Must return ERR-002-FORMAT on rejection • Must read whitelist configuration from FR-001 BE-01, applying new types without code change | J5: Backend Dev | K5: FR-001 / BE-01 | L5: 2 | M5: 0.5 | N5: =MAX(ROUND(M5*1.2/0.25,0)*0.25,0.25) -> 0.5 | O5: GitHub Copilot — generate Tika integration + whitelist check Claude — edge case logic for polyglot files | P5: Apache Tika · Spring Boot · Java Enum (whitelist) | Q5: READ (session) | R5: Redis (session only) | S5: [in-memory upload context] | T5: Reads uploaded file bytes from session context. Returns validation result. No DB write on pass. On fail: error code returned to FE; session cleared. | U5: INTERNAL — called inside FR-001 BE-10 handler. Apache Tika validates actual bytes (not extension). Returns: {valid, detected_mime, error_code} Errors emitted: ERR-001-FORMAT, ERR-001-CORRUPT Not a standalone HTTP endpoint. This is the security gate — client check (FR-001 FE-01) is UX only and does not replace this.
A6: 1 | B6: Uploading requirements | C6: FR-001 | D6: Design & Author | E6: Drop file or click | F6: BE-05 | G6: Enforces the file size limit at the API layer before the file reaches storage, returning a structured error if the limit is exceeded. | H6: • Enforces the file size limit at the API layer by validating actual received bytes, not Content-Length header. • Reads the configurable max size limit from FR-001 BE-02 (AWS SSM / application.yml) at runtime. • Rejects files exceeding the limit before any parsing occurs. • Returns a structured error if the limit is exceeded. | I6: • Must validate actual received byte count, not Content-Length header • Must reject files exceeding the configured limit with HTTP 413 + ERR-002-SIZE • Must read the configurable max size limit from FR-001 BE-02 at runtime • Must apply configuration changes from FR-001 BE-02 without service restart • Must reject files even when Content-Length header is spoofed to bypass validation | J6: Backend Dev | K6: FR-001 / BE-02 | L6: 2 | M6: 0.5 | N6: =MAX(ROUND(M6*1.2/0.25,0)*0.25,0.25) -> 0.5 | O6: GitHub Copilot — scaffold size enforcement + config binding | P6: Spring Boot · AWS SSM · @ConfigurationProperties | Q6: READ (session) | R6: Redis (session only) | S6: [in-memory upload context] | T6: Reads uploaded file bytes from session context. Returns validation result. No DB write on pass. On fail: error code returned to FE; session cleared. | U6: INTERNAL — called inside FR-001 BE-10 handler. Compares file size against configured max. Config: ICE_MAX_UPLOAD_MB (default 20). Emits: ERR-001-SIZE if exceeded. Not a standalone HTTP endpoint.
A7: 1 | B7: Uploading requirements | C7: FR-001 | D7: Design & Author | E7: Drop file or click | F7: BE-06 | G7: Defines the standard JSON error response schema returned on upload failure, including error code, message, and resolution hint fields. | H7: • Defines the standard JSON error response schema with fields: code, message, and detail. • Implements Spring Boot @ControllerAdvice that catches validation failures and serializes them using the error code registry from FR-001 BE-03. • Applies priority order for error reporting: format → size → integrity. | I7: • Must return all validation failures as JSON with fields: code, message, and detail • Must never return raw 500 errors or plain text responses • Must use error codes that match FR-001 BE-03 registry exactly • Must return the first failure in priority order when multiple simultaneous failures occur: format → size → integrity | J7: Backend Dev | K7: FR-001 / BE-03 | L7: 1 | M7: 0.25 | N7: =MAX(ROUND(M7*1.2/0.25,0)*0.25,0.25) -> 0.25 | O7: GitHub Copilot — generate error schema + @ControllerAdvice Claude — error priority order design | P7: Spring Boot @ControllerAdvice · OpenAPI 3.0 · Java Enum | Q7: READ (session) | R7: Redis (session only) | S7: [in-memory upload context] | T7: Reads uploaded file bytes from session context. Returns validation result. No DB write on pass. On fail: error code returned to FE; session cleared. | U7: INTERNAL — defines error response schema. All validation errors returned as: HTTP 400 {code: 'ERR-001-*', message: string, detail: string} No raw 500s. No generic 'upload failed' string.
A8: 1 | B8: Uploading requirements | C8: FR-001 | D8: Design & Author | E8: Drop file or click | F8: BE-07 | G8: Validates file integrity by checking for corruption or truncation after upload, ensuring the received file matches the declared content length. | H8: • Validates file integrity by attempting to parse the file using format-specific libraries (pdfplumber, python-docx, openpyxl, csv.reader). • Performs deep integrity check after upload to ensure the received file matches declared content length. • Rejects files that are corrupt, zero-byte, truncated, or password-protected. | I8: • Must return ERR-001-CORRUPT for corrupt .pdf files • Must return ERR-001-CORRUPT for password-protected DOCX files • Must return ERR-001-EMPTY for zero-byte files • Must accept valid parseable files of all 4 types: PDF, DOCX, XLSX, CSV • Must validate file integrity by parsing with format-specific libraries: pdfplumber, python-docx, openpyxl, csv.reader | J8: Backend Dev | K8: FR-001 / BE-01, BE-10 | L8: 4 | M8: 1 | N8: =MAX(ROUND(M8*1.2/0.25,0)*0.25,0.25) -> 1.25 | O8: GitHub Copilot — generate per-format parser stubs Claude — edge case logic (password-protected, zero-byte) | P8: pdfplumber · python-docx · openpyxl · csv.reader · Spring Boot | Q8: WRITE (session) | R8: Redis (session only) | S8: session.checkpoint_data [in-memory pool] | T8: No test_case / test_step write. File bytes + parsed TCs held in session only. Pool is client-side state. | U8: INTERNAL — called inside BE-10 upload handler. Runs Apache Tika on file bytes to verify real MIME type matches declared extension. Returns: {valid: bool, detected_mime, error_code} Not a standalone HTTP endpoint.
A9: 1 | B9: Uploading requirements | C9: FR-001 | D9: Design & Author | E9: Drop file or click | F9: BE-08 | G9: Stores the uploaded file reference in the active session context so downstream CLAP steps can access it without re-upload. | H9: • Stores the uploaded file reference in the active session context keyed by session ID. • Uploaded file bytes and parsed content are held in active session only, with no write to ICE DB. • Downstream CLAP steps access the file from session context without re-upload. | I9: • Must store uploaded file reference in active session context keyed by session ID • Must allow file content to be retrievable within same session by session ID • Must return null for expired session IDs • Must write zero rows to any ICE DB table during Step 1 • Must hold uploaded file bytes and parsed content in active session only with no write to ICE DB | J9: Backend Dev | L9: 4 | M9: 1.5 | N9: =MAX(ROUND(M9*1.2/0.25,0)*0.25,0.25) -> 1.75 | O9: GitHub Copilot — generate Redis session config + unit tests Claude — session isolation design | P9: Spring Session · Redis · Spring Security · Jackson (serialisation) | Q9: WRITE (session) | R9: Redis (session only) | S9: session.checkpoint_data [in-memory pool] | T9: No test_case / test_step write. File bytes + parsed TCs held in session only. Pool is client-side state. | U9: INTERNAL — Session store, no HTTP endpoint. Redis key: ice:session:{session_id}:upload Stores: {file_bytes, parsed_content, file_name, mime_type, size_bytes} TTL: matches session expires_at (4 ). Read by: FR-003 BE-07 (Gateway Orchestrator)
A10: 1 | B10: Uploading requirements | C10: FR-001 | D10: Design & Author | E10: Drop file or click | F10: BE-09 | G10: Supports multiple file uploads per session, allowing users to add further requirement documents without restarting the session. | H10: • Supports multiple file uploads per session, allowing users to add further requirement documents without restarting. • Each uploaded file is stored with a unique sessionFileId within the session context. • All files are held in session and passed to CLAP for test case generation. | I10: • Must allow multiple files to be uploaded in the same session • Must store each uploaded file with a unique sessionFileId within the session context • Must keep each sessionFileId independently resolvable within the session • Must enable the Generate button after at least one valid file is uploaded • Must update the file list in UI to show all uploaded files • Must allow removing individual files without affecting others or ending the session | J10: Backend Dev | K10: FR-001 / BE-08, BE-10 | L10: 2 | M10: 0.5 | N10: =MAX(ROUND(M10*1.2/0.25,0)*0.25,0.25) -> 0.5 | O10: GitHub Copilot — generate session replacement logic + concurrent tests | P10: Spring Session · Redis TTL / key eviction · JUnit 5 | Q10: WRITE (session) | R10: Redis (session only) | S10: session.checkpoint_data [in-memory pool] | T10: No test_case / test_step write. File bytes + parsed TCs held in session only. Pool is client-side state. | U10: INTERNAL — session guard called inside BE-10. Checks Redis for existing upload in session. If found: returns 409 with message 'Session already has a file. Remove it first.' Not a standalone HTTP endpoint.
A11: 1 | B11: Uploading requirements | C11: FR-001 | D11: Design & Author | E11: Drop file or click | F11: BE-10 | G11: Exposes the POST /api/v1/upload endpoint that accepts multipart file uploads, validates them, and returns a file reference on success. | H11: • Exposes POST /api/v1/sessions/{session_id}/upload endpoint that accepts multipart/form-data. • Orchestrates the validation pipeline: MIME check (BE-04) → size check (BE-05) → integrity check (BE-07) → session store (BE-08). • Returns a file reference on success or structured error response using codes from BE-03 registry. | I11: • Must return HTTP 200 + { sessionFileId, fileName, sizeBytes, format } for valid file uploads • Must return HTTP 422 + ERR-001-FORMAT for invalid file format • Must return HTTP 413 + ERR-001-SIZE for oversized files • Must return HTTP 422 + ERR-001-CORRUPT for corrupt files • Must return HTTP 422 + ERR-001-EMPTY for empty files • Must reject requests containing more than one file per request • Must orchestrate validation pipeline: MIME check (BE-04) → size check (BE-05) → integrity check (BE-07) → session store (BE-08) | J11: Backend Dev | K11: FR-001 / BE-03, BE-04, BE-05, BE-07, BE-08 | L11: 4 | M11: 1.5 | N11: =MAX(ROUND(M11*1.2/0.25,0)*0.25,0.25) -> 1.75 | O11: GitHub Copilot — generate MultipartFile controller + validation chain Claude — API contract design Postman AI — generate test collection from OpenAPI spec | P11: Spring Boot · Spring MVC (MultipartFile) · OpenAPI 3.0 · JUnit 5 + Mockito | Q11: WRITE (session) | R11: Redis (session only) | S11: session.checkpoint_data [in-memory pool] | T11: No test_case / test_step write. File bytes + parsed TCs held in session only. Pool is client-side state. | U11: ENDPOINT YOU CREATE: POST /api/v1/sessions/{session_id}/upload Content-Type: multipart/form-data Body: file (binary) Response 200: {file_name, size_bytes, mime_type, session_id, uploaded_at} Errors: 400 ERR-001-FORMAT — invalid mime type 400 ERR-001-SIZE — exceeds limit 400 ERR-001-CORRUPT — unreadable 400 ERR-001-EMPTY — zero bytes 409 — session already has a file | V11: → FR-002 BE-02 session.uploadedFiles[sessionFileId] = { fileBytes, parsedText, format, fileName, sizeBytes } FR-002 BE-02 reads parsedText from this key.
A12: 1 | B12: Uploading requirements | C12: FR-001 | D12: Design & Author | E12: Drop file or click | F12: FE-01 | G12: Renders the file upload area on the Design & Author screen, supporting both drag-and-drop and click-to-browse file selection. | H12: • Renders the file upload area on the Design & Author screen supporting both drag-and-drop and click-to-browse file selection. • Single file upload only with multi-file disabled. • Accepts the 4 allowed extensions at OS picker level. | I12: • Must restrict file picker accept attribute to .pdf,.docx,.xlsx,.csv • Must accept single file via drag-and-drop • Must reject multiple files dropped simultaneously • Must show placeholder/prompt when no file is loaded • Must support both drag-and-drop and click-to-browse file selection | J12: Frontend Dev | L12: 4 | M12: 1 | N12: =MAX(ROUND(M12*1.2/0.25,0)*0.25,0.25) -> 1.25 | O12: v0.dev — generate drag-and-drop upload UI component GitHub Copilot — react-dropzone wiring + validation logic | P12: React · react-dropzone · TypeScript · Tailwind CSS · HTML5 File API | Q12: WRITE (session) | R12: Redis (session only) | S12: session.checkpoint_data [in-memory pool] | T12: No test_case / test_step write. File bytes + parsed TCs held in session only. Pool is client-side state. | U12: ENDPOINT YOU CALL (defined in FR-001 BE-10): POST /api/v1/sessions/{session_id}/upload Send: multipart/form-data with file field. On 200: show file name + size, enable Generate. On 400 ERR-001-FORMAT: show format error inline. On 400 ERR-001-SIZE: show size error inline. On 409: prompt user to remove existing file first. While uploading: show progress indicator (FE-03).
A13: 1 | B13: Uploading requirements | C13: FR-001 | D13: Design & Author | E13: Drop file or click | F13: FE-02 | G13: Displays inline validation error messages directly below the upload area when a file is rejected, using the error codes from BE-03. | H13: • Displays inline validation error messages directly below the upload area when a file is rejected. • Shows error code and human-readable message from BE-03 registry. • Uses inline banner only, no modal or toast notification. | I13: • Must display error message within 300 ms of rejection • Must show error code and plain-English description from BE-03 registry • Must clear error when user selects a new file • Must use inline banner only, not modal or toast notification • Must display error directly below the upload area | J13: Frontend Dev | L13: 2 | M13: 0.5 | N13: =MAX(ROUND(M13*1.2/0.25,0)*0.25,0.25) -> 0.5 | O13: v0.dev — generate inline error banner component GitHub Copilot — error code ↔ message mapping | P13: React · Tailwind CSS · TypeScript | Q13: WRITE (session) | R13: Redis (session only) | S13: session.checkpoint_data [in-memory pool] | T13: No test_case / test_step write. File bytes + parsed TCs held in session only. Pool is client-side state. | U13: No API call — pure UI component. Listens for error state from FE-01 (FE-04) and renders inline error banner below upload zone. Displays: error code + human-readable message. Clears on new file selection.
A14: 1 | B14: Uploading requirements | C14: FR-001 | D14: Design & Author | E14: Drop file or click | F14: FE-03 | G14: Shows a progress indicator during upload, reflecting real-time upload percentage and transitioning to a success state on completion. | H14: • Shows a progress indicator (spinner or bar) during file transmission and validation. • Upload area is locked and non-interactive during in-progress state. • Transitions to success state on completion. | I14: • Must display a progress indicator (spinner or bar) immediately upon file selection or drop • Must lock the upload area and make it non-interactive during the upload process • Must transition the indicator to a success state upon successful upload completion • Must remove the indicator on error and allow the upload area to become interactive again | J14: Frontend Dev | L14: 2 | M14: 0.5 | N14: =MAX(ROUND(M14*1.2/0.25,0)*0.25,0.25) -> 0.5 | O14: v0.dev — generate progress indicator UI GitHub Copilot — Axios interceptor for progress events | P14: React · Tailwind CSS · Axios · HTML5 upload progress event | Q14: WRITE (session) | R14: Redis (session only) | S14: session.checkpoint_data [in-memory pool] | T14: No test_case / test_step write. File bytes + parsed TCs held in session only. Pool is client-side state. | U14: No API call — pure UI component. Reads XMLHttpRequest upload progress event from FE-04 API integration call. Shows % progress bar while upload is in flight.
A15: 1 | B15: Uploading requirements | C15: FR-001 | D15: Design & Author | E15: Drop file or click | F15: FE-04 | G15: Calls the BE-10 upload API on file selection, handles the response, and passes the file reference to the session context. | H15: • Calls POST /api/v1/upload (BE-10) when file is selected in the upload UI (FE-01). • On success, stores sessionFileId in application state for session context. • On failure, passes error code to error display component (FE-02). | I15: • Must trigger exactly one POST request to /api/v1/upload when a file is selected in FE-01 • Must store sessionFileId in application state and display the file name when HTTP 200 is received • Must surface the specific error code inline when HTTP 422 or 413 is received • Must display a user-friendly retry message on network timeout • Must pass the error code to the error display component (FE-02) on any failure response | J15: Frontend Dev | K15: FR-001 / FE-01, FE-02, FE-03, BE-10 | L15: 3 | M15: 1 | N15: =MAX(ROUND(M15*1.2/0.25,0)*0.25,0.25) -> 1.25 | O15: GitHub Copilot — Axios call + React Query wiring Cursor — auto-wire error codes to FE-02 display | P15: React · Axios · React Query / Redux Toolkit · TypeScript · Jest + React Testing Library | Q15: WRITE (session) | R15: Redis (session only) | S15: session.checkpoint_data [in-memory pool] | T15: No test_case / test_step write. File bytes + parsed TCs held in session only. Pool is client-side state. | U15: ENDPOINT YOU CALL (defined in FR-001 BE-10): POST /api/v1/sessions/{session_id}/upload Wire file from FE-01 dropzone to this endpoint. Use XMLHttpRequest (not fetch) for progress events. Headers: Content-Type: multipart/form-data On success: notify FE-01, FE-05, FE-06. On error: pass error code to FE-02 for display.
A16: 1 | B16: Uploading requirements | C16: FR-001 | D16: Design & Author | E16: Drop file or click | F16: FE-05 | G16: Enables the Generate & Add to Pool button only after at least one valid file has been successfully uploaded and its reference stored in session. | H16: • Generate Test Cases button is disabled until a valid file is confirmed with sessionFileId in state. • Button is enabled only after at least one valid file has been successfully uploaded. • Re-disables if file is cleared or replaced before new upload completes. | I16: • Must keep the Generate Test Cases button disabled on page load • Must enable the button only after HTTP 200 response sets sessionFileId in state • Must disable the button again if the file is cleared before a new upload completes • Must set aria-disabled='true' attribute in the disabled state, not rely on visual styling alone | J16: Frontend Dev | K16: FR-001 / FE-04 | L16: 2 | M16: 0.5 | N16: =MAX(ROUND(M16*1.2/0.25,0)*0.25,0.25) -> 0.5 | O16: GitHub Copilot — button state logic + aria-disabled wiring Cursor — generate enable/disable state machine | P16: React · TypeScript · ARIA attributes · Jest + Testing Library | Q16: WRITE (session) | R16: Redis (session only) | S16: session.checkpoint_data [in-memory pool] | T16: No test_case / test_step write. File bytes + parsed TCs held in session only. Pool is client-side state. | U16: ENDPOINT YOU CALL (defined in FR-001 BE-10): Watch response from POST /upload. Enable Generate button only when 200 received and session has a file (check via GET /api/v1/sessions/{id}/status). Disable if session file removed or expired.
A17: 1 | B17: Uploading requirements | C17: FR-001 | D17: Design & Author | E17: Drop file or click | F17: FE-06 | G17: Displays the uploaded file name and metadata (size, type) alongside the upload area as confirmation of a successful upload. | H17: • Displays the uploaded file name, format badge, and file size after successful upload as confirmation to the user. • The file metadata is rendered alongside the upload area in the frontend UI. • Provides Remove and Replace affordances to clear the file and reset the upload state. | I17: • Must display the uploaded file name accurately, truncating with a tooltip if longer than 40 characters • Must show a format badge displaying one of: PDF, DOCX, XLSX, or CSV • Must display file size in KB or MB rounded to 1 decimal place • Must clear sessionFileId and disable the Generate button when the Remove action is clicked • Must provide both Remove and Replace affordances alongside the file metadata display | J17: Frontend Dev | K17: FR-001 / FE-04 | L17: 2 | M17: 0.5 | N17: =MAX(ROUND(M17*1.2/0.25,0)*0.25,0.25) -> 0.5 | O17: v0.dev — generate file metadata card UI GitHub Copilot — truncation + tooltip + Remove handler | P17: React · TypeScript · Tailwind CSS · React Tooltip · Bytes.js | Q17: WRITE (session) | R17: Redis (session only) | S17: session.checkpoint_data [in-memory pool] | T17: No test_case / test_step write. File bytes + parsed TCs held in session only. Pool is client-side state. | U17: ENDPOINT YOU CALL (defined in FR-001 BE-10): Read {file_name, size_bytes} from POST /upload 200 response to display file metadata strip below upload zone (name · size · type badge).
A18: 1 | B18: Uploading requirements | C18: FR-001 | D18: Design & Author | E18: Drop file or click | F18: INT-01 | G18: Validates the full upload happy path: valid file selected, uploaded successfully, file reference stored in session, Generate button enabled. | H18: • Validates the complete upload happy path for all 4 supported file formats from file selection through to Generate button enablement. • Tests that upload succeeds, file name is displayed, Generate button is enabled, and sessionFileId is scoped to the session only. • Covers the full end-to-end flow ensuring file reference is stored in session and ready for generation. | I18: • Must complete the full upload flow without error for each of the 4 supported file formats (PDF, DOCX, XLSX, CSV) • Must display the file name and enable the Generate button after each successful upload • Must ensure that two parallel browser sessions each see only their own uploaded file • Must not create any DB rows in ICE tables during the upload process | J18: QA / Both Devs | K18: FR-001 / All BE + FE tasks | L18: 3 | M18: 1 | N18: =MAX(ROUND(M18*1.2/0.25,0)*0.25,0.25) -> 1.25 | O18: Playwright AI — generate E2E test scripts from user stories Claude — generate test scenarios from AC GitHub Actions AI — suggest CI pipeline config | P18: Playwright · Cypress · Docker Compose · GitHub Actions CI | Q18: WRITE (session) | R18: Redis (session only) | S18: session.checkpoint_data [in-memory pool] | T18: No test_case / test_step write. File bytes + parsed TCs held in session only. Pool is client-side state. | U18: ENDPOINT UNDER TEST: POST /api/v1/sessions/{session_id}/upload Test cases: 200 — valid PDF, DOCX, XLSX, CSV 400 ERR-001-FORMAT — .exe file 400 ERR-001-SIZE — 25MB file 400 ERR-001-CORRUPT — corrupted PDF 400 ERR-001-EMPTY — empty file 409 — second upload same session
A19: 1 | B19: Uploading requirements | C19: FR-001 | D19: Design & Author | E19: Drop file or click | F19: INT-02 | G19: Validates all upload rejection paths including wrong format, oversized file, corrupted file, and duplicate upload within the same session. | H19: • Validates all upload rejection scenarios including wrong format, oversized file, corrupted file, and duplicate upload within the same session. • Tests both client-side fast-fail validation (FE-01) and server-side enforcement (BE-04, BE-05, BE-07). • Verifies that each error code surfaces correctly in the UI inline banner with the appropriate message. | I19: • Must reject files with wrong extensions client-side with ERR-001-FORMAT in under 100ms • Must reject .exe files renamed to .pdf with ERR-002-FORMAT via Tika server-side validation (BE-04) • Must reject polyglot files with ERR-002-FORMAT as ambiguous • Must reject files larger than 20 MB with ERR-001-SIZE client-side and ERR-002-SIZE server-side (BE-05) • Must reject corrupted files with ERR-001-CORRUPT (BE-07) • Must reject zero-byte files with an appropriate error code | J19: QA / Both Devs | K19: FR-001 / BE-07, BE-04, BE-05, BE-06, FE-01, FE-02, INT-01 | L19: 3 | M19: 1 | N19: =MAX(ROUND(M19*1.2/0.25,0)*0.25,0.25) -> 1.25 | O19: Playwright AI — generate negative test scripts for all ERR-001-* codes Postman AI — generate error scenario collection Claude — generate edge case matrix | P19: Playwright · Cypress · Postman / REST Assured · JUnit 5 · GitHub Actions CI | Q19: WRITE (session) | R19: Redis (session only) | S19: session.checkpoint_data [in-memory pool] | T19: No test_case / test_step write. File bytes + parsed TCs held in session only. Pool is client-side state. | U19: ENDPOINT UNDER TEST: POST /api/v1/sessions/{session_id}/upload Focus: all error scenarios. Verify: each error code returned correctly, FE displays correct inline message per code, no raw 500s surface to UI.
A20: 2 | B20: Extract the requirement ,structure & loading to CLAP session | C20: FR-002 | D20: Design & Author | E20: Drop file or click | F20: BE-01 | G20: Builds the structured prompt template that wraps the extracted requirement content before it is sent to CLAP, ensuring consistent formatting across all generation requests. | H20: • Builds the structured prompt template that wraps extracted requirement content before sending to CLAP. • Loads and renders admin-configurable templates stored in the system configuration. • Injects template variables including {requirements}, {format}, and {examples} to ensure consistent formatting across all generation requests. | I20: • Must render the prompt template with all 3 required variables: {requirements}, {format}, and {examples} • Must load admin-configurable templates from system configuration without requiring a restart • Must raise a clear configuration error at startup if any template variable is undefined | J20: Backend Dev | L20: 3 | M20: 0.75 | N20: =MAX(ROUND(M20*1.2/0.25,0)*0.25,0.25) -> 1 | O20: GitHub Copilot — generate template engine + variable resolver Claude — template variable validation design | P20: Mustache / Thymeleaf · Spring Boot · AWS SSM | Q20: READ (session) | R20: Redis (session only) | S20: session.checkpoint_data [in-memory file context] | T20: Reads: requirements context from session. Builds structured CLAP prompt. No DB write — internal step in the generation pipeline. | U20: INTERNAL — prompt template engine. Builds structured CLAP prompt from: requirements context + BDD spec + config. Template stored in: /resources/prompts/ tc_generation.mustache Not a standalone HTTP endpoint. Called by: FR-003 BE-07 (Gateway Orchestrator).
A21: 2 | B21: Extract the requirement ,structure & loading to CLAP session | C21: FR-002 | D21: Design & Author | E21: Drop file or click | F21: BE-02 | G21: Constructs the BDD output format specification that CLAP uses as its target structure when generating test cases (Feature / Scenario / Given / When / Then). | H21: • Constructs the BDD output format specification that CLAP uses as its target structure when generating test cases. • Builds the {format} variable containing the Gherkin field specification including Feature, Scenario, Given, When, Then, and And. • Ensures the LLM receives a clear schema definition to guide structured test case generation. | I21: • Must include the format specification in every generated prompt • Must match the 9-field Gherkin schema defined in FR-004 (Feature, Scenario, Given, When, Then, And) • Must version the format specification alongside the schema | J21: Backend Dev | K21: FR-002 / BE-01 | L21: 2 | M21: 0.5 | N21: =MAX(ROUND(M21*1.2/0.25,0)*0.25,0.25) -> 0.5 | O21: GitHub Copilot — generate format spec builder from schema | P21: Spring Boot · Java Constants / Enum | Q21: READ (session) | R21: Redis (session only) | S21: session.checkpoint_data [in-memory file context] | T21: Reads: requirements context from session. Builds structured CLAP prompt. No DB write — internal step in the generation pipeline. | U21: INTERNAL — BDD format spec builder. Appends BDD format instructions to prompt: Given/When/Then structure, field names, output JSON schema. Not a standalone HTTP endpoint.
A22: 2 | B22: Extract the requirement ,structure & loading to CLAP session | C22: FR-002 | D22: Design & Author | E22: Drop file or click | F22: BE-03 | G22: Extracts and injects the requirement document content into the session context, making it available to CLAP for test case generation. | H22: • Extracts requirement document content and injects it into the session context for CLAP to use during test case generation. • The uploaded requirements content is inserted into the {requirements} prompt variable. • Truncates content gracefully to stay within the model token limit while preserving requirement integrity. | I22: • Must inject the full requirement document content into the {requirements} variable if within token limit • Must gracefully truncate content using the most relevant sections when the token limit is exceeded • Must log all truncation events for audit purposes | J22: Backend Dev | K22: FR-002 / BE-01 | L22: 4 | M22: 1 | N22: =MAX(ROUND(M22*1.2/0.25,0)*0.25,0.25) -> 1.25 | O22: GitHub Copilot — generate context injector + truncation logic Claude — truncation strategy design | P22: Spring AI (token counting) · Apache Commons Text · Spring Boot | Q22: READ (session) | R22: Redis (session only) | S22: session.checkpoint_data [in-memory file context] | T22: Reads: requirements context from session. Builds structured CLAP prompt. No DB write — internal step in the generation pipeline. | U22: INTERNAL — requirements context injector. Reads parsed file content from session Redis key ice:session:{id}:upload Injects into prompt template. Not a standalone HTTP endpoint.
A23: 2 | B23: Extract the requirement ,structure & loading to CLAP session | C23: FR-002 | D23: Design & Author | E23: Drop file or click | F23: BE-04 | G23: Logs every prompt sent to CLAP including the session ID, timestamp, and token count, providing an audit trail for traceability and debugging. | H23: • Logs every prompt sent to CLAP including sessionId, timestamp, templateVersion, and tokenCount for audit and traceability. • Sensitive information such as secrets is excluded from the logged prompt content. • Provides a complete audit trail for debugging and compliance purposes. | I23: • Must log every prompt sent to CLAP with 4 required fields: sessionId, timestamp, templateVersion, and tokenCount • Must exclude all sensitive information including api_key and PII from logged prompt content • Must make all prompt logs queryable by sessionId | J23: Backend Dev | K23: FR-002 / BE-01,BE-03,BE-02 | L23: 2 | M23: 0.5 | N23: =MAX(ROUND(M23*1.2/0.25,0)*0.25,0.25) -> 0.5 | O23: GitHub Copilot — generate audit logger + PII redactor | P23: Spring Boot · Logback / SLF4J · Elasticsearch / CloudWatch | Q23: READ (session) | R23: Redis (session only) | S23: session.checkpoint_data [in-memory file context] | T23: Reads: requirements context from session. Builds structured CLAP prompt. No DB write — internal step in the generation pipeline. | U23: ENDPOINT YOU CREATE: GET /api/v1/sessions/{session_id}/prompt-log Response 200: {session_id, prompt_version, prompt_hash, template_used, injected_at, token_count} Admin/debug use only. 403 for non-admin users. Used by: FR-004 INT-01 for audit verification. | V23: → FR-003 BE-06 session.builtPrompt[sessionId] = { promptText, tokenCount, templateVersion, requirementsHash, formatSpec } FR-003 BE-06 reads promptText and dispatches to LLM.
A24: 2 | B24: Extract the requirement ,structure & loading to CLAP session | C24: FR-002 | D24: Design & Author | E24: Drop file or click | F24: INT-01 | G24: Validates the full prompt construction pipeline: file uploaded, content extracted, prompt built, and CLAP receives well-formed input with correct BDD spec. | H24: • Validates the full prompt construction pipeline from file upload through content extraction to final prompt delivery to CLAP. • Verifies the prompt contains all 3 required variables: {requirements}, {format}, and {examples}. • Confirms the well-formed prompt with correct BDD format specification is successfully sent to the LLM gateway. | I24: • Must validate that the constructed prompt includes all 3 required variables: {requirements}, {format}, and {examples} • Must ensure the final prompt token count is within the model's token limit • Must create an audit log entry for each prompt generation event | J24: QA / Both Devs | K24: FR-002 / All BE | L24: 3 | M24: 0.75 | N24: =MAX(ROUND(M24*1.2/0.25,0)*0.25,0.25) -> 1 | O24: Playwright AI — generate E2E prompt validation tests Claude — generate audit log verification scenarios | P24: Playwright · WireMock · GitHub Actions CI | Q24: READ (session) | R24: Redis (session only) | S24: session.checkpoint_data [in-memory file context] | T24: Reads: requirements context from session. Builds structured CLAP prompt. No DB write — internal step in the generation pipeline. | U24: ENDPOINT UNDER TEST: GET /api/v1/sessions/{session_id}/prompt-log Test: after generate call, verify prompt log populated with correct template + token count. Test: requirements context present in log.
A25: 3 | B25: ICE sends prompt to CLAP | C25: FR-003 | D25: Design & Author | E25: Generate & Add to Pool | F25: BE-01 | G25: Defines the LLM provider configuration schema including provider name, model, API key, and temperature, stored per tenant in the ICE database. | H25: • Defines the LLM provider configuration schema including provider name, model, api_key_ref, and timeout parameters. • Stored per tenant in the ICE database with API keys referenced from secret manager. • The runtime configuration is retrieved and applied when constructing LLM API requests. | I25: • Must load the LLM provider configuration with 4 required fields: provider name, model, api_key_ref, and timeout • Must resolve api_key from the secret manager and never log it in plain text • Must raise a clear configuration error on startup if the provider name is invalid | J25: Backend Dev | L25: 3 | M25: 1 | N25: =MAX(ROUND(M25*1.2/0.25,0)*0.25,0.25) -> 1.25 | O25: GitHub Copilot — generate config schema + secret resolver Claude — secret manager integration design | P25: Spring Boot · AWS SSM / Secrets Manager · application.yml | Q25: WRITE (session) | R25: Redis (session only) | S25: session.checkpoint_data [in-memory pool] | T25: Reads: session file context. Calls CLAP (Claude API). Writes generated TC list to in-memory pool. No test_case write. | U25: INTERNAL CONFIG — LLM provider settings. Stored in: tenant.llm_config JSONB Fields: provider (claude|gpt4o|gemini), model_version, max_tokens, temperature Exposed via FR-003 BE-06 Config Admin API.
A26: 3 | B26: ICE sends prompt to CLAP | C26: FR-003 | D26: Design & Author | E26: Generate & Add to Pool | F26: BE-02 | G26: Resolves the active LLM provider for the current tenant and constructs the provider-specific API request before sending to CLAP. | H26: • Resolves the active LLM provider configuration for the current tenant and constructs provider-specific API requests. • Retrieves the api_key_ref from AWS Secrets Manager at runtime when making CLAP calls. • Auto-refreshes API keys within 60 seconds of rotation in the secret manager. | I26: • Must resolve the active LLM provider configuration for the current tenant from tenant settings • Must retrieve the api_key_ref from AWS Secrets Manager at runtime when making CLAP calls • Must reflect API key rotation within 60 seconds of change without service restart • Must never log or persist API keys in logs or database tables • Must return a provider-specific API request payload ready for transmission | J26: Backend Dev | L26: 4 | M26: 1.5 | N26: =MAX(ROUND(M26*1.2/0.25,0)*0.25,0.25) -> 1.75 | O26: GitHub Copilot — generate Secrets Manager client + cache Claude — rotation/TTL design | P26: AWS Secrets Manager / HashiCorp Vault · Spring Boot · Caffeine Cache | Q26: WRITE (session) | R26: Redis (session only) | S26: session.checkpoint_data [in-memory pool] | T26: Reads: session file context. Calls CLAP (Claude API). Writes generated TC list to in-memory pool. No test_case write. | U26: INTERNAL — Secret Manager integration. API keys stored encrypted in AWS SSM or Vault. Retrieved at runtime via SecretManagerService. Never stored in DB plain-text. Not an HTTP endpoint. Called by: FR-003 BE-07 Gateway Orchestrator.
A27: 3 | B27: ICE sends prompt to CLAP | C27: FR-003 | D27: Design & Author | E27: Generate & Add to Pool | F27: BE-03 | G27: Manages the streaming connection between ICE and the CLAP LLM, handling token streaming, timeouts, and connection errors. | H27: • Manages the streaming connection between ICE and the CLAP LLM including token streaming, timeouts, and connection errors. • Defines the ChatClient interface via Spring AI as the abstraction layer for all LLM provider calls. • All provider interactions are routed through this unified interface for consistency. | I27: • Must support streaming connections with GPT-4o, Claude, and Gemini adapters via the ChatClient interface • Must allow provider swap via configuration change without code modification • Must normalize all provider responses to a standard schema regardless of source provider • Must handle token streaming, connection timeouts, and connection errors during the LLM call • Must surface connection errors with clear error codes when the stream is interrupted or fails | J27: Backend Dev | L27: 4 | M27: 1.5 | N27: =MAX(ROUND(M27*1.2/0.25,0)*0.25,0.25) -> 1.75 | O27: GitHub Copilot — generate adapter stubs for each provider Claude — interface contract design | P27: Spring AI · ChatClient · Java Interface · Spring Boot | Q27: WRITE (session) | R27: Redis (session only) | S27: session.checkpoint_data [in-memory pool] | T27: Reads: session file context. Calls CLAP (Claude API). Writes generated TC list to in-memory pool. No test_case write. | U27: INTERNAL — ILLMProvider adapter interface. Interface: {generate(prompt): LLMResponse} Implementations: ClaudeProvider, GPT4oProvider, GeminiProvider. Selected at runtime based on tenant.llm_config. Not an HTTP endpoint.
A28: 3 | B28: ICE sends prompt to CLAP | C28: FR-003 | D28: Design & Author | E28: Generate & Add to Pool | F28: BE-04 | G28: Implements retry logic for transient CLAP API failures, with configurable back-off and a maximum retry count before surfacing an error to the user. | H28: • Implements retry logic for transient CLAP API failures with configurable back-off and maximum retry count. • Defines error codes ERR-003-TIMEOUT, ERR-003-RATE_LIMIT, ERR-003-PROVIDER_ERROR, and ERR-003-EMPTY_RESPONSE for specific failure scenarios. • Surfaces a clear error to the user after exhausting all retry attempts. | I28: • Must retry transient CLAP API failures using configurable exponential back-off • Must enforce a maximum retry count before surfacing failure to the caller • Must return ERR-003-TIMEOUT for timeout failures, ERR-003-RATE_LIMIT for rate limit errors, ERR-003-PROVIDER_ERROR for provider failures, and ERR-003-EMPTY_RESPONSE for empty responses • Must structure all errors as { code, message, detail } without exposing raw LLM error messages to the UI • Must log each retry attempt with error code and retry count for diagnostics | J28: Backend Dev | L28: 2 | M28: 0.5 | N28: =MAX(ROUND(M28*1.2/0.25,0)*0.25,0.25) -> 0.5 | O28: GitHub Copilot — generate error registry + exception handler Claude — error taxonomy design | P28: Spring Boot @ControllerAdvice · Java Enum · OpenAPI 3.0 | Q28: WRITE (session) | R28: Redis (session only) | S28: session.checkpoint_data [in-memory pool] | T28: Reads: session file context. Calls CLAP (Claude API). Writes generated TC list to in-memory pool. No test_case write. | U28: INTERNAL — error code registry for LLM failures. Codes: ERR-003-TIMEOUT, ERR-003-PROVIDER_DOWN, ERR-003-TOKEN_LIMIT, ERR-003-INVALID_RESPONSE Returned inside Generate API response body.
A29: 3 | B29: ICE sends prompt to CLAP | C29: FR-003 | D29: Design & Author | E29: Generate & Add to Pool | F29: BE-05 | G29: Enforces token limits per request to prevent runaway generation costs, truncating the prompt context if necessary while preserving requirement fidelity. | H29: • Enforces token limits per request to prevent runaway generation costs and manage LLM usage. • Normalizes prompts to a standard schema before sending to the LLM using admin-configurable templates. • Truncates prompt context if necessary while preserving requirement fidelity and staying within token budget. | I29: • Must enforce a per-request token limit to prevent runaway generation costs • Must build prompts from requirements + BDD format spec + admin-configurable template • Must allow template changes via configuration without requiring deployment • Must truncate prompt context if necessary while preserving essential requirement data • Must log the final prompt (excluding secrets) for audit purposes | J29: Backend Dev | K29: FR-003 / BE-01 | L29: 5 | M29: 1.5 | N29: =MAX(ROUND(M29*1.2/0.25,0)*0.25,0.25) -> 1.75 | O29: GitHub Copilot — generate prompt builder + template engine Claude — template variable validation | P29: Spring AI · Mustache / Thymeleaf · Spring Boot | Q29: WRITE (session) | R29: Redis (session only) | S29: session.checkpoint_data [in-memory pool] | T29: Reads: session file context. Calls CLAP (Claude API). Writes generated TC list to in-memory pool. No test_case write. | U29: INTERNAL — prompt normalisation layer. Strips PII, truncates to token limit, adds BDD format spec header. Called by: FR-002 BE-02 Requirements Context Injector before sending to CLAP. Not an HTTP endpoint.
A30: 3 | B30: ICE sends prompt to CLAP | C30: FR-003 | D30: Design & Author | E30: Generate & Add to Pool | F30: BE-06 | G30: Tracks CLAP API usage metrics per tenant (tokens consumed, latency, error rate) for billing and performance monitoring. | H30: • Tracks CLAP API usage metrics per tenant including tokens consumed, latency, and error rate for billing and performance monitoring. • Exposes a REST endpoint for admins to read and update LLM provider configuration at runtime. • Configuration changes take effect immediately without requiring system restart. | I30: • Must track tokens consumed, latency, and error rate per tenant for billing and performance monitoring • Must expose GET endpoint that returns current provider and model without exposing the API key • Must allow admin PATCH to update provider configuration and apply changes on the next CLAP call • Must return HTTP 403 for non-admin users attempting to read or update LLM configuration • Must apply configuration changes without service restart | J30: Backend Dev | K30: FR-003 / BE-01,BE-02 | L30: 3 | M30: 1 | N30: =MAX(ROUND(M30*1.2/0.25,0)*0.25,0.25) -> 1.25 | O30: GitHub Copilot — generate admin REST controller + auth guard | P30: Spring Boot · Spring Security · OpenAPI 3.0 | Q30: WRITE (session) | R30: Redis (session only) | S30: session.checkpoint_data [in-memory pool] | T30: Reads: session file context. Calls CLAP (Claude API). Writes generated TC list to in-memory pool. No test_case write. | U30: ENDPOINT YOU CREATE: GET /api/v1/admin/llm-config PUT /api/v1/admin/llm-config Request (PUT): {provider, model_version, max_tokens, temperature} Response 200: {provider, model_version, status: active|fallback} Errors: 400 invalid provider, 403 not admin
A31: 3 | B31: ICE sends prompt to CLAP | C31: FR-003 | D31: Design & Author | E31: Generate & Add to Pool | F31: BE-07 | G31: Validates the CLAP API key and provider connectivity at session start, surfacing a clear error before the user attempts generation. | H31: • Validates the CLAP API key and provider connectivity at session start before the user attempts generation. • Exposes the /health/llm endpoint to check LLM provider health status. • Automatically falls back to the secondary provider if the primary provider is unhealthy. | I31: • Must validate CLAP API key and provider connectivity at session start before generation is attempted • Must expose /health/llm endpoint returning { provider, status, latencyMs } • Must automatically fall back to the secondary provider if the primary provider is unhealthy • Must log fallback events with timestamp, primary provider status, and secondary provider used • Must surface a clear error message if both primary and secondary providers are unavailable | J31: Backend Dev | K31: FR-003 / BE-08 | L31: 4 | M31: 1.5 | N31: =MAX(ROUND(M31*1.2/0.25,0)*0.25,0.25) -> 1.75 | O31: GitHub Copilot — generate health check + fallback logic | P31: Spring Boot Actuator · Spring AI · Micrometer | Q31: WRITE (session) | R31: Redis (session only) | S31: session.checkpoint_data [in-memory pool] | T31: Reads: session file context. Calls CLAP (Claude API). Writes generated TC list to in-memory pool. No test_case write. | U31: INTERNAL — health check + provider fallback. GET /api/v1/internal/llm/health (internal only) Response: {provider, status: ok|degraded|down} On primary provider down: falls back to secondary provider if configured.
A32: 3 | B32: ICE sends prompt to CLAP | C32: FR-003 | D32: Design & Author | E32: Generate & Add to Pool | F32: BE-08 | G32: Caches repeated identical prompts within a session to avoid redundant CLAP calls when the user regenerates without changing the requirements. | H32: • Caches identical prompts within a session to avoid redundant CLAP calls when users regenerate without changing requirements. • Orchestrates the workflow by receiving the prompt, routing to the provider, receiving the response, normalizing it, and returning the result. • Retries failed requests up to 3 times before surfacing an error. | I32: • Must cache identical prompts within a session to avoid redundant CLAP calls on regeneration without requirement changes • Must orchestrate the workflow by receiving the prompt, routing to the provider, normalizing the response, and returning it • Must return a normalized response containing content, tokenUsage, modelUsed, and latencyMs for valid prompts • Must retry provider timeouts up to 3 times before returning ERR-003-TIMEOUT • Must return cached response immediately if the prompt matches a prior request in the same session | J32: Backend Dev | K32: FR-002 / BE-04 FR-003 / BE-01, FR-014 BE-01, FR-014 BE-02, FR-015 BE-01, BE-05 | L32: 3 | M32: 1 | N32: =MAX(ROUND(M32*1.2/0.25,0)*0.25,0.25) -> 1.25 | O32: GitHub Copilot — generate orchestrator + retry logic Claude — partial response detection | P32: Spring AI · Spring Retry · Jackson · Spring Boot | Q32: WRITE (session) | R32: Redis (session only) | S32: session.checkpoint_data [in-memory pool] | T32: Reads: session file context. Calls CLAP (Claude API). Writes generated TC list to in-memory pool. No test_case write. | U32: INTERNAL — Gateway Orchestrator. Coordinates: prompt build → provider call → response parse → validate → return. Called by FR-004 BE-04 Generation API Endpoint. Not a standalone HTTP endpoint. | V32: → FR-004 BE-02 LlmResponse = { content (raw JSON string), tokenUsage, modelUsed, latencyMs } FR-004 BE-02 parses content into 9-field TC objects.
A33: 3 | B33: ICE sends prompt to CLAP | C33: FR-003 | D33: Design & Author | E33: Generate & Add to Pool | F33: FE-01 | G33: Renders the Generate & Add to Pool button and manages its enabled/loading/disabled states throughout the generation lifecycle. | H33: • Renders the Generate & Add to Pool button and manages its enabled, loading, and disabled states throughout the generation lifecycle. • Displays the active LLM provider and health badge in the UI header. • Polls the /health/llm endpoint every 30 seconds to update provider status. | I33: • Must display a badge showing the active LLM provider name and green/red health status in the UI header • Must poll the /health/llm endpoint every 30 seconds to refresh the provider health status • Must update the badge within 30 seconds of a provider change or health status change • Must not block page load while polling or updating the health badge • Must render the Generate & Add to Pool button with enabled, loading, or disabled state based on generation lifecycle | J33: Frontend Dev | L33: 2 | M33: 0.5 | N33: =MAX(ROUND(M33*1.2/0.25,0)*0.25,0.25) -> 0.5 | O33: v0.dev — generate status badge component GitHub Copilot — polling hook | P33: React · TypeScript · Tailwind CSS · React Query | Q33: WRITE (session) | R33: Redis (session only) | S33: session.checkpoint_data [in-memory pool] | T33: Reads: session file context. Calls CLAP (Claude API). Writes generated TC list to in-memory pool. No test_case write. | U33: ENDPOINT YOU CALL: GET /api/v1/admin/llm-config (defined in FR-003 BE-06) Show provider name + status badge on Design & Author screen header. Green badge = active, amber = fallback, red = down.
A34: 3 | B34: ICE sends prompt to CLAP | C34: FR-003 | D34: Design & Author | E34: Generate & Add to Pool | F34: FE-02 | G34: Displays a generation progress indicator (spinner and status message) while the CLAP request is in flight, preventing duplicate submissions. | H34: • Displays a generation progress indicator with spinner and status message while the CLAP request is in flight. • Prevents duplicate submissions by disabling the button during active requests. • Surfaces ERR-003-* errors as user-friendly inline messages with a retry button for transient failures. | I34: • Must display a spinner and status message while the CLAP request is in flight • Must disable the Generate & Add to Pool button during active requests to prevent duplicate submissions • Must map each ERR-003-* error code to a plain-English user-friendly inline message • Must display a retry button for ERR-003-TIMEOUT and ERR-003-RATE_LIMIT errors • Must clear the error message on successful retry or new generation attempt | J34: Frontend Dev | K34: FR-003 / FE-01 | L34: 3 | M34: 1 | N34: =MAX(ROUND(M34*1.2/0.25,0)*0.25,0.25) -> 1.25 | O34: v0.dev — generate error message component GitHub Copilot — error code ↔ message mapping | P34: React · TypeScript · Tailwind CSS | Q34: WRITE (session) | R34: Redis (session only) | S34: session.checkpoint_data [in-memory pool] | T34: Reads: session file context. Calls CLAP (Claude API). Writes generated TC list to in-memory pool. No test_case write. | U34: ENDPOINT YOU CALL: GET /api/v1/admin/llm-config (defined in FR-003 BE-06) When status=down or error received from FR-004 BE-04, show user-facing error message with error code and retry suggestion.
A35: 3 | B35: ICE sends prompt to CLAP | C35: FR-003 | D35: Design & Author | E35: Generate & Add to Pool | F35: INT-01 | G35: Validates the end-to-end prompt send flow: button clicked, prompt constructed, sent to CLAP, response received, and test cases returned to FR-004. | H35: • Validates the end-to-end prompt send flow from button click through prompt construction, CLAP submission, response receipt, and test case delivery to FR-004. • Tests provider switching via the admin API to verify configuration changes take effect. • Verifies that the next generation request uses the newly configured provider. | I35: • Must validate the end-to-end flow from button click through prompt construction, CLAP submission, response receipt, and test case delivery to FR-004 • Must verify that switching the provider via admin API causes the next generation to use the new model • Must update the health badge within 30 seconds of the provider switch • Must complete provider switch without service downtime or user-visible interruption • Must confirm the new provider is used for all subsequent CLAP calls after the switch | J35: QA / Both Devs | K35: FR-003 / All BE + FE | L35: 4 | M35: 1.5 | N35: =MAX(ROUND(M35*1.2/0.25,0)*0.25,0.25) -> 1.75 | O35: Playwright AI — generate E2E switching tests Postman AI — generate admin API test collection | P35: Playwright · Postman · GitHub Actions CI | Q35: WRITE (session) | R35: Redis (session only) | S35: session.checkpoint_data [in-memory pool] | T35: Reads: session file context. Calls CLAP (Claude API). Writes generated TC list to in-memory pool. No test_case write. | U35: ENDPOINT UNDER TEST: GET/PUT /api/v1/admin/llm-config Test: switch provider → verify generation uses new provider. Test: primary down → verify fallback activates.
A36: 3 | B36: ICE sends prompt to CLAP | C36: FR-003 | D36: Design & Author | E36: Generate & Add to Pool | F36: INT-02 | G36: Validates error handling: CLAP timeout, invalid API key, and provider unavailability all surface the correct user-facing error messages. | H36: • Validates error handling for CLAP timeout, invalid API key, and provider unavailability scenarios. • Simulates all ERR-003-* conditions end-to-end including timeout, rate limit, empty response, and provider down. • Confirms that each error condition surfaces the correct user-facing error message. | I36: • Must surface the correct ERR-003-* error code in the UI for CLAP timeout, invalid API key, and provider unavailability scenarios • Must simulate and validate ERR-003-TIMEOUT, ERR-003-RATE_LIMIT, ERR-003-EMPTY_RESPONSE, and ERR-003-PROVIDER_ERROR end-to-end • Must allow retry for transient errors (timeout, rate limit) and succeed after the condition clears • Must activate fallback to secondary provider when the primary provider is down • Must log each error condition with error code, provider, and timestamp for diagnostics | J36: QA / Both Devs | K36: FR-003 / INT-01 | L36: 3 | M36: 1 | N36: =MAX(ROUND(M36*1.2/0.25,0)*0.25,0.25) -> 1.25 | O36: Playwright AI — generate error scenario scripts Claude — generate edge case matrix | P36: Playwright · WireMock · JUnit 5 | Q36: WRITE (session) | R36: Redis (session only) | S36: session.checkpoint_data [in-memory pool] | T36: Reads: session file context. Calls CLAP (Claude API). Writes generated TC list to in-memory pool. No test_case write. | U36: ENDPOINT UNDER TEST: POST /api/v1/sessions/{id}/generate (defined in FR-004 BE-04) Test: simulate LLM timeout → ERR-003-TIMEOUT. Test: provider returns malformed JSON → ERR-003-INVALID_RESPONSE surfaced in UI.
A37: 4 | B37: CLAP processes requirements, generates test cases and returns structured JSON response | C37: FR-004 | D37: Design & Author | E37: Generate & Add to Pool | F37: BE-01 | G37: CLAP receives the structured prompt and processes the requirements from session context, generating BDD-format test cases for each identified requirement. | H37: • CLAP receives the structured prompt from FR-003 and processes parsed requirements held in session context. • Generates BDD-format test cases with Feature, Scenario, Given, When, and Then structure for each identified requirement. • Returns a structured JSON array of test cases to ICE for downstream validation in FR-005 without user interaction. | I37: • Must receive the structured prompt from FR-003 and process parsed requirements held in session context • Must generate BDD-format test cases with Feature, Scenario, Given, When, and Then structure for each identified requirement • Must return a structured response containing exactly 10 fields: Description, Test Step, Expected Result, Test Type, Priority, and 5 others as defined in the schema • Must reject responses missing mandatory fields (Description, Test Step, Expected Result) with a validation error specifying the missing field name • Must accept only valid Test Type values (Functional, Regression, Performance, Accessibility, Responsiveness) and Priority values (High, Medium, Low) • Must version the response schema in the OpenAPI spec for traceability | J37: Backend Dev | L37: 2 | M37: 0.5 | N37: =MAX(ROUND(M37*1.2/0.25,0)*0.25,0.25) -> 0.5 | O37: GitHub Copilot — generate schema class + validator Claude — 9-field schema design | P37: Spring Boot · Java Record · OpenAPI 3.0 · Jackson | Q37: WRITE (session) | R37: Redis (session only) | S37: session.checkpoint_data [in-memory pool] | T37: INTERNAL — TC schema definition. 10 fields: Test Case Id, Prerequisites, Test Case Description, Test Step ID, Test Step, Expected Result, Test Type, Priority, Criticality, Functionality. Defined as Java Record + Jackson. Used by: BE-02 (parser), BE-03 (validator). | U37: INTERNAL — TC schema definition. 9-field schema enforced on all generated TCs: tc_id, feature, scenario, given, when, then, priority, tags, notes Defined as Java class + Jackson schema. Used by: BE-02 (parser), BE-03 (validator).
A38: 4 | B38: CLAP processes requirements, generates test cases and returns structured JSON response | C38: FR-004 | D38: Design & Author | E38: Generate & Add to Pool | F38: BE-02 | G38: Parses the raw CLAP response and extracts the structured test case array, validating that each item conforms to the expected JSON schema before passing to FR-005. | H38: • Parses raw LLM output into structured 10-field TC objects and validates each item against the expected JSON schema. • Auto-generates Test Case Id as TC-{sessionId}-{seq} and splits multi-step test cases into individual step rows under the same TC-ID. • Handles partial or malformed output gracefully before passing structured data downstream. | I38: • Must parse valid LLM output into a list of 10-field TestCase objects conforming to the expected JSON schema • Must auto-generate Test Case Id as TC-{sessionId}-{seq} if the LLM omits it • Must split multi-step test cases into individual step rows under the same TC-ID • Must flag malformed fields with ERR-004-INVALID-FIELD without rejecting the entire batch • Must return ERR-004-EMPTY-RESPONSE when the LLM output is empty • Must allow partially valid batches to proceed with flagged items included | J38: Backend Dev | K38: FR-004 / BE-01 | L38: 4 | M38: 1 | N38: =MAX(ROUND(M38*1.2/0.25,0)*0.25,0.25) -> 1.25 | O38: GitHub Copilot — generate parser + markdown stripper Claude — malformed output handling strategy | P38: Jackson · Spring Boot · regex (fence stripper) | Q38: WRITE (session) | R38: Redis (session only) | S38: session.checkpoint_data [in-memory pool] | T38: Validates CLAP output against 9-field BDD schema. Writes validated TC rows to pool. Flagged rows shown in UI. No DB write. | U38: INTERNAL — LLM response parser. Parses CLAP JSON output into 9-field TC objects. On parse failure: flags TC with ERR-004-PARSE. Called by: FR-004 BE-05 (Generation API). Not a standalone HTTP endpoint.
A39: 4 | B39: CLAP processes requirements, generates test cases and returns structured JSON response | C39: FR-004 | D39: Design & Author | E39: Generate & Add to Pool | F39: BE-03 | G39: Handles partial CLAP responses where generation was interrupted, returning whatever test cases were generated along with a partial-completion flag. | H39: • Handles partial CLAP responses where generation was interrupted by returning whatever test cases were successfully generated. • Returns a partial-completion flag alongside the available test cases. • Allows the system to surface partial results rather than treating interruption as a complete failure. | I39: • Must return whatever test cases were successfully generated when CLAP generation is interrupted • Must include a partial-completion flag alongside the available test cases • Must return ERR-005-MISSING-DESCRIPTION when Test Case Description is missing • Must return ERR-005-MISSING-STEP when Test Step is missing • Must return ERR-005-MISSING-EXPECTED-RESULT when Expected Result is missing • Must return ERR-005-INVALID-TEST-TYPE for invalid Test Type values • Must pass valid cases through unchanged and return validation summary with flaggedCount | J39: Backend Dev | K39: FR-004 / BE-02 | L39: 3 | M39: 0.75 | N39: =MAX(ROUND(M39*1.2/0.25,0)*0.25,0.25) -> 1 | O39: GitHub Copilot — generate validator + reason code registry | P39: Spring Boot · Java Bean Validation · OpenAPI 3.0 | Q39: WRITE (session) | R39: Redis (session only) | S39: session.checkpoint_data [in-memory pool] | T39: INTERNAL — TC field validator after parsing. Mandatory fields: description, test_step, expected_result. On failure: TC flagged (not rejected). Not a standalone HTTP endpoint. | U39: INTERNAL — TC validator after parsing. Checks: all 9 fields present and non-empty, BDD keywords correct (Given/When/Then). On failure: TC flagged (not rejected) — shown with warning in FR-005 FE-01. Not a standalone HTTP endpoint.
A40: 4 | B40: CLAP processes requirements, generates test cases and returns structured JSON response | C40: FR-004 | D40: Design & Author | E40: Generate & Add to Pool | F40: BE-04 | G40: Maps CLAP-generated test case fields to the ICE 9-field TC schema, ensuring all mandatory fields are populated from the generation output. | H40: • Validates each parsed test case for field completeness, checking that all mandatory fields are present. • Requires Test Case Description, Test Step, and Expected Result as mandatory fields. • Flags incomplete test cases inline without blocking the entire generation batch. | I40: • Must validate each parsed test case for presence of all mandatory fields • Must fire a nudge retry automatically when a mandatory field is missing • Must specify exactly which fields are missing in the nudge prompt • Must allow a maximum of 2 nudge retries before surfacing ERR-004-MAX-RETRIES • Must include retry count in response metadata • Must produce clean 10-field TCs on successful retry | J40: Backend Dev | K40: FR-004 / BE-02,BE-03 | L40: 4 | M40: 1 | N40: =MAX(ROUND(M40*1.2/0.25,0)*0.25,0.25) -> 1.25 | O40: GitHub Copilot — generate retry orchestrator Claude — nudge prompt design + retry cap logic | P40: Spring Retry · Spring AI · Spring Boot | Q40: WRITE (session) | R40: Redis (session only) | S40: session.checkpoint_data [in-memory pool] | T40: INTERNAL — nudge retry. Nudge: "Please include Test Case Description, Test Step, and Expected Result for each TC." Max 2 retries. Called by: FR-004 BE-05. Not a standalone HTTP endpoint. | U40: INTERNAL — nudge retry logic. If CLAP returns < expected TC count: re-sends prompt with 'generate N more' nudge. Max 2 retries. Not a standalone HTTP endpoint. Called by: FR-004 BE-05.
A41: 4 | B41: CLAP processes requirements, generates test cases and returns structured JSON response | C41: FR-004 | D41: Design & Author | E41: Generate & Add to Pool | F41: BE-05 | G41: Stores the raw CLAP generation output in the session checkpoint so the result can be replayed or audited without re-calling CLAP. | H41: • CLAP receives the structured prompt from FR-003 and processes parsed requirements held in session context. • Generates BDD-format test cases with Feature, Scenario, Given, When, and Then structure for each identified requirement. • Returns a structured JSON array of test cases to ICE for downstream validation in FR-005 without user interaction. | I41: • Must return test cases when a valid sessionFileId is provided • Must return 400 with ERR-004-NO-FILE when sessionFileId is invalid or missing • Must include testCases[], validationSummary, modelUsed, and latencyMs in the response • Must process parsed requirements held in session context • Must generate BDD-format test cases with Feature, Scenario, Given, When, and Then structure | J41: Backend Dev | K41: FR-004 / BE-01,BE-02,BE-03,BE-04 | L41: 5 | M41: 1.5 | N41: =MAX(ROUND(M41*1.2/0.25,0)*0.25,0.25) -> 1.75 | O41: GitHub Copilot — generate REST controller + orchestration chain Postman AI — generate API test collection | P41: Spring Boot · Spring MVC · OpenAPI 3.0 · JUnit 5 + Mockito | Q41: WRITE (session) | R41: Redis (session only) | S41: session.checkpoint_data [in-memory pool] | T41: ENDPOINT YOU CREATE: POST /api/v1/sessions/{session_id}/generate Response 200 (SSE stream): event: tc_generated data: {tc_id, prerequisites, description, step_id, test_step, expected_result, test_type, priority, criticality, functionality, flagged, flag_reason?} event: generation_complete data: {total_generated, flagged_count} Errors: 400 no file, 503 PROVIDER_DOWN | U41: ENDPOINT YOU CREATE: POST /api/v1/sessions/{session_id}/generate Request: {model_override? (optional)} Response 200 (streamed SSE): event: tc_generated data: {tc_id, feature, scenario, given, when, then, priority, tags, notes, flagged: bool, flag_reason?} event: generation_complete data: {total_generated, flagged_count} Errors: 400 no file in session, 503 ERR-003-PROVIDER_DOWN | V41: → FR-005 BE-01 session.tcPool[sessionId] = [ { tcId, feature, scenario, given, when, then, linkedReq, status, priority } ] FR-005 BE-01 reads each TC and validates Gherkin structure.
A42: 4 | B42: CLAP processes requirements, generates test cases and returns structured JSON response | C42: FR-004 | D42: Design & Author | E42: Generate & Add to Pool | F42: FE-01 | G42: Renders the generated test cases in the TC pool table as they stream in from CLAP, updating the row count and table content in real time. | H42: • Wires the Generate button to POST /api/v1/generate and manages button state during the request. • Shows a loading spinner and disables the button while the generation call is in progress. • Prevents duplicate submissions by enforcing single-request-at-a-time behavior. | I42: • Must fire exactly one POST to /api/v1/generate when the Generate button is clicked • Must display a loading spinner while the generation call is in progress • Must disable the Generate button until the response is received • Must prevent duplicate submissions by enforcing single-request-in-flight logic | J42: Frontend Dev | L42: 3 | M42: 0.75 | N42: =MAX(ROUND(M42*1.2/0.25,0)*0.25,0.25) -> 1 | O42: v0.dev — generate loading state UI GitHub Copilot — generate API hook + loading state | P42: React · Axios · React Query · TypeScript · Tailwind CSS | Q42: WRITE (session) | R42: Redis (session only) | S42: session.checkpoint_data [in-memory pool] | T42: Validates CLAP output against 9-field BDD schema. Writes validated TC rows to pool. Flagged rows shown in UI. No DB write. | U42: ENDPOINT YOU CALL (defined in FR-004 BE-05): POST /api/v1/sessions/{session_id}/generate Use EventSource (SSE) to stream results. On tc_generated: append TC row to pool table. While generating: show spinner on button, disable button, show 'Generating...' label. On generation_complete: re-enable button, show count toast.
A43: 4 | B43: CLAP processes requirements, generates test cases and returns structured JSON response | C43: FR-004 | D43: Design & Author | E43: Generate & Add to Pool | F43: FE-02 | G43: Displays a generation summary banner (e.g. 12 test cases generated) on completion, with a breakdown of fully generated vs partially complete TCs. | H43: • Renders generated test cases as a scrollable table with a sticky header displaying 10 columns: Test Case Id, Prerequisites, Test Case Description, Test Step ID, Test Step, Expected Result, Test Type, Priority, Criticality, and Functionality. • Visually groups multiple test steps under the same TC-ID to indicate they belong to a single test case. • Updates the table content in real time as test cases stream in from the generation process. | I43: • Must render all 10 fields per row: Test Case Id, Prerequisites, Test Case Description, Test Step ID, Test Step, Expected Result, Test Type, Priority, Criticality, and Functionality • Must display a sticky header during vertical scroll • Must enable horizontal scroll for narrow viewports • Must render correctly for 1 test case and for 200+ test cases • Must group multi-step TCs under the same TC-ID • Must show flagged TCs with an amber row background | J43: Frontend Dev | K43: FR-004 / FE-01 | L43: 4 | M43: 1 | N43: =MAX(ROUND(M43*1.2/0.25,0)*0.25,0.25) -> 1.25 | O43: v0.dev — generate chat view table component GitHub Copilot — sticky header + virtual scroll wiring | P43: React · TypeScript · Tailwind CSS · react-window | Q43: WRITE (session) | R43: Redis (session only) | S43: session.checkpoint_data [in-memory pool] | T43: ENDPOINT YOU CALL (FR-004 BE-05): POST /api/v1/sessions/{session_id}/generate Render 10-column standard TC table. Group multi-step TCs under same TC-ID. Flagged TCs: amber row (FR-005 FE-01). | U43: ENDPOINT YOU CALL (defined in FR-004 BE-05): POST /api/v1/sessions/{session_id}/generate Render TC rows in chat view table as SSE events arrive. Flagged TCs shown with amber warning row (FR-005 FE-01 handles the flag UI).
A44: 4 | B44: CLAP processes requirements, generates test cases and returns structured JSON response | C44: FR-004 | D44: Design & Author | E44: Generate & Add to Pool | F44: INT-01 | G44: Validates the full CLAP generation flow: prompt sent, BDD test cases returned, mapped to 9-field schema, and stored in session. | H44: • Validates the full CLAP generation flow from prompt submission through BDD test case generation and schema mapping. • Confirms that generated test cases are mapped to the 9-field schema and stored in session. • Tests the upload-to-render pipeline by uploading a valid file, triggering generation, and verifying test cases appear in the chat view. | I44: • Must populate all 10 standard fields per TC • Must not write any DB rows and operate on session data only • Must complete with latencyMs < 30s for a typical document • Must render multi-step TCs with grouped step rows under the same TC-ID • Must support all 4 supported file formats in the upload-to-render pipeline | J44: QA / Both Devs | K44: FR-004 / All BE + FE | L44: 4 | M44: 1 | N44: =MAX(ROUND(M44*1.2/0.25,0)*0.25,0.25) -> 1.25 | O44: Playwright AI — generate E2E generation tests Claude — generate test scenario coverage matrix | P44: Playwright · GitHub Actions CI · Docker Compose | Q44: WRITE (session) | R44: Redis (session only) | S44: session.checkpoint_data [in-memory pool] | T44: Validates CLAP output against 9-field BDD schema. Writes validated TC rows to pool. Flagged rows shown in UI. No DB write. | U44: ENDPOINT UNDER TEST: POST /api/v1/sessions/{session_id}/generate Test: valid requirements file → TCs streamed, all 9 fields populated, SSE events correct. Test: verify tc_generated events arrive in real time (not batched at end).
A45: 4 | B45: CLAP processes requirements, generates test cases and returns structured JSON response | C45: FR-004 | D45: Design & Author | E45: Generate & Add to Pool | F45: INT-02 | G45: Validates CLAP partial response handling: interrupted generation returns available TCs with a partial-completion flag rather than an error. | H45: • Validates CLAP partial response handling to ensure interrupted generation returns available test cases with a partial-completion flag. • Simulates LLM errors including empty response, invalid fields, and timeout scenarios. • Verifies that retry after nudge successfully recovers from transient failures. | I45: • Must surface each ERR-004-* error correctly for the corresponding failure scenario • Must resolve invalid field errors via nudge retry when applicable • Must stop retrying after max retries and show an error instead of looping infinitely • Must return available test cases with a partial-completion flag when generation is interrupted • Must handle empty response, invalid fields, and timeout scenarios correctly | J45: QA / Both Devs | K45: FR-004 / INT-01 | L45: 4 | M45: 1.5 | N45: =MAX(ROUND(M45*1.2/0.25,0)*0.25,0.25) -> 1.75 | O45: Playwright AI — generate retry scenario scripts WireMock — simulate LLM responses | P45: Playwright · WireMock · JUnit 5 · GitHub Actions CI | Q45: WRITE (session) | R45: Redis (session only) | S45: session.checkpoint_data [in-memory pool] | T45: Validates CLAP output against 9-field BDD schema. Writes validated TC rows to pool. Flagged rows shown in UI. No DB write. | U45: ENDPOINT UNDER TEST: POST /api/v1/sessions/{session_id}/generate Test: LLM returns partial JSON → nudge retry fires, second attempt succeeds. Test: max retries exceeded → ERR-003-TIMEOUT surfaced correctly in UI.
A46: 5 | B46: ICE validates the response — checks mandatory fields and flags incomplete TCs | C46: FR-005 | D46: Design & Author | E46: Generate & Add to Pool | F46: BE-01 | G46: Validates each generated test case against the mandatory 9-field schema, flagging any TC where a required field is missing or empty. | H46: • Validates each generated test case against the mandatory 9-field schema, checking for missing or empty required fields. • Requires Test Case Description, Test Step, and Expected Result to be present and non-empty. • Runs inside the FR-004 BE-05 pipeline and flags incomplete test cases without rejecting the entire batch. | I46: • Must return ERR-005-MISSING-DESCRIPTION when Test Case Description is missing or empty • Must return ERR-005-MISSING-STEP when Test Step is missing or empty • Must return ERR-005-MISSING-EXPECTED-RESULT when Expected Result is missing or empty • Must return ERR-005-INVALID-TEST-TYPE when Test Type value is invalid • Must treat empty strings the same as missing values • Must flag TCs inline without blocking the entire generation batch | J46: Backend Dev | L46: 3 | M46: 0.75 | N46: =MAX(ROUND(M46*1.2/0.25,0)*0.25,0.25) -> 1 | O46: GitHub Copilot — generate Gherkin validator + error registry Claude — nested step edge cases | P46: Spring Boot · Java · OpenAPI 3.0 | Q46: READ (session) | R46: Redis (session only) | S46: [in-memory pool] | T46: INTERNAL — mandatory field validator. Runs post-generation inside FR-004 BE-05. Checks: description, test_step, expected_result present and non-empty (not whitespace). ERR-005-* codes: MISSING-DESCRIPTION MISSING-STEP MISSING-EXPECTED-RESULT INVALID-TEST-TYPE Flags TC — does not reject. Not a standalone HTTP endpoint. | U46: INTERNAL — Gherkin structure validator. Runs post-generation inside FR-004 BE-09. Checks: Given/When/Then present, non-empty, correct keyword order. Flags TC — does not reject it. Not a standalone HTTP endpoint.
A47: 5 | B47: ICE validates the response — checks mandatory fields and flags incomplete TCs | C47: FR-005 | D47: Design & Author | E47: Generate & Add to Pool | F47: BE-02 | G47: Detects duplicate test cases within the session pool by comparing TC descriptions and step sequences, flagging duplicates for user review. | H47: • Flags test cases that fail mandatory field validation inline during generation or import. • Returns both valid and flagged TCs together in the session pool response. • Flagged TCs include rowIndex, fieldName, and ERR-005-* reasonCode for traceability. | I47: • Must return valid cases with flagged=false • Must return flagged cases with rowIndex, fieldName, and reasonCode (ERR-005-*) • Must include validCount and flaggedCount in the response • Must list all reason codes when multiple fields are missing on the same TC • Must return all flagged TCs when all TCs are invalid instead of returning an empty success response | J47: Backend Dev | K47: FR-005 / BE-01 | L47: 3 | M47: 0.75 | N47: =MAX(ROUND(M47*1.2/0.25,0)*0.25,0.25) -> 1 | O47: GitHub Copilot — generate inline flagging + response builder Claude — partial success response design | P47: Spring Boot · Jackson · OpenAPI 3.0 | Q47: READ (session) | R47: Redis (session only) | S47: [in-memory pool] | T47: INTERNAL — inline flagging engine. Adds flagged=true + flag_reason[] to TC when mandatory field validation fails. ERR-005-* codes: MISSING-DESCRIPTION, MISSING-STEP, MISSING-EXPECTED-RESULT, INVALID-TEST-TYPE. Not a standalone HTTP endpoint. | U47: INTERNAL — inline flagging engine. Adds flagged=true + flag_reason to TC object when validation fails. Flag returned in SSE event from FR-004 BE-09. Not a standalone HTTP endpoint.
A48: 5 | B48: ICE validates the response — checks mandatory fields and flags incomplete TCs | C48: FR-005 | D48: Design & Author | E48: Generate & Add to Pool | F48: BE-03 | G48: Assigns a validation status to each TC (valid, flagged-incomplete, flagged-duplicate) and writes the result to the session checkpoint. | H48: • Exposes a summary endpoint called after generation completes to provide validation metrics. • Returns counts and breakdown of which mandatory fields caused flags across all generated TCs. • Enables the front-end to display aggregate validation status without re-processing the pool. | I48: • Must return summary fields even when flaggedCount is 0 • Must list unique ERR-005-* codes in flaggedReasons with counts and field names • Must ensure the summary flaggedCount matches the actual flagged row count • Must provide a breakdown showing how many TCs are missing Description, Test Step, and Expected Result respectively | J48: Backend Dev | K48: FR-005 / BE-02 | L48: 2 | M48: 0.5 | N48: =MAX(ROUND(M48*1.2/0.25,0)*0.25,0.25) -> 0.5 | O48: GitHub Copilot — generate summary builder | P48: Spring Boot · Jackson · Java Record | Q48: READ (session) | R48: Redis (session only) | S48: [in-memory pool] | T48: ENDPOINT YOU CREATE: GET /api/v1/sessions/{session_id}/validation-summary Response 200: {total: int, valid: int, flagged: int, reasons: [{code: ERR-005-*, count: int, field: "Test Step" etc.}]} Errors: 404 session not found | U48: ENDPOINT YOU CREATE: GET /api/v1/sessions/{session_id}/validation-summary Response 200: {total: int, flagged: int, flag_reasons: [{tc_id, reason}]} Called after generation completes. Errors: 404 session not found | V48: → FR-006 FE-01 session.tcPool[sessionId][].flagged = true/false session.tcPool[sessionId][].flagReason = string FR-006 FE-01 renders valid TCs in table; flagged rows shown in amber.
A49: 5 | B49: ICE validates the response — checks mandatory fields and flags incomplete TCs | C49: FR-005 | D49: Design & Author | E49: Generate & Add to Pool | F49: FE-01 | G49: Renders validation status badges on each TC row in the pool table, distinguishing valid, incomplete, and duplicate entries visually. | H49: • Highlights flagged test case rows with an amber background in the pool table. • Shows the reason code as a tooltip on hover over the flagged row. • Provides immediate visual feedback on which TCs require user attention. | I49: • Must show flagged test case rows with an amber background in the pool table • Must display a plain-English reason on hover tooltip (e.g. 'Missing Test Step' instead of ERR-005-MISSING-STEP) • Must leave valid rows visually unaffected • Must list all reasons in the tooltip when multiple flags apply to the same TC | J49: Frontend Dev | L49: 3 | M49: 0.75 | N49: =MAX(ROUND(M49*1.2/0.25,0)*0.25,0.25) -> 1 | O49: v0.dev — generate flagged row component GitHub Copilot — tooltip + reason code mapping | P49: React · TypeScript · Tailwind CSS · React Tooltip | Q49: READ (session) | R49: Redis (session only) | S49: [in-memory pool] | T49: Reads: generated TC rows from pool. Validates mandatory field completeness. Flags incomplete rows. No DB write. | U49: ENDPOINT YOU CALL (defined in FR-004 BE-09 SSE): Listen for flagged=true in tc_generated event. Render amber warning row for flagged TCs. Show flag_reason tooltip on hover. No separate API call needed — flag is in the SSE stream from generation.
A50: 5 | B50: ICE validates the response — checks mandatory fields and flags incomplete TCs | C50: FR-005 | D50: Design & Author | E50: Generate & Add to Pool | F50: FE-02 | G50: Displays a validation summary card above the pool table showing total TCs, valid count, flagged count, and duplicate count. | H50: • Displays a banner above the chat view showing '{validCount} valid, {flaggedCount} flagged'. • Updates the summary counts automatically on regeneration or edit. • Provides a quick overview of pool health without scrolling the table. | I50: • Must display a banner above the chat view showing '{validCount} valid, {flaggedCount} flagged' after TC generation • Must update the summary counts automatically whenever a regeneration or edit occurs • Must show green styling when flaggedCount = 0 and amber styling when flaggedCount > 0 • Must remain visible at all times after initial generation without requiring scroll | J50: Frontend Dev | K50: FR-005 / FE-01 | L50: 2 | M50: 0.5 | N50: =MAX(ROUND(M50*1.2/0.25,0)*0.25,0.25) -> 0.5 | O50: v0.dev — generate summary banner component GitHub Copilot — colour logic | P50: React · TypeScript · Tailwind CSS | Q50: READ (session) | R50: Redis (session only) | S50: [in-memory pool] | T50: Reads: generated TC rows from pool. Validates BDD structure. Flags incomplete rows. No DB write. | U50: ENDPOINT YOU CALL (defined in FR-005 BE-03): GET /api/v1/sessions/{session_id}/validation-summary Call after generation_complete SSE event. Show banner: '{N} test cases flagged for review' with count of flagged TCs.
A51: 5 | B51: ICE validates the response — checks mandatory fields and flags incomplete TCs | C51: FR-005 | D51: Design & Author | E51: Generate & Add to Pool | F51: INT-01 | G51: Validates the full validation pipeline: generated TCs processed, mandatory fields checked, duplicates detected, and status badges rendered correctly. | H51: • Validates the full validation pipeline from generation through to UI rendering. • Generates TCs with requirements designed to produce flagged cases. • Verifies that inline flags and summary counts are correct and consistent. | I51: • Must validate the full pipeline from TC generation through UI rendering with requirements designed to produce flagged cases • Must display flagged rows with amber background and tooltip showing plain-English field name for the violated rule • Must show banner counts that match the actual flagged row count in the table • Must render a mix of valid and invalid TCs correctly in their respective categories • Must return validation summary with correct ERR-005-* code breakdown covering all 4 defined error codes | J51: QA / Both Devs | K51: FR-005 / All BE + FE | L51: 4 | M51: 1 | N51: =MAX(ROUND(M51*1.2/0.25,0)*0.25,0.25) -> 1.25 | O51: Playwright AI — generate validation E2E tests Claude — generate requirements triggering specific errors | P51: Playwright · GitHub Actions CI · Docker Compose | Q51: READ (session) | R51: Redis (session only) | S51: [in-memory pool] | T51: Reads: generated TC rows from pool. Validates BDD structure. Flags incomplete rows. No DB write. | U51: ENDPOINT UNDER TEST: GET /api/v1/sessions/{session_id}/validation-summary Also: SSE stream from POST /generate. Test: requirements that produce flagged TCs → flagged=true in SSE events. → validation-summary returns correct counts.
A52: 6 | B52: Rendering of test case pool table | C52: FR-006 | D52: Design & Author | E52: Generate & Add to Pool | F52: BE-01 | G52: Exposes the GET /api/v1/session/testcases endpoint that returns the full TC pool from the Redis session, supporting pagination and sort parameters. | H52: • Exposes GET /api/v1/session/testcases/search?q= for free-text search across TC descriptions, test steps, and expected results. • Exposes GET /api/v1/session/testcases/filter with query params testType, priority, and others combined with AND logic. • Supports debounced server-side search; empty q returns the full list. | I52: • Must return matches across TC Description, Test Step, and Expected Results fields for GET /api/v1/session/testcases/search?q= • Must return only Functional rows when testType=Functional filter is applied via GET /api/v1/session/testcases/filter • Must apply multiple filters with AND logic when testType and priority are both specified • Must display correct active filter badge count per column in the response metadata • Must return the full unfiltered pool when all filters are cleared • Must return an empty result set with 200 status when no TCs match the applied filters | J52: Backend Dev | L52: 3 | M52: 1 | N52: =MAX(ROUND(M52*1.2/0.25,0)*0.25,0.25) -> 1.25 | O52: GitHub Copilot — filter query param parsing Claude — combined filter + search logic | P52: Spring Boot · Java · Session store (Redis) | Q52: READ | R52: Redis (session pool) | S52: session pool — ice.testcases | T52: testType, priority, functionality, source, flagged, testCaseDescription, testStep, expectedResults | U52: GET /api/v1/session/testcases/search?q={text} GET /api/v1/session/testcases/filter?testType=&priority=&functionality=&source=&flagged= Returns: [{tcId, prerequisite, description, stepId, step, expected, testType, functionality, priority, source, flagged}]
A53: 6 | B53: Rendering of test case pool table | C53: FR-006 | D53: Design & Author | E53: Generate & Add to Pool | F53: BE-02 | G53: Exposes the GET /api/v1/session/testcases/search endpoint that performs free-text search across TC descriptions and step content within the session pool. | H53: • Exposes DELETE /api/v1/session/testcases/{tcId} to remove a single TC from the session pool in Redis. • Exposes DELETE /api/v1/session/testcases with body {tcIds: ["TC-001", "TC-002"]} for atomic bulk delete. • Exposes PUT /api/v1/session/testcases/{tcId} to edit any subset of TC fields in place. • Returns 204 on success, 404 if tcId not found, and {deleted: N} for bulk operations. | I53: • Must remove the TC from the session pool via DELETE /api/v1/session/testcases/{tcId} so it no longer appears in GET responses • Must remove all specified TCs atomically via DELETE /api/v1/session/testcases with body {tcIds: [...]} • Must return 404 when DELETE is called on a non-existent tcId • Must update only the supplied fields via PUT /api/v1/session/testcases and leave unsupplied fields unchanged • Must return 400 with the field name in the error body when PUT receives an empty value for a mandatory field • Must mark the edited TC with an editedAt timestamp and editedBy flag in the session pool | J53: Backend Dev | L53: 3 | M53: 1 | N53: =MAX(ROUND(M53*1.2/0.25,0)*0.25,0.25) -> 1.25 | O53: GitHub Copilot — REST endpoint boilerplate Claude — atomic bulk delete design | P53: Spring Boot · Redis · Jackson | Q53: READ + WRITE | R53: Redis (session pool) | S53: session pool — ice.testcases | T53: tcId, all 9 TC fields, edited flag, deleted timestamp | U53: DELETE /api/v1/session/testcases/{tcId} → 204 DELETE /api/v1/session/testcases body:{tcIds[]} → {deleted:N} PUT /api/v1/session/testcases/{tcId} body:{fields} → updated TC
A54: 6 | B54: Rendering of test case pool table | C54: FR-006 | D54: Design & Author | E54: Generate & Add to Pool | F54: FE-01 | G54: Renders the 9-column TC pool table populated from the session, displaying all generated and imported test cases with their validation status badges. | H54: • Renders a 9-column TC pool table displaying Checkbox, TC ID, Prerequisite, Test Case Description, Test Step ID, Test Step, Expected Results, Test Type, and Functionality. • Implements sticky header during vertical scroll, virtual scroll for > 100 rows, and horizontal scroll on narrow viewports. • Shows a source badge per row: ICE (purple) for generated TCs or Excel (green) for imported TCs. | I54: • Must render all 9 columns (Checkbox, TC ID, Prerequisite, Test Case Description, Test Step ID, Test Step, Expected Results, Test Type, Functionality) with correct data from the session pool • Must keep the header row sticky during vertical scroll • Must render 500 rows without lag using virtual scroll • Must display the correct source badge (ICE / Excel / Xray) per row • Must show flagged rows with amber background and display a tooltip on hover • Must support horizontal scroll on 1024px viewport without breaking layout | J54: Frontend Dev | L54: 4 | M54: 1.5 | N54: =MAX(ROUND(M54*1.2/0.25,0)*0.25,0.25) -> 1.75 | O54: Cursor AI — table layout + virtual scroll Claude — source badge + flagged row styling | P54: React · TypeScript · Tailwind CSS · React Virtual / TanStack Virtual | Q54: READ | R54: Redis (via BE-01) | S54: session pool — ice.testcases | T54: All 9 TC fields + source + flagged + edited | U54: Calls: GET /api/v1/session/testcases (initial load) Reads pool via BE-01 search/filter
A55: 6 | B55: Rendering of test case pool table | C55: FR-006 | D55: Design & Author | E55: Generate & Add to Pool | F55: FE-02 | G55: Renders the column headers and sort controls for the TC pool table, allowing the user to sort by any of the 9 TC fields. | H55: • Renders a ▼ icon on every column header that opens a dropdown of unique values for that column. • Populates dropdown from the current session pool and allows selection of one or more values to filter the table immediately. • Active filter shows a filled ▼ icon with a count badge on the column header, e.g. 'TEST TYPE ▼ 1'. | I55: • Must render a ▼ icon on all 5 filterable column headers that opens a dropdown of unique values from the session pool • Must filter the table immediately to show only rows matching the selected value (e.g., 'Functional') • Must apply AND logic correctly when two or more filters are active simultaneously • Must display the correct active filter badge count on each column header • Must reset the table to the full unfiltered pool when 'Clear all filters' is clicked | J55: Frontend Dev | K55: FR-006 / BE-03 | L55: 4 | M55: 1.5 | N55: =MAX(ROUND(M55*1.2/0.25,0)*0.25,0.25) -> 1.75 | O55: Cursor AI — dropdown filter component Claude — multi-column AND logic + badge count | P55: React · TypeScript · Tailwind CSS | Q55: READ | R55: Redis (via BE-01) | S55: session pool — ice.testcases | T55: testType, priority, functionality, source, flagged | U55: Calls: GET /api/v1/session/testcases/filter (BE-01) | V55: → FR-008 BE-01 session.tcPool[sessionId] — fully validated, flagged TCs marked. FR-008 BE-01 serialises this pool to .xlsx on export trigger.
A56: 6 | B56: Rendering of test case pool table | C56: FR-006 | D56: Design & Author | E56: Generate & Add to Pool | F56: FE-03 | G56: Renders the free-text search input above the pool table and filters displayed rows in real time as the user types. | H56: • Renders a free-text search input above the pool table with 300ms debounce before firing GET /session/testcases/search?q=. • Searches across Test Case Description, Test Step, and Expected Results fields. • Shows result count 'Showing 12 of 47 test cases', a clear button (×) to reset, and works in combination with column filters using AND logic. | I56: • Must fire GET /session/testcases/search?q= after 300ms debounce, not on every keypress • Must search across Test Case Description, Test Step, and Expected Results fields • Must display the result count as 'Showing X of Y test cases' • Must reset to the full unfiltered list when the clear button is clicked • Must apply both search and column filter simultaneously when both are active | J56: Frontend Dev | L56: 2 | M56: 0.5 | N56: =MAX(ROUND(M56*1.2/0.25,0)*0.25,0.25) -> 0.5 | O56: Cursor AI — search bar with debounce Claude — combined filter state | P56: React · TypeScript · Tailwind CSS | Q56: READ | R56: Redis (via BE-01) | S56: session pool — ice.testcases | T56: testCaseDescription, testStep, expectedResults | U56: Calls: GET /api/v1/session/testcases/search?q= (BE-01)
A57: 6 | B57: Rendering of test case pool table | C57: FR-006 | D57: Design & Author | E57: Generate & Add to Pool | F57: FE-04 | G57: Renders filter controls for test type, priority, and validation status, allowing the user to narrow the pool table to a specific subset. | H57: • Renders a + button in the second column of every TC row to expand inline sub-rows showing test steps. • Sub-row columns display Step ID (auto-generated as TS-{tcId}-01, TS-{tcId}-02, …), Test Step, and Expected Results. • The + changes to − when expanded, and multiple rows can be expanded simultaneously without affecting others. | I57: • Must render a + button in the second column of every TC row • Must expand inline sub-rows below the parent row showing Step ID (TS-{tcId}-01, TS-{tcId}-02, ...), Test Step, and Expected Results when + is clicked • Must change the + icon to − when the row is expanded • Must allow multiple rows to be expanded simultaneously without overlap or layout breakage • Must collapse sub-rows correctly when − is clicked • Must preserve the expand state of rows when a column filter is applied | J57: Frontend Dev | K57: FR-006 / FE-01 | L57: 3 | M57: 1 | N57: =MAX(ROUND(M57*1.2/0.25,0)*0.25,0.25) -> 1.25 | O57: Cursor AI — expandable row component Claude — step ID generation + multi-expand state | P57: React · TypeScript · Tailwind CSS | Q57: READ | R57: Redis (via BE-01) | S57: session pool — ice.testcases (steps field) | T57: stepId, testStep, expectedResults per step | U57: Client-side only — reads steps from already-loaded TC object.
A58: 6 | B58: Rendering of test case pool table | C58: FR-006 | D58: Design & Author | E58: Generate & Add to Pool | F58: FE-05 | G58: Renders the expandable step detail panel for each TC row, showing the full step sequence when the user clicks to expand. | H58: • Renders a copy icon on every row that copies all 9 TC fields as formatted plain text to the clipboard. • Shows a 'Copied!' tooltip that fades after 1.5 seconds. • Operates purely client-side with no API call required. | I58: • Must render a copy icon on every TC row • Must copy all 9 TC fields as formatted plain text to the clipboard when the icon is clicked • Must display a 'Copied!' tooltip that fades after 1.5 seconds • Must operate purely client-side with no API call • Must work in Chrome, Firefox, Safari, and Edge browsers | J58: Frontend Dev | K58: FR-006 / FE-01 | L58: 1 | M58: 0.5 | N58: =MAX(ROUND(M58*1.2/0.25,0)*0.25,0.25) -> 0.5 | O58: Cursor AI — clipboard API + tooltip | P58: React · TypeScript · Clipboard API | Q58: READ | R58: Client state | S58: None — reads from React component state | T58: All 9 TC fields | U58: None — pure client-side.
A59: 6 | B59: Rendering of test case pool table | C59: FR-006 | D59: Design & Author | E59: Generate & Add to Pool | F59: FE-06 | G59: Renders the bulk select checkbox column and Select All control, enabling the user to select multiple TCs for bulk operations. | H59: • Renders an edit icon (pencil) on every TC row that opens a slide-out panel from the right when clicked. • Overlay displays TC ID (read-only), Prerequisite (text input), Test Case Description (textarea), Test Step (textarea), Expected Results (textarea), and Test Type (dropdown: Functional, Edge case, Regression). • Table remains visible behind the panel; changes are sent via PUT /session/testcases/{tcId} on save. | I59: • Must open a slide-out panel from the right when the edit (pencil) icon is clicked • Must pre-populate all editable fields (Prerequisite, Test Case Description, Test Step, Expected Results, Test Type, Functionality) with current TC values • Must display TC ID as read-only in the overlay • Must call PUT and update the row in the table without full page reload when Save is clicked • Must close the overlay without persisting changes when Cancel is clicked • Must remove the row from the table when Delete is clicked from the overlay • Must show the edited TC row with italic TC ID and a ✎ indicator after save • Must return a validation error and prevent save when a mandatory field is left empty • Must persist the updated TC to session pool in ice.testcases and be retrievable on subsequent reads | J59: Frontend Dev | K59: FR-006 / FE-01 | L59: 5 | M59: 1.5 | N59: =MAX(ROUND(M59*1.2/0.25,0)*0.25,0.25) -> 1.75 | O59: Cursor AI — slide-out panel + form Claude — unsaved changes guard + edited indicator | P59: React · TypeScript · Tailwind CSS | Q59: READ + WRITE | R59: Redis (via BE-02) | S59: session pool — ice.testcases | T59: All 9 editable TC fields + edited flag | U59: PUT /api/v1/session/testcases/{tcId} (BE-02) DELETE /api/v1/session/testcases/{tcId} (BE-02)
A60: 6 | B60: Rendering of test case pool table | C60: FR-006 | D60: Design & Author | E60: Generate & Add to Pool | F60: FE-07 | G60: Renders the per-row delete button that removes a single TC from the session pool without affecting other TCs. | H60: • Renders a trash icon on every TC row that triggers an inline confirmation prompt: 'Delete TC-001? This cannot be undone. [Delete] [Cancel]'. • On confirmation, fires DELETE /session/testcases/{tcId} and removes the row with a fade-out animation. • Pool count in the header updates immediately after deletion. | I60: • Must render a trash icon on every TC row • Must trigger an inline confirmation prompt 'Delete TC-001? This cannot be undone. [Delete] [Cancel]' when the trash icon is clicked • Must fire DELETE /session/testcases/{tcId} and remove the row with a fade-out animation on confirmation • Must decrement the pool count in the header correctly after deletion • Must remove all selected rows when bulk delete is triggered • Must display an empty state message when all TCs are deleted from the pool • Must persist the deletion to session pool in ice.testcases and confirm removal on subsequent reads | J60: Frontend Dev | K60: FR-006 / All BE + FE | L60: 3 | M60: 1 | N60: =MAX(ROUND(M60*1.2/0.25,0)*0.25,0.25) -> 1.25 | O60: Cursor AI — delete confirmation + animation Claude — bulk delete toolbar design | P60: React · TypeScript · Tailwind CSS | Q60: WRITE | R60: Redis (via BE-02) | S60: session pool — ice.testcases | T60: tcId (delete key) | U60: DELETE /api/v1/session/testcases/{tcId} (BE-02) DELETE /api/v1/session/testcases body:{tcIds[]} (BE-02)
A61: 6 | B61: Rendering of test case pool table | C61: FR-006 | D61: Design & Author | E61: Generate & Add to Pool | F61: FE-08 | G61: Renders the bulk action toolbar that appears when one or more TCs are selected, providing bulk delete and export options. | H61: • Renders a checkbox in the first column of every row and a header checkbox to select all visible rows (respects active filters). • Header checkbox shows indeterminate state when some but not all rows are selected. • A bulk action toolbar appears below the table header when ≥1 row is selected, displaying 'N selected — [Export to Excel] [Delete]'. | I61: • Must render a checkbox in the first column of every row and a header checkbox to select all visible rows • Must respect active filters when 'select all' is clicked, selecting only visible rows • Must show the header checkbox in indeterminate state when some but not all rows are selected • Must display the bulk action toolbar below the table header on first selection and hide it when selection is cleared • Must pass selected tcIds to FR-008 export handler when the Export button in the toolbar is clicked • Must pass selected tcIds to FR-009 Xray integration when the Push to Xray button in the toolbar is clicked | J61: Frontend Dev | K61: FR-006 / INT-01 | L61: 3 | M61: 1 | N61: =MAX(ROUND(M61*1.2/0.25,0)*0.25,0.25) -> 1.25 | O61: Cursor AI — checkbox + indeterminate state Claude — filter-aware select-all logic | P61: React · TypeScript · Tailwind CSS | Q61: READ | R61: Client state (React) | S61: None — client-side selection state | T61: tcId[] selected set | U61: No API call — selection state passed as props to FR-008 and FR-009.
A62: 6 | B62: Rendering of test case pool table | C62: FR-006 | D62: Design & Author | E62: Generate & Add to Pool | F62: FE-09 | G62: Renders the Push to Xray button in the footer, enabled only when the pool contains at least one valid TC with no unresolved flags. | H62: • Renders the Push to Xray button in the footer, enabled only when the pool contains at least one valid TC with no unresolved flags. • Button is disabled (greyed) when pool is empty or all TCs are flagged, with tooltip 'Add at least one valid test case to continue'. • On click, reads current pool from session (ice.testcases) and validates gate conditions before proceeding. | I62: • Must render the Push to Xray button disabled with tooltip 'Add at least one valid test case' when pool is empty • Must render the button disabled with tooltip when all TCs in pool are flagged • Must enable the button when pool contains at least one valid unflagged TC • Must write ice.enrichment.input to session on click with tcIds[] matching pool contents and correct counts • Must navigate to the enrichment screen after session write completes | J62: Frontend Dev | L62: 2 | M62: 0.5 | N62: =MAX(ROUND(M62*1.2/0.25,0)*0.25,0.25) -> 0.5 | O62: Cursor AI — button gate logic + disabled state styling Claude — handoff key design + mid-generation guard | P62: React · TypeScript · Tailwind CSS · Redis (session write) | Q62: WRITE | R62: Redis (session) | S62: Session key: ice.enrichment.input | T62: ice.enrichment.input: {tcIds[], source, poolCount, validCount, flaggedCount, timestamp} | U62: INTERNAL — no HTTP endpoint. Session write: POST /api/v1/session/enrichment/init Body: {tcIds[], poolCount, validCount, flaggedCount} Called by FE on button click before navigation. Returns 200 → FE navigates. Returns 400 if pool empty.
A63: 6 | B63: Rendering of test case pool table | C63: FR-006 | D63: Design & Author | E63: Generate & Add to Pool | F63: INT-01 | G63: Validates the full pool table render: TCs loaded from session, displayed with correct validation badges, search and filter working, Push to Xray button state correct. | H63: • Validates the full pool table render with TCs loaded from session, displayed with correct validation badges, search and filter working, and Push to Xray button state. • Test 1 applies column filter (testType=Functional, priority=High) and verifies AND logic and clear all restores full pool. • Test 2 combines testType=Edge case filter with 'CVV' search and verifies combined result; Test 3 clicks row expand to verify detail display. | I63: • Must load all TCs from session pool ice.testcases and display with correct validation badges • Must apply column filters (testType, priority) and return only matching rows • Must combine search and filter using AND logic and display correct result set • Must save edits to session pool and reflect changes immediately in the table • Must remove deleted TC from pool permanently with no recovery option • Must support multi-select and correctly feed selected TCs to FR-008 and FR-009 | J63: QA / Both Devs | L63: 5 | M63: 1.5 | N63: =MAX(ROUND(M63*1.2/0.25,0)*0.25,0.25) -> 1.75 | O63: Claude — E2E scenario design Copilot — test automation code | P63: TestNG · Selenium · React Testing Library · GitHub Actions | Q63: READ + WRITE | R63: Redis (session pool) | S63: session pool — ice.testcases | T63: All interaction fields verified end-to-end | U63: All FR-006 BE-01 + BE-02 endpoints under test.
A64: 7 | B64: Adding/deleting/modifying test cases in the pool table. | C64: FR-007 | D64: Design & Author | E64: ice.testcases ice.editoverlay ice.fileref Prevent key collisions | F64: BE-01 | G64: Exposes the API endpoints for adding, editing, and deleting individual test cases in the Redis session pool, with key collision prevention. | H64: • Exposes API endpoints for adding, editing, and deleting individual test cases in the Redis session pool. • Session key namespacing defined as ice.testcases, ice.editoverlay, ice.fileref to prevent key collisions. • Constants shared via config across all Design & Author FRs. | I64: • Must expose API endpoints for adding, editing, and deleting individual test cases in Redis session pool • Must resolve each namespace (ice.testcases, ice.editoverlay, ice.fileref) to correct data structure • Must prevent cross-namespace contamination between concurrent user sessions • Must share constants via config with no hardcoded strings in endpoint code | J64: Backend Dev | L64: 1 | M64: 0.5 | N64: =MAX(ROUND(M64*1.2/0.25,0)*0.25,0.25) -> 0.5 | O64: GitHub Copilot — session namespace constants | P64: Spring Boot · Redis | Q64: READ + WRITE | R64: Redis | S64: Session keys: ice.testcases, ice.editoverlay, ice.fileref | T64: Namespace constant definitions | U64: INTERNAL — no HTTP endpoint.
A65: 7 | B65: Adding/deleting/modifying test cases in the pool table. | C65: FR-007 | D65: Design & Author | E65: GET /session/ttl POST /session/extend Remaining seconds TTL reset on extend | F65: BE-02 | G65: Exposes the GET /session/ttl and POST /session/extend endpoints that return remaining session time and allow the user to extend the session before it expires. | H65: • Exposes GET /api/v1/session/ttl and POST /api/v1/session/extend endpoints that return remaining session time and allow session extension. • GET /api/v1/session/ttl returns {remainingSeconds, expiresAt}; POST /api/v1/session/extend resets TTL to configured maximum. • Front end polls GET /session/ttl every 30s (FR-007 FE-02) to track session lifetime. | I65: • Must return {remainingSeconds, expiresAt} from GET /api/v1/session/ttl at any point in active session • Must return remainingSeconds as 0 when session has expired • Must reset TTL to configured value on POST /api/v1/session/extend for valid sessions • Must reject POST /api/v1/session/extend with error when session is already expired • Must return full TTL value on subsequent GET after successful extend | J65: Backend Dev | L65: 2 | M65: 0.5 | N65: =MAX(ROUND(M65*1.2/0.25,0)*0.25,0.25) -> 0.5 | O65: GitHub Copilot — TTL endpoint boilerplate | P65: Spring Boot · Redis · Jackson | Q65: READ + WRITE | R65: Redis | S65: Session TTL key | T65: remainingSeconds, expiresAt | U65: GET /api/v1/session/ttl → {remainingSeconds, expiresAt} POST /api/v1/session/extend → {newExpiresAt}
A66: 7 | B66: Adding/deleting/modifying test cases in the pool table. | C66: FR-007 | D66: Design & Author | E66: Global 401 intercept Redirect to expired screen Clear session data Fresh login recovery | F66: BE-03 | G66: Intercepts 401 Unauthorized responses globally and redirects the user to the session-expired screen, clearing session data before redirecting to fresh login. | H66: • Intercepts 401 Unauthorized responses globally and redirects the user to the session-expired screen. • Spring Security filter clears Redis session keys (ice.testcases, ice.editoverlay, ice.fileref) on 401 and returns redirect URL. • Expired screen displays 'Your session has expired. Your work has been saved as a draft.' with [Resume] and [Start fresh] options. | I66: • Must intercept any 401 Unauthorized response from Design & Author endpoints and redirect to expired screen within 500ms • Must clear all Redis session keys (ice.testcases, ice.editoverlay, ice.fileref) on 401 before redirect • Must provide clean session state with no residual data after fresh login • Must offer Resume option to restore last auto-saved draft if available | J66: Backend Dev | L66: 2 | M66: 0.5 | N66: =MAX(ROUND(M66*1.2/0.25,0)*0.25,0.25) -> 0.5 | O66: GitHub Copilot — Spring Security 401 handler | P66: Spring Boot · Spring Security · Redis | Q66: WRITE (clear) | R66: Redis | S66: Session keys cleared: ice.testcases, ice.editoverlay, ice.fileref | T66: All session keys cleared on 401 | U66: INTERNAL — Spring Security filter. No HTTP endpoint.
A67: 7 | B67: Adding/deleting/modifying test cases in the pool table. | C67: FR-007 | D67: Design & Author | E67: Banner at <5 min Re-shown at <60s Extend Session button Web Worker — background tab | F67: FE-01 | G67: Renders the session expiry warning banner when fewer than 5 minutes remain, re-showing it at under 60 seconds with an Extend Session button. | H67: • Renders the session expiry warning banner when fewer than 5 minutes remain, re-showing it at under 60 seconds with an Extend Session button. • Polls GET /session/ttl every 30s; banner appears at < 5 min with 'Your session expires in 4:32 — [Extend Session]', dismissed banner re-shows at < 60s. • Uses Web Worker for accurate countdown in background tabs; Extend Session triggers POST /session/extend and dismisses banner. • On expiry, triggers 401 interceptor which clears session and redirects to expired screen. | I67: • Must poll GET /session/ttl every 30 seconds and display banner when fewer than 5 minutes remain • Must update countdown timer every second while banner is visible • Must re-show dismissed banner when fewer than 60 seconds remain • Must reset TTL and dismiss banner when user clicks Extend Session button • Must continue polling and firing banner via Web Worker when browser tab is in background | J67: Frontend Dev | L67: 3 | M67: 1 | N67: =MAX(ROUND(M67*1.2/0.25,0)*0.25,0.25) -> 1.25 | O67: Cursor AI — countdown banner + Web Worker Claude — extension limit logic | P67: React · TypeScript · Web Worker API · Tailwind CSS | Q67: READ | R67: Redis (via BE-02) | S67: Session TTL | T67: remainingSeconds | U67: GET /api/v1/session/ttl (BE-02) — polled every 30s POST /api/v1/session/extend (BE-02) — on Extend Session click
A68: 7 | B68: Adding/deleting/modifying test cases in the pool table. | C68: FR-007 | D68: Design & Author | E68: Simulate expiry mid-use Verify banner + extend Force 401 → redirect Fresh login = clean state | F68: INT-01 | G68: Validates the full session management lifecycle: expiry warning shown, Extend Session button works, forced expiry triggers redirect, fresh login restores clean state. | H68: • Validates the full session management lifecycle: expiry warning shown, Extend Session button works, forced expiry triggers redirect, and fresh login restores state. • Test 1 sets session TTL to 4 min, verifies banner appears, clicks Extend, and verifies TTL reset with banner dismissed. • Test 2 dismisses banner at 4 min, fast-forwards to 55s, and verifies re-appearance; Test 3 invalidates session server-side and triggers any API call to verify 401 redirect. | I68: • Must display session expiry warning banner at correct TTL threshold (< 5 min) • Must trigger 401 redirect to expired screen within 500ms when session expires • Must clear all session data from Redis after expiry, confirmed via Redis CLI check • Must enforce configured extension limit and reject further extensions beyond that limit • Must restore available state on fresh login if auto-saved draft exists | J68: QA / Both Devs | L68: 3 | M68: 1 | N68: =MAX(ROUND(M68*1.2/0.25,0)*0.25,0.25) -> 1.25 | O68: Claude — E2E session scenario design | P68: TestNG · Selenium · Redis client · GitHub Actions | Q68: READ + WRITE | R68: Redis | S68: Session keys verified via Redis CLI in test | T68: remainingSeconds, session keys, redirect URL | U68: FR-007 BE-02 + BE-03 endpoints under test.
A69: 8 | B69: Exporting generated test cases to excel | C69: FR-008 | D69: Design & Author | E69: Export Selected to Excel (FE: footer button) | F69: BE-02 | G69: Generates an Excel file from the selected TCs in the session pool, mapping all 9 TC fields to the standard ICE Excel export template columns. | H69: • Generates an Excel file from the selected TCs in the session pool, mapping all 9 TC fields to the standard ICE Excel export template columns. • File named ICE_TestCases_{projectName}_{timestamp}.xlsx with sanitised project name. • Exports selected test cases with all field mappings intact for downstream use. | I69: • Must generate Excel file named ICE_TestCases_{projectName}_{timestamp}.xlsx with sanitised project name • Must replace special characters in project name with underscores • Must format timestamp in ISO format • Must map all 9 TC fields from session pool to standard ICE Excel export template columns • Must export only selected TCs from the in-memory pool | J69: Backend Dev | K69: FR-008 / BE-01 | L69: 1 | M69: 0.25 | N69: =MAX(ROUND(M69*1.2/0.25,0)*0.25,0.25) -> 0.25 | O69: GitHub Copilot — generate filename sanitiser | P69: Spring Boot · Java · Regex | Q69: READ (session) | R69: Redis (session only) | S69: [in-memory pool] | T69: Reads: selected TC rows from pool. Serialises to .xlsx. Streamed to browser. No DB read or write. | U69: INTERNAL — file name convention. Format: ICE_TCs_{YYYY-MM-DD}_{session_id_short}.xlsx Used by: FR-008 BE-01 Content-Disposition header. Not a standalone HTTP endpoint.
A70: 8 | B70: Exporting generated test cases to excel | C70: FR-008 | D70: Design & Author | E70: Export Selected to Excel (FE: footer button) | F70: FE-01 | G70: Renders the Export Selected to Excel button in the pool table footer and triggers the BE-02 export, prompting the browser to download the generated file. | H70: • Renders the Export Selected to Excel button in the pool table footer and triggers the BE-02 export. • Export button located in chat view triggers POST request to backend. • Prompts the browser to download the generated file via Blob mechanism. | I70: • Must render Export Selected to Excel button in pool table footer • Must fire exactly one POST request to backend on button click • Must trigger browser download automatically via Blob mechanism when response arrives • Must disable button during export operation and re-enable on completion or error | J70: Frontend Dev | L70: 2 | M70: 0.5 | N70: =MAX(ROUND(M70*1.2/0.25,0)*0.25,0.25) -> 0.5 | O70: v0.dev — generate export button component GitHub Copilot — download trigger via Blob | P70: React · Axios (blob response) · TypeScript · Tailwind CSS | Q70: READ (session) | R70: Redis (session only) | S70: [in-memory pool] | T70: Reads: selected TC rows from pool. Serialises to .xlsx. Streamed to browser. No DB read or write. | U70: ENDPOINT YOU CALL (defined in FR-008 BE-01): POST /api/v1/sessions/{id}/export/excel Body: {tc_ids: [selected row IDs]} Trigger browser download from response blob. Show loading state on button while in flight. On 400: show 'No test cases to export' toast.
A71: 8 | B71: Exporting generated test cases to excel | C71: FR-008 | D71: Design & Author | E71: Export Selected to Excel (FE: footer button) | F71: INT-01 | G71: Validates the full Excel export flow: TCs selected, export triggered, file downloaded, and all 9 fields correctly mapped in the output file. | H71: • Validates the full Excel export flow: TCs selected, export triggered, file downloaded, and all 9 fields correctly mapped in the output file. • Generates test cases, exports to Excel, and verifies file structure integrity. • Confirms content correctness of all mapped fields in the downloaded file. | I71: • Must generate downloadable Excel file that opens without error in standard spreadsheet applications • Must include all 9 columns with correct headers matching ICE standard schema • Must export row count matching the number of selected test cases from pool • Must correctly map all 9 TC field values to corresponding Excel columns | J71: QA / Both Devs | K71: FR-008 / BE-01,FE-01 | L71: 3 | M71: 0.75 | N71: =MAX(ROUND(M71*1.2/0.25,0)*0.25,0.25) -> 1 | O71: Playwright AI — generate export E2E test Claude — generate file content verification scenarios | P71: Playwright · openpyxl (verification) · GitHub Actions CI | Q71: READ (session) | R71: Redis (session only) | S71: [in-memory pool] | T71: Reads: selected TC rows from pool. Serialises to .xlsx. Streamed to browser. No DB read or write. | U71: ENDPOINT UNDER TEST: POST /api/v1/sessions/{id}/export/excel Test: generate TCs → export → verify .xlsx has 9 columns, one row per TC. Test: export with selection → only selected TCs in file.
A72: 9 | B72: Exporting generated test cases to Xray | C72: FR-009 | D72: Design & Author | E72: Export Selected to Xray (FE: footer button) | F72: BE-01 | G72: Authenticates with the Xray API using the tenant's configured credentials from FR-027, obtaining a bearer token for the export session. | H72: • Authenticates with the Xray API using the tenant's configured credentials from FR-027, obtaining a bearer token for the export session. • Authenticates via OAuth 2.0 client credentials flow with Xray API. • Token cached with TTL and auto-refresh mechanism for session persistence. | I72: • Must authenticate with Xray API via OAuth 2.0 client credentials flow using tenant's configured credentials from xray_config • Must fetch bearer token on first Xray API call for the session • Must cache token with TTL and auto-refresh before expiry • Must never log or expose token value in application logs or error messages | J72: Backend Dev | L72: 4 | M72: 1 | N72: =MAX(ROUND(M72*1.2/0.25,0)*0.25,0.25) -> 1.25 | O72: GitHub Copilot — generate OAuth client + token cache Claude — token rotation design | P72: Spring Security OAuth2 · Caffeine Cache · Spring Boot | Q72: READ (session) + EXT WRITE | R72: Redis + Xray API + PostgreSQL (xray_config read) | S72: xray_config [in-memory pool] | T72: Reads: pool TCs from session + xray_config (auth) from PostgreSQL. External: pushes TCs to Xray REST API. No test_case table write — xray_key returned to UI only. | U72: INTERNAL — Xray OAuth2 integration. Fetches bearer token from Xray: POST https://xray.cloud.getxray.app /api/v2/authenticate Body: {client_id, client_secret} Token cached in Redis for 1. Used by: FR-009 BE-04 Xray Issue Creation API.
A73: 9 | B73: Exporting generated test cases to Xray | C73: FR-009 | D73: Design & Author | E73: Export Selected to Xray (FE: footer button) | F73: BE-02 | G73: Maps the selected TCs from the ICE 9-field schema to the Xray test case format and calls the Xray bulk import API to create test issues. | H73: • Maps the selected TCs from the ICE 9-field schema to the Xray test case format and calls the Xray bulk import API to create test issues. • Maps ICE 10-field standard schema to Xray Test Issue fields with configurable mapping per tenant. • Invokes Xray bulk import API to create corresponding test issues in Jira. | I73: • Must map all 10 ICE standard fields to Xray Test Issue fields using tenant-specific mapping from xray_config • Must skip unmapped optional fields gracefully without error • Must map Test Case Description to Xray summary field • Must map Test Step and Expected Result to Xray test step rows • Must invoke Xray bulk import API to create test issues for selected TCs from in-memory pool | J73: Backend Dev | K73: FR-009 / BE-01 | L73: 3 | M73: 0.75 | N73: =MAX(ROUND(M73*1.2/0.25,0)*0.25,0.25) -> 1 | O73: GitHub Copilot — generate mapper + config schema Claude — field mapping design | P73: Spring Boot · Jackson · ICE DB (mapping config) | Q73: READ (session) + EXT WRITE | R73: Redis + Xray API + PostgreSQL (xray_config read) | S73: xray_config [in-memory pool] | T73: Reads: pool TCs from session + xray_config (auth) from PostgreSQL. External: pushes TCs to Xray REST API. No test_case table write — xray_key returned to UI only. | U73: INTERNAL — TC to Xray issue mapper. Maps ICE 9-field TC to Xray Test issue JSON: summary = scenario, description = given+when+then labels = tags, priority = priority Not a standalone HTTP endpoint. Called by: FR-009 BE-04.
A74: 9 | B74: Exporting generated test cases to Xray | C74: FR-009 | D74: Design & Author | E74: Export Selected to Xray (FE: footer button) | F74: BE-03 | G74: Handles partial Xray push failures, returning a per-TC success/failure report so the user can identify which TCs were not pushed. | H74: • Handles partial Xray push failures, returning a per-TC success/failure report so the user can identify which TCs were not pushed. • Runs Xray export as background job with main screen unblocked during operation. • Progress tracked via job ID allowing user to monitor export status. | I74: • Must start the Xray export job immediately and return a job ID without blocking the main screen • Must allow the user to query export progress via GET /api/v1/export/xray/{jobId} while the job runs • Must return a per-TC success/failure report on completion showing which test cases were pushed and which failed • Must display a completion notification once all TCs have been processed • Must handle partial failures by completing the export for successful TCs and listing failed TCs with reasons | J74: Backend Dev | K74: FR-009 / BE-02 | L74: 5 | M74: 1.25 | N74: =MAX(ROUND(M74*1.2/0.25,0)*0.25,0.25) -> 1.5 | O74: GitHub Copilot — generate async job + progress tracker Claude — job state machine design | P74: Spring @Async · Redis (job state) · Spring Boot | Q74: READ (session) + EXT WRITE | R74: Redis + Xray API + PostgreSQL (xray_config read) | S74: xray_config [in-memory pool] | T74: Reads: pool TCs from session + xray_config (auth) from PostgreSQL. External: pushes TCs to Xray REST API. No test_case table write — xray_key returned to UI only. | U74: INTERNAL — background export job. Spawns async tead for bulk Xray push. Job status tracked in Redis: ice:session:{id}:xray_export_status Polled by: FR-009 FE-01 modal. Not a standalone HTTP endpoint.
A75: 9 | B75: Exporting generated test cases to Xray | C75: FR-009 | D75: Design & Author | E75: Export Selected to Xray (FE: footer button) | F75: BE-04 | G75: Updates each successfully pushed TC in the session with its Xray issue key (e.g. PAY-1041) and sets xray_pushed_at timestamp. | H75: • Updates each successfully pushed TC in the session with its Xray issue key (e.g. PAY-1041) and sets xray_pushed_at timestamp. • POSTs test cases to Xray /test REST API in batches of 50. • Handles partial failures by tracking success/failure per TC in batch. | I75: • Must POST test cases to the Xray /test REST API in batches of 50 • Must create each test case as an Xray Test issue and return its Xray issue key (e.g. PAY-1041) • Must update each successfully pushed TC in the session with its Xray issue key and xray_pushed_at timestamp • Must handle partial failures by committing successful cases and listing failed cases separately • Must track success/failure status per individual TC in the batch | J75: Backend Dev | K75: FR-009 / BE-02,BE-03 | L75: 5 | M75: 1.25 | N75: =MAX(ROUND(M75*1.2/0.25,0)*0.25,0.25) -> 1.5 | O75: GitHub Copilot — generate batch POST + partial failure handler Claude — idempotency + rate limit design | P75: Xray REST API · Spring Boot · Spring Retry | Q75: READ (session) + EXT WRITE | R75: Redis + Xray API + PostgreSQL (xray_config read) | S75: xray_config [in-memory pool] | T75: Reads: pool TCs from session + xray_config (auth) from PostgreSQL. External: pushes TCs to Xray REST API. No test_case table write — xray_key returned to UI only. | U75: ENDPOINT YOU CREATE: POST /api/v1/sessions/{id}/export/xray Request: {tc_ids?: string[]} Response 202: {job_id, status: 'queued', poll_url: '/api/v1/jobs/{job_id}/status'} Poll endpoint: GET /api/v1/jobs/{job_id}/status Response: {status, pushed: int, failed: int, results: [{tc_id, xray_key, status}]} | V75: → FR-010 / FR-011 / FR-012 ICE DB: test_case.xray_key populated after push. Downstream import/validation FRs read from ICE DB.
A76: 9 | B76: Exporting generated test cases to Xray | C76: FR-009 | D76: Design & Author | E76: Export Selected to Xray (FE: footer button) | F76: FE-01 | G76: Renders the Export Selected to Xray button in the footer and displays push progress and per-TC results on completion. | H76: • Renders the Export Selected to Xray button in the footer and displays push progress and per-TC results on completion. • Background export modal with progress indicator shows operation status. • Main screen remains interactive behind modal during export operation. | I76: • Must render the Export Selected to Xray button in the footer • Must open a background export modal displaying a progress indicator showing export progress percentage • Must keep the main screen interactive while the modal is open during export • Must close the modal and display a summary on completion showing total pushed and failed counts • Must display per-TC results including which TCs succeeded and which failed | J76: Frontend Dev | L76: 3 | M76: 0.75 | N76: =MAX(ROUND(M76*1.2/0.25,0)*0.25,0.25) -> 1 | O76: v0.dev — generate progress modal component GitHub Copilot — job polling hook | P76: React · TypeScript · Tailwind CSS · React Query | Q76: READ (session) + EXT WRITE | R76: Redis + Xray API + PostgreSQL (xray_config read) | S76: xray_config [in-memory pool] | T76: Reads: pool TCs from session + xray_config (auth) from PostgreSQL. External: pushes TCs to Xray REST API. No test_case table write — xray_key returned to UI only. | U76: ENDPOINT YOU CALL (defined in FR-009 BE-04): 1. POST /api/v1/sessions/{id}/export/xray → get job_id from 202 response 2. Poll GET /api/v1/jobs/{job_id}/status every 2s until status=complete|failed. Show modal with per-row push status. On complete: show xray_keys in modal.
A77: 9 | B77: Exporting generated test cases to Xray | C77: FR-009 | D77: Design & Author | E77: Export Selected to Xray (FE: footer button) | F77: INT-01 | G77: Validates the full Xray export flow: TCs selected, authenticated, pushed to Xray, Xray keys written back to session, and partial failure report shown. | H77: • Validates the complete Xray export workflow from test case selection through authentication, push to Xray, and writing Xray keys back to the session. • Verifies that issues are created in Xray with all correct field mappings and that partial failure reports are displayed to the user. • Ensures end-to-end integration between ICE session pool, Xray API authentication, and bidirectional synchronization of test case metadata. | I77: • Must validate that selected test cases are pushed to Xray and appear as Xray Test issues • Must verify that all 9 ICE fields are correctly mapped to Xray issue fields according to tenant configuration • Must write Xray issue keys back to the session for all successfully pushed TCs • Must keep the main screen interactive during the entire export operation • Must handle partial failures by completing successful pushes and reporting failed TCs with reasons | J77: QA / Both Devs | K77: FR-009 / All BE + FE | L77: 5 | M77: 1.25 | N77: =MAX(ROUND(M77*1.2/0.25,0)*0.25,0.25) -> 1.5 | O77: Playwright AI — generate Xray export E2E Postman AI — generate Xray API test collection | P77: Playwright · Xray API (sandbox) · GitHub Actions CI | Q77: READ (session) + EXT WRITE | R77: Redis + Xray API + PostgreSQL (xray_config read) | S77: xray_config [in-memory pool] | T77: Reads: pool TCs from session + xray_config (auth) from PostgreSQL. External: pushes TCs to Xray REST API. No test_case table write — xray_key returned to UI only. | U77: ENDPOINT UNDER TEST: POST /api/v1/sessions/{id}/export/xray GET /api/v1/jobs/{job_id}/status Test: push 5 TCs → all get Xray keys. Test: Xray auth failure → 503 returned. Test: partial failure → failed rows retryable.
A78: 10 | B78: Importing module test cases from Excel and adding to the test case pool | C78: FR-010 | D78: Design & Author | E78: Import All & Add to Pool (FE: Import from Excel panel) | F78: BE-01 | G78: Parses the uploaded Excel file using the ICE import template, extracting TC rows and mapping each column to the corresponding ICE 9-field schema field. | H78: • Parses uploaded Excel files using the ICE import template and extracts test case rows from the spreadsheet. • Maps each column to the corresponding field in the ICE 9-field schema by matching header names rather than column positions. • Transforms raw Excel data into structured test case objects ready for validation and session pool insertion. | I78: • Must parse uploaded Excel files using the ICE import template and extract all test case rows • Must map each column to the corresponding ICE 9-field schema field by matching header names, not column positions • Must parse all 9 fields correctly for each valid row • Must ignore unknown columns gracefully without failing the import • Must return ERR-010-MISSING-COLUMN when a mandatory column header is missing from the template | J78: Backend Dev | L78: 4 | M78: 1 | N78: =MAX(ROUND(M78*1.2/0.25,0)*0.25,0.25) -> 1.25 | O78: GitHub Copilot — generate Excel parser + header mapper Claude — column mapping strategy | P78: openpyxl / Apache POI · Spring Boot · Jackson | Q78: WRITE (session) | R78: Redis (session only) | S78: [in-memory pool] | T78: Parses .xlsx columns by header. Writes TC rows to in-memory pool. No test_case / test_step write. | U78: ENDPOINT YOU CREATE: POST /api/v1/sessions/{id}/import/excel Content-Type: multipart/form-data Body: file (binary .xlsx) Response 200: {imported: int, failed: int, tcs: [{tc_id, ...9 fields, valid: bool, errors?: [string]}]} Errors: 400 ERR-010-FORMAT (wrong columns), 400 ERR-010-EMPTY (no data rows)
A79: 10 | B79: Importing module test cases from EXCEL and creating user journeys | C79: FR-010 | D79: Design & Author | E79: Import All & Add to Pool (FE: Import from Excel panel) | F79: BE-02 | G79: Validates the imported Excel rows against the 9-field schema before adding them to the session pool, flagging rows with missing mandatory fields. | H79: • Validates imported Excel rows against the 9-field schema requirements before allowing them into the session pool. • Checks that all mandatory fields are present, TC-ID values are unique per tenant, and field formats are correct. • Flags rows that fail validation with specific error reasons rather than silently discarding them. | I79: • Must validate that all mandatory fields are present in each imported row before allowing it into the session pool • Must return ERR-010-MISSING-TCID when a row is missing the TC-ID field • Must return ERR-010-DUPLICATE-TCID when a TC-ID value already exists for the tenant • Must return ERR-010-INVALID-STATUS when the Status field contains a value not in the allowed list • Must flag and reject rows that fail validation while continuing to process valid rows | J79: Backend Dev | K79: FR-010 / BE-01 | L79: 3 | M79: 0.75 | N79: =MAX(ROUND(M79*1.2/0.25,0)*0.25,0.25) -> 1 | O79: GitHub Copilot — generate row validator + error collector Claude — bulk import error strategy | P79: Spring Boot · Java Bean Validation · ICE DB | Q79: WRITE (session) | R79: Redis (session only) | S79: [in-memory pool] | T79: Parses .xlsx columns by header. Writes TC rows to in-memory pool. No test_case / test_step write. | U79: INTERNAL — import validation. Called inside FR-010 BE-01 after parsing. Checks: all 9 mandatory fields present, no duplicate TC-IDs in batch. Returns: [{tc_id, valid, errors}] per row. Not a standalone HTTP endpoint.
A80: 10 | B80: Importing module test cases from EXCEL and creating user journeys | C80: FR-010 | D80: Design & Author | E80: Import All & Add to Pool (FE: Import from Excel panel) | F80: BE-03 | G80: Adds the validated imported TCs to the Redis session pool, assigning each a unique TC ID and an import source tag for traceability. | H80: • Adds validated imported test cases to the Redis session pool after FR-012 validation completes successfully. • Assigns each test case a unique TC-ID and attaches an import source tag for traceability of origin. • Processes imports in all-or-nothing batches of 50 rows, with ICE DB persistence deferred until explicit user save or export action. | I80: • Must add validated imported test cases to the Redis session pool only after all FR-012 validations pass • Must assign each imported test case a unique TC-ID if not provided, or use the provided TC-ID if valid • Must attach an import source tag to each TC for traceability of its origin • Must write all valid rows to the session pool and make them immediately readable by FR-006 chat view • Must not write failed rows to the session pool and report each with its row index and failure reason • Must roll back only the failed batch on batch failure while allowing subsequent batches to continue • Must write zero rows to any ICE DB table during the import process | J80: Backend Dev | K80: FR-010 / BE-02 | L80: 4 | M80: 1 | N80: =MAX(ROUND(M80*1.2/0.25,0)*0.25,0.25) -> 1.25 | O80: GitHub Copilot — generate repository layer + batch save Claude — transaction boundary design | P80: Spring Data JPA · PostgreSQL · Spring Boot · @Transactional | Q80: WRITE (session) | R80: Redis (session only) | S80: [in-memory pool] | T80: Parses .xlsx columns by header. Writes TC rows to in-memory pool. No test_case / test_step write. | U80: INTERNAL — import pool persistence. Writes validated TCs to in-session pool (Redis ice:session:{id}:import_pool). NOTE: only writes to session — NOT to test_case DB table at this stage. Not a standalone HTTP endpoint. | V80: → FR-012 BE-01 ICE DB: test_case rows written (7 fields + audit). FR-012 BE-01 (Schema Validator) reads newly persisted rows for validation.
A81: 10 | B81: Importing module test cases from EXCEL and creating user journeys | C81: FR-010 | D81: Design & Author | E81: Import All & Add to Pool (FE: Import from Excel panel) | F81: FE-01 | G81: Renders the Import from Excel panel with a file upload dropzone, import summary, and flagged row table after import completes. | H81: • Renders the Import from Excel panel featuring a file upload dropzone for .xlsx template files. • Displays an import summary showing the count of successfully imported test cases, failed row count, and detailed error list. • Presents a flagged row table after import completes, allowing users to review and correct validation failures. | I81: • Must render the Import from Excel panel with a file upload dropzone accepting .xlsx template files • Must trigger the import process immediately upon file upload • Must display an import summary showing the count of successfully imported test cases and the count of failed rows • Must present a flagged row table listing each failed row with its row number and specific error code • Must show the import summary and flagged row table only after the import completes | J81: Frontend Dev | L81: 3 | M81: 0.75 | N81: =MAX(ROUND(M81*1.2/0.25,0)*0.25,0.25) -> 1 | O81: v0.dev — generate import summary component GitHub Copilot — error list rendering | P81: React · TypeScript · Tailwind CSS · react-dropzone | Q81: WRITE (session) | R81: Redis (session only) | S81: [in-memory pool] | T81: Parses .xlsx columns by header. Writes TC rows to in-memory pool. No test_case / test_step write. | U81: ENDPOINT YOU CALL (defined in FR-010 BE-01): POST /api/v1/sessions/{id}/import/excel Send: multipart/form-data with xlsx file. On 200: render TC rows in pool table. Show per-row validation errors inline. On 400 ERR-010-FORMAT: show 'Wrong column format' error with column name guidance.
A82: 10 | B82: Importing module test cases from EXCEL and creating user journeys | C82: FR-010 | D82: Design & Author | E82: Import All & Add to Pool (FE: Import from Excel panel) | F82: INT-01 | G82: Validates the full Excel import happy path: template uploaded, rows parsed, valid TCs added to pool, flagged rows shown with reasons. | H82: • Validates the complete Excel import happy path from template upload through row parsing and valid test case insertion into the session pool. • Verifies that all successfully parsed rows are persisted with correct field values matching the source Excel data. • Confirms that flagged rows are displayed with specific validation failure reasons for user review. | I82: • Must validate that all successfully parsed rows from the Excel template are added to the session pool • Must verify that the row count in the session pool matches the count of valid rows in the import file • Must confirm that all 7 persisted fields for each TC match the corresponding values in the source Excel file • Must display an import summary showing 0 errors when all rows are valid • Must make all imported TCs immediately readable after the import completes | J82: QA / Both Devs | K82: FR-010 / All BE + FE | L82: 4 | M82: 1 | N82: =MAX(ROUND(M82*1.2/0.25,0)*0.25,0.25) -> 1.25 | O82: Playwright AI — generate import E2E Claude — generate import test data (valid + error cases) | P82: Playwright · PostgreSQL (verification) · GitHub Actions CI | Q82: WRITE (session) | R82: Redis (session only) | S82: [in-memory pool] | T82: Parses .xlsx columns by header. Writes TC rows to in-memory pool. No test_case / test_step write. | U82: ENDPOINT UNDER TEST: POST /api/v1/sessions/{id}/import/excel Test: valid 9-column xlsx → all TCs imported. Test: missing 'scenario' column → ERR-010-FORMAT.
A83: 10 | B83: Importing module test cases from EXCEL and creating user journeys | C83: FR-010 | D83: Design & Author | E83: Import All & Add to Pool (FE: Import from Excel panel) | F83: INT-02 | G83: Validates Excel import error handling: wrong template format, missing mandatory columns, and partially valid files all produce appropriate user feedback. | H83: • Validates Excel import error handling across multiple failure scenarios including wrong template format and missing mandatory columns. • Tests the system's handling of partially valid files containing a mix of correct and invalid test case rows. • Verifies that appropriate user feedback is generated for each error type, including partial success reporting and specific row-level error messages. | I83: • Must reject files with wrong template format and return a clear error without writing any rows • Must return an error when mandatory columns are missing from the template • Must save valid rows and reject invalid rows when processing partially valid files • Must display an error list showing correct row numbers for each invalid row • Must allow re-import of previously failed rows after they are corrected in the file | J83: QA / Both Devs | K83: FR-010 / INT-01 | L83: 3 | M83: 0.75 | N83: =MAX(ROUND(M83*1.2/0.25,0)*0.25,0.25) -> 1 | O83: Playwright AI — generate error scenario import tests | P83: Playwright · openpyxl (test file builder) · GitHub Actions CI | Q83: WRITE (session) | R83: Redis (session only) | S83: [in-memory pool] | T83: Parses .xlsx columns by header. Writes TC rows to in-memory pool. No test_case / test_step write. | U83: ENDPOINT UNDER TEST: POST /api/v1/sessions/{id}/import/excel Test: duplicate TC-IDs in file → flagged rows. Test: 500-row file → all rows processed. Test: empty file → 400 ERR-010-EMPTY.
A84: 11 | B84: Importing module test cases from Xray and adding to the test case pool | C84: FR-011 | D84: Design & Author | E84: Import & Add to Pool (FE: Import from Xray panel) | F84: BE-01 | G84: Authenticates with the Xray API and retrieves the list of test cases from the configured project, filtered by the user's selected criteria. | H84: • Authenticates with the Xray API using configured tenant credentials and retrieves test cases from the specified project. • Proxies user-selected filter parameters including project, module, type, and status to the Xray API query. • Returns a filtered list of TC-IDs with their descriptions for user selection before full import. | I84: • Must authenticate with the Xray API using the tenant's configured credentials from xray_config • Must retrieve test cases from the Xray project specified in the tenant configuration • Must apply user-selected filter parameters (project, module, type, status) using AND logic • Must return an empty array when no test cases match the selected filters • Must return ERR-011-XRAY-UNAVAILABLE when the Xray API is unreachable or returns an error | J84: Backend Dev | L84: 4 | M84: 1 | N84: =MAX(ROUND(M84*1.2/0.25,0)*0.25,0.25) -> 1.25 | O84: GitHub Copilot — generate Xray filter proxy + param builder Claude — AND/OR filter logic design | P84: Xray REST API · Spring Boot · Spring WebClient | Q84: READ (session) + EXT READ | R84: Redis + Xray API + PostgreSQL (xray_config read) | S84: xray_config [in-memory pool] | T84: Reads: xray_config (auth) from PostgreSQL. Fetches filtered TCs from Xray REST API. Writes to pool. No test_case write. | U84: ENDPOINT YOU CREATE: GET /api/v1/xray/tcs Query params: project_key, module?, type?, status?, label?, page, page_size Response 200: {tcs: [{xray_key, summary, type, status, labels}], total, page, pages} Proxies to Xray REST API with tenant auth. Errors: 401 Xray auth failed, 404 project not found
A85: 11 | B85: Importing module test cases from Xray and creating user journeys | C85: FR-011 | D85: Design & Author | E85: Import & Add to Pool (FE: Import from Xray panel) | F85: BE-02 | G85: Maps the retrieved Xray test issues to the ICE 9-field TC schema and adds them to the Redis session pool with an xray-import source tag. | H85: • Executes a single batch Xray API call to fetch complete test step details for all user-selected TC-IDs. • Maps retrieved Xray test issues to the ICE 9-field test case schema according to tenant-specific field mappings. • Adds the mapped test cases to the Redis session pool with an xray-import source tag for origin tracking. | I85: • Must execute a single batch Xray API call to fetch complete test step details for all user-selected TC-IDs when the count is ≤ 100 • Must auto-split into multiple API calls when the TC-ID count exceeds 100 • Must map each retrieved Xray test issue to the ICE 9-field schema using tenant-specific field mappings from xray_config • Must return a response containing { tcId, steps[] } for each TC • Must log and skip any TC-IDs that are missing from the Xray API response without failing the entire import • Must add all successfully mapped test cases to the Redis session pool with an xray-import source tag | J85: Backend Dev | K85: FR-011 / BE-01 | L85: 4 | M85: 1 | N85: =MAX(ROUND(M85*1.2/0.25,0)*0.25,0.25) -> 1.25 | O85: GitHub Copilot — generate batch fetch + split logic Claude — API limit handling strategy | P85: Xray REST API · Spring Boot · Spring WebClient | Q85: READ (session) + EXT READ | R85: Redis + Xray API + PostgreSQL (xray_config read) | S85: xray_config [in-memory pool] | T85: Reads: xray_config (auth) from PostgreSQL. Fetches filtered TCs from Xray REST API. Writes to pool. No test_case write. | U85: ENDPOINT YOU CREATE: POST /api/v1/xray/tcs/steps Request: {xray_keys: string[]} Response 200: {steps: [{xray_key, steps: [{step_id, action, expected_result, order}]}]} Batch fetches all steps in one Xray API call. Errors: 400 empty xray_keys array, 503 Xray unavailable
A86: 11 | B86: Importing module test cases from Xray and creating user journeys | C86: FR-011 | D86: Design & Author | E86: Import & Add to Pool (FE: Import from Xray panel) | F86: BE-03 | G86: Handles Xray API pagination, fetching all matching test cases across multiple pages before adding them to the session pool in a single operation. | H86: • Handles Xray API pagination to retrieve all matching test cases when result sets exceed single-page limits. • Maps Xray test step fields to the ICE 10-field standard schema using configurable per-tenant field mappings. • Adds all fetched and mapped test cases to the session pool in a single atomic operation after pagination completes. | I86: • Must handle Xray API pagination and fetch all matching test cases across multiple pages before adding them to the session pool • Must map Xray test step fields to the ICE 10-field standard schema using configurable per-tenant field mappings from xray_config • Must store unmapped Xray fields in the 'additional' field • Must apply tenant-specific mapping configuration retrieved from xray_config • Must add all fetched and mapped test cases to the in-memory session pool without writing to the ICE database | J86: Backend Dev | K86: FR-011 / BE-02 | L86: 3 | M86: 0.75 | N86: =MAX(ROUND(M86*1.2/0.25,0)*0.25,0.25) -> 1 | O86: GitHub Copilot — generate Xray → ICE mapper Claude — field mapping design | P86: Spring Boot · Jackson · ICE DB | Q86: READ (session) + EXT READ | R86: Redis + Xray API + PostgreSQL (xray_config read) | S86: xray_config [in-memory pool] | T86: Reads: xray_config (auth) from PostgreSQL. Fetches filtered TCs from Xray REST API. Writes to pool. No test_case write. | U86: INTERNAL — Xray to ICE schema mapper. Maps Xray Test issue fields to ICE 9-field TC. Called inside FR-011 BE-01 / BE-02 responses. Not a standalone HTTP endpoint. | V86: → FR-012 BE-01 Mapped TC objects (ICE schema) held in session. FR-012 BE-01 validates structure before FR-017 persists to DB.
A87: 11 | B87: Importing module test cases from Xray and creating user journeys | C87: FR-011 | D87: Design & Author | E87: Import & Add to Pool (FE: Import from Xray panel) | F87: FE-01 | G87: Renders the Import from Xray panel with project and filter selectors, an import count preview, and an Import & Add to Pool button. | H87: • Renders the Import from Xray panel with project selector and filter controls for module, type, and status. • Displays an import count preview showing how many test cases match the current filter criteria. • Provides an Import & Add to Pool button that triggers the batch fetch and schema mapping workflow. | I87: • Must render the Import from Xray panel with project selector and all 4 filter controls for module, type, and status • Must display an import count preview showing how many test cases match the current filter criteria • Must provide an Import & Add to Pool button that triggers the import process • Must fire one API call with all selected filters when search is triggered • Must display result list showing TC-ID + Description for each matching test case | J87: Frontend Dev | L87: 4 | M87: 1 | N87: =MAX(ROUND(M87*1.2/0.25,0)*0.25,0.25) -> 1.25 | O87: v0.dev — generate filter panel + result list GitHub Copilot — filter state management | P87: React · TypeScript · Tailwind CSS · React Query | Q87: READ (session) + EXT READ | R87: Redis + Xray API + PostgreSQL (xray_config read) | S87: xray_config [in-memory pool] | T87: Reads: xray_config (auth) from PostgreSQL. Fetches filtered TCs from Xray REST API. Writes to pool. No test_case write. | U87: ENDPOINT YOU CALL (defined in FR-011 BE-01): GET /api/v1/xray/tcs?project_key=X&type=Y Render 4-filter panel. On filter change: debounce 400ms then call GET /xray/tcs. Show loading skeleton while in flight. Paginate results with Load More button.
A88: 11 | B88: Importing module test cases from Xray and creating user journeys | C88: FR-011 | D88: Design & Author | E88: Import & Add to Pool (FE: Import from Xray panel) | F88: FE-02 | G88: Displays the import result summary after the Xray import completes, showing how many TCs were added and flagging any that failed schema mapping. | H88: • Displays checkbox selection interface for TC-IDs returned from Xray filter results. • Triggers batch step fetch (BE-02), schema mapping (BE-03), and session pool write when the Import button is clicked. • Shows import result summary after completion with counts of added test cases and any schema mapping failures, with no ICE DB write occurring at this stage. | I88: • Must display checkbox selection interface for TC-IDs returned from Xray filter results • Must implement Select All that selects current page only • Must disable Import button until at least 1 TC is selected • Must show spinner on Import button during fetch, map, and write operations • Must trigger batch step fetch (BE-02), schema mapping (BE-03), and session pool write when Import button is clicked • Must display import result summary after completion showing how many TCs were added and flagging any that failed validation • Must make imported TCs visible in session pool after completion | J88: Frontend Dev | K88: FR-011 / FE-01 | L88: 3 | M88: 0.75 | N88: =MAX(ROUND(M88*1.2/0.25,0)*0.25,0.25) -> 1 | O88: GitHub Copilot — generate checkbox selection + import trigger Cursor — state sync between filter + selection | P88: React · TypeScript · Tailwind CSS | Q88: READ (session) + EXT READ | R88: Redis + Xray API + PostgreSQL (xray_config read) | S88: xray_config [in-memory pool] | T88: Reads: xray_config (auth) from PostgreSQL. Fetches filtered TCs from Xray REST API. Writes to pool. No test_case write. | U88: ENDPOINTS YOU CALL: 1. POST /api/v1/xray/tcs/steps (FR-011 BE-02) — fetch steps for selected TCs 2. POST /api/v1/sessions/{id}/import/pool (FR-011 internal) — add fetched TCs to pool On success: show 'N TCs imported' toast and add rows to pool table.
A89: 11 | B89: Importing module test cases from Xray and creating user journeys | C89: FR-011 | D89: Design & Author | E89: Import & Add to Pool (FE: Import from Xray panel) | F89: INT-01 | G89: Validates the full Xray import flow: project selected, TCs fetched, mapped to 9-field schema, added to session pool, and result summary shown. | H89: • Validates the complete Xray import flow from project selection through TC fetching, 9-field schema mapping, and session pool insertion. • Verifies that filtered and selected test cases are written correctly to the Redis session pool with proper field mappings. • Confirms that no ICE DB rows are written at import time, with persistence deferred to explicit save or export actions. | I89: • Must validate the complete Xray import flow from project selection through TC fetching, 10-field schema mapping, and session pool insertion • Must write filtered and selected test cases to the Redis session pool with proper field mapping • Must display imported TCs in session pool with correct 10-field standard values • Must write zero rows to ICE DB during import • Must preserve Xray-specific fields in the mapping • Must show import summary with count of imported TCs | J89: QA / Both Devs | K89: FR-011 / All BE + FE | L89: 5 | M89: 1.25 | N89: =MAX(ROUND(M89*1.2/0.25,0)*0.25,0.25) -> 1.5 | O89: Playwright AI — generate Xray import E2E Postman AI — generate Xray API test collection | P89: Playwright · Xray API (sandbox) · GitHub Actions CI | Q89: READ (session) + EXT READ | R89: Redis + Xray API + PostgreSQL (xray_config read) | S89: xray_config [in-memory pool] | T89: Reads: xray_config (auth) from PostgreSQL. Fetches filtered TCs from Xray REST API. Writes to pool. No test_case write. | U89: ENDPOINTS UNDER TEST: GET /api/v1/xray/tcs POST /api/v1/xray/tcs/steps Test: filter by module → correct TC subset. Test: select 5 TCs → steps fetched + in pool.
A90: 12 | B90: Import Validation service for FR-010 and FR-011 | C90: FR-012 | D90: Design & Author | E90: Import All & Add to Pool / Import & Add to Pool (BE: validation called on import) | F90: BE-01 | G90: Runs the shared import validation service on all incoming TCs from both Excel (FR-010) and Xray (FR-011) imports, checking mandatory fields and detecting duplicates before pool entry. | H90: • Runs the shared import validation service on all incoming test cases from both Excel (FR-010) and Xray (FR-011) import sources. • Provides centralized validation logic that checks the 10-field standard schema requirements consistently across import types. • Validates mandatory field presence, field format correctness, and schema compliance before allowing test cases into the session pool. | I90: • Must run the shared import validation service on all incoming test cases from both Excel (FR-010) and Xray (FR-011) import sources • Must provide centralized validation logic that checks the 10-field standard schema requirements consistently across import sources • Must validate mandatory fields: Test Case Id, Test Case Description, Test Step, Expected Result • Must skip optional fields if absent without flagging as error • Must return validation result in format { valid, errors[] } | J90: Backend Dev | L90: 3 | M90: 0.75 | N90: =MAX(ROUND(M90*1.2/0.25,0)*0.25,0.25) -> 1 | O90: GitHub Copilot — generate validator service + error schema Claude — mandatory vs optional field design | P90: Spring Boot · Java Bean Validation · OpenAPI 3.0 | Q90: READ (session) | R90: Redis (session only) | S90: [in-memory pool] | T90: Validates mandatory fields + duplicate detection against in-memory pool. No DB write on pass. Flags invalid rows for FE display. | U90: INTERNAL — schema validator service. Called by FR-010 BE-02 and FR-011 FE-02. Validates all 9 mandatory TC fields present and non-empty. Returns [{tc_id, valid, errors}]. Not a standalone HTTP endpoint.
A91: 12 | B91: Import Validation service for FR-009 and FR010 | C91: FR-012 | D91: Design & Author | E91: Import All & Add to Pool / Import & Add to Pool (BE: validation called on import) | F91: BE-02 | G91: Assigns a validation status (valid, flagged-incomplete, flagged-duplicate) to each imported TC and returns a structured validation report to the calling import service. | H91: • Assigns a validation status of valid, flagged-incomplete, or flagged-duplicate to each imported test case based on validation results. • Detects duplicate TC-IDs both within the current import batch and against existing database records for the same project. • Returns a structured validation report to the calling service containing status assignments and specific error details for flagged test cases. | I91: • Must assign validation status of valid, flagged-incomplete, or flagged-duplicate to each imported test case based on validation results • Must detect duplicate TC-IDs within the current import batch and flag with ERR-012-DUPLICATE • Must detect duplicate TC-IDs against existing database records for the same tenant and flag with ERR-012-DUPLICATE • Must list all duplicates with their row index in the error report • Must return a structured validation summary with status and error details per TC | J91: Backend Dev | K91: FR-012 / BE-01 | L91: 3 | M91: 0.75 | N91: =MAX(ROUND(M91*1.2/0.25,0)*0.25,0.25) -> 1 | O91: GitHub Copilot — generate duplicate detector + DB check | P91: Spring Boot · Spring Data JPA · PostgreSQL | Q91: READ (session) | R91: Redis (session only) | S91: [in-memory pool] | T91: Validates mandatory fields + duplicate detection against in-memory pool. No DB write on pass. Flags invalid rows for FE display. | U91: INTERNAL — duplicate detection. Checks: TC-ID uniqueness within import batch AND against existing DB records for same tenant. Returns: [{tc_id, duplicate: bool, source}]. Not a standalone HTTP endpoint. | V91: → FR-017 BE-01 Validated TC list (duplicates removed, schema confirmed). FR-017 BE-01 (Test Case Entity & Repository) persists to ICE DB.
A92: 12 | B92: Import Validation service for FR-009 and FR010 | C92: FR-012 | D92: Design & Author | E92: Import All & Add to Pool / Import & Add to Pool (BE: validation called on import) | F92: INT-01 | G92: Validates that the import validation service correctly flags incomplete and duplicate TCs from both import paths before they enter the session pool. | H92: • Validates that the import validation service correctly flags incomplete and duplicate TCs from both import paths before they enter the session pool. • Import files are tested with schema violations to trigger validation errors. • Each ERR-012-* error code must be surfaced correctly during the validation process. | I92: • Must flag incomplete and duplicate TCs from both Excel and Xray import paths before they enter the session pool • Must trigger validation errors when import files contain schema violations • Must surface each ERR-012-* error code in the UI with clear messaging • Must allow valid rows in the same batch to be imported even when other rows have errors • Must match error row numbers to actual file rows for accurate identification | J92: QA / Both Devs | K92: FR-012 / All BE | L92: 3 | M92: 0.75 | N92: =MAX(ROUND(M92*1.2/0.25,0)*0.25,0.25) -> 1 | O92: Playwright AI — generate validation E2E Claude — generate import files with specific errors | P92: Playwright · openpyxl (file builder) · GitHub Actions CI | Q92: READ (session) | R92: Redis (session only) | S92: [in-memory pool] | T92: Validates mandatory fields + duplicate detection against in-memory pool. No DB write on pass. Flags invalid rows for FE display. | U92: INTERNAL SERVICE TEST (no direct HTTP endpoint). Test via: POST /api/v1/sessions/{id}/import/excel (FR-010 BE-01) and GET /api/v1/xray/tcs (FR-011 BE-01). Test: duplicate TC-IDs in batch → flagged. Test: missing 'scenario' field → validation error.
A93: 13 | B93: CLAP does test case Enrichment | C93: FR-013 | D93: Journey Stitcher | E93: Accept all high confidence / Proceed to Step 2 | F93: BE-01 | G93: Triggers the CLAP enrichment pipeline when the user enters Phase 1 of the Journey Stitcher, processing all accepted TCs from the session pool. | H93: • Triggers the CLAP enrichment pipeline when the user enters Phase 1 of the Journey Stitcher, processing all accepted TCs from the session pool. • CLAP enriches each TC with normalised precondition, confidence score, and module tag. • Enrichment results are stored in session-only data with no write to the ICE DB. | I93: • Must trigger the CLAP enrichment pipeline when the user enters Phase 1 of the Journey Stitcher • Must process all accepted TCs from the session pool through CLAP enrichment • Must enrich each TC with normalised precondition, confidence score (high/medium/low), and module tag • Must write enrichment results to session.checkpoint_data without writing to the ICE database • Must return enriched precondition and confidence level for each processed TC | J93: Backend Dev | K93: FR-003 | L93: 4 | M93: 1.5 | N93: =MAX(ROUND(M93*1.2/0.25,0)*0.25,0.25) -> 1.75 | O93: Claude API — structured output | P93: Spring Boot · CLAP client | Q93: WRITE (session) | R93: Redis + PostgreSQL (session only) | S93: session.checkpoint_data | T93: enriched_tcs[]: tc_id, precondition, confidence, reviewed, accepted. No test_case write. | U93: ENDPOINT YOU CREATE: POST /api/v1/sessions/{id}/enrich Request: {} (reads TCs from session) Response 200 (SSE stream): event: tc_enriched data: {tc_id, precondition, confidence: high|medium|low, module_tag} event: enrichment_complete data: {total, high, medium, low} Errors: 400 no TCs in session
A94: 13 | B94: CLAP does test case Enrichment | C94: FR-013 | D94: Journey Stitcher-Enrichment | E94: ✓ Accept enrichment ✗ Reject Accept all high confidence | F94: BE-02 | G94: Records the user's accept or reject decision for each enriched TC in the session checkpoint, supporting both single and bulk accept operations. | H94: • Records the user's accept or reject decision for each enriched TC in the session checkpoint, supporting both single and bulk accept operations. • PATCH /sessions/{id}/tcs/{tc_id}/review writes reviewed=true and accepted=true/false to session checkpoint_data. • Bulk endpoint accepts an array of tc_ids for processing multiple decisions at once. | I94: • Must record user's accept or reject decision for each enriched TC in session.checkpoint_data • Must support both single and bulk accept operations • Must set accepted=true and reviewed=true in session checkpoint for per-TC accept via PATCH /sessions/{id}/tcs/{tc_id}/review • Must set accepted=false and reviewed=true in session checkpoint for per-TC reject • Must update all high-confidence TCs in one call for bulk accept operations • Must write decisions to session.checkpoint_data only without writing to the ICE database | J94: Backend Dev | K94: FR-013 / BE-01 | L94: 1 | M94: 0.5 | N94: =MAX(ROUND(M94*1.2/0.25,0)*0.25,0.25) -> 0.5 | O94: GitHub Copilot — PATCH session state handler | P94: Spring Boot · Spring Data JPA · Redis | Q94: WRITE (session) | R94: Redis + PostgreSQL (session only) | S94: session.checkpoint_data | T94: enriched_tcs[]: tc_id, reviewed, accepted updated in session. | U94: PATCH /api/v1/sessions/{id}/tcs/{tc_id}/review Body: {accepted: bool} Response 200: {tc_id, reviewed, accepted} POST /api/v1/sessions/{id}/tcs/bulk-accept Body: {confidence: 'high'} Response 200: {updated: int}
A95: 13 | B95: CLAP does test case Enrichment | C95: FR-013 | D95: Journey Stitcher-Enrichment | E95: Accept all high confidence | F95: FE-01 | G95: Renders the Phase 1 Enrichment review screen showing all enriched TCs with confidence dots, enriched preconditions, and accept/reject controls. | H95: • Renders the Phase 1 Enrichment review screen showing all enriched TCs with confidence dots, enriched preconditions, and accept/reject controls. • TC list displays confidence dot and reviewed badge for each item. • Detail view shows enriched precondition, step sequence, Accept/Reject buttons, and bulk Accept all high confidence option. | I95: • Must render the Phase 1 Enrichment review screen showing all enriched TCs with confidence dots, enriched preconditions, and accept/reject controls • Must display TC list with confidence indicator and reviewed badge for each item • Must load detail view on TC click showing enriched precondition and original precondition for comparison • Must update row badge when Accept or Reject is triggered without full page reload • Must support bulk accept operation for multiple TCs | J95: Frontend Dev | K95: BE-01 | L95: 4 | M95: 1.5 | N95: =MAX(ROUND(M95*1.2/0.25,0)*0.25,0.25) -> 1.75 | O95: Cursor AI | P95: React · TypeScript | Q95: WRITE (session) | R95: Redis + PostgreSQL (session only) | S95: session.checkpoint_data | T95: UI triggers BE-01 enrichment review. checkpoint_data updated on confirm. | U95: ENDPOINT YOU CALL (defined in FR-013B BE-01): POST /api/v1/sessions/{id}/enrich Use EventSource (SSE) to stream enrichment. On tc_enriched: update TC row with confidence dot (green/amber/red) and precondition. On enrichment_complete: enable Proceed btn.
A96: 13 | B96: CLAP does test case Enrichment | C96: FR-013 | D96: Journey Stitcher-Enrichment | E96: ✓ Accept enrichment | F96: FE-02 | G96: Renders the Accept button per TC row, calling the session write API and updating the row badge to Accepted without a full page reload. | H96: • Renders the Accept button per TC row, calling the session write API and updating the row badge to Accepted without a full page reload. • Calls PATCH /sessions/{id}/tcs/{tc_id}/review with accepted=true on button click. • Updates confidence dot and reviewed badge on the TC row without requiring a page reload. | I96: • Must render the Accept button per TC row • Must call PATCH /sessions/{id}/tcs/{tc_id}/review with accepted=true on button click • Must update TC row badge to Accepted without a full page reload • Must update confidence dot and reviewed status indicator after accept • Must increment reviewed counter on accept | J96: Frontend Dev | K96: FR-013 / BE-02 | L96: 1 | M96: 0.5 | N96: =MAX(ROUND(M96*1.2/0.25,0)*0.25,0.25) -> 0.5 | O96: Cursor AI — component from mockup | P96: React · TypeScript · Tailwind CSS | Q96: WRITE (session) | R96: Redis + PostgreSQL (session only) | S96: session.checkpoint_data | T96: UI calls BE-02. checkpoint_data.enriched_tcs[tc_id].accepted = true. | U96: ENDPOINT YOU CALL (FR-013 BE-02): PATCH /api/v1/sessions/{id}/tcs/{tc_id}/review Body: {accepted: true}
A97: 13 | B97: CLAP does test case Enrichment | C97: FR-013 | D97: Journey Stitcher-Enrichment | E97: ✗ Reject | F97: FE-03 | G97: Renders the Reject button per TC row, restoring the original unenriched precondition on that row and marking it as Rejected. | H97: • Renders the Reject button per TC row, restoring the original unenriched precondition on that row and marking it as Rejected. • Calls PATCH /sessions/{id}/tcs/{tc_id}/review with accepted=false on button click. • Restores original precondition display on the TC row after rejection. | I97: • Must render the Reject button per TC row • Must call PATCH /sessions/{id}/tcs/{tc_id}/review with accepted=false on button click • Must restore the original unenriched precondition on that row when rejected • Must mark the TC row badge as Rejected • Must increment reviewed counter on reject | J97: Frontend Dev | K97: FR-013 / BE-02 | L97: 1 | M97: 0.5 | N97: =MAX(ROUND(M97*1.2/0.25,0)*0.25,0.25) -> 0.5 | O97: Cursor AI — component from mockup | P97: React · TypeScript · Tailwind CSS | Q97: WRITE (session) | R97: Redis + PostgreSQL (session only) | S97: session.checkpoint_data | T97: UI calls BE-02. checkpoint_data.enriched_tcs[tc_id].accepted = false. | U97: ENDPOINT YOU CALL (FR-013 BE-02): PATCH /api/v1/sessions/{id}/tcs/{tc_id}/review Body: {accepted: false}
A98: 13 | B98: CLAP does test case Enrichment | C98: FR-013 | D98: Journey Stitcher-Enrichment | E98: Accept all high confidence | F98: FE-04 | G98: Renders the Accept All High Confidence button that bulk-accepts all TCs with a high confidence score in a single API call. | H98: • Renders the Accept All High Confidence button that bulk-accepts all TCs with a high confidence score in a single API call. • Calls POST /sessions/{id}/tcs/bulk-accept with confidence=high parameter. • Updates all high-confidence TC rows to reviewed and accepted status in one action. | I98: • Must render the Accept All High Confidence button visible and enabled when high-confidence TCs exist • Must call POST /sessions/{id}/tcs/bulk-accept with confidence=high parameter on button click • Must update all high-confidence TC rows to display reviewed badge after successful API response • Must update the reviewed counter to reflect the total number of accepted TCs • Must disable or hide the button when zero high-confidence TCs remain unreviewed | J98: Frontend Dev | K98: FR-013 / BE-02 | L98: 1 | M98: 0.5 | N98: =MAX(ROUND(M98*1.2/0.25,0)*0.25,0.25) -> 0.5 | O98: Cursor AI — component from mockup | P98: React · TypeScript · Tailwind CSS | Q98: WRITE (session) | R98: Redis + PostgreSQL (session only) | S98: session.checkpoint_data | T98: UI calls BE-02 bulk. All high-confidence tc rows updated in session. | U98: ENDPOINT YOU CALL (FR-013 BE-02): POST /api/v1/sessions/{id}/tcs/bulk-accept Body: {confidence: 'high'}
A99: 13 | B99: CLAP does test case Enrichment | C99: FR-013 | D99: Journey Stitcher-Enrichment | E99: Proceed to Step 2 → | F99: FE-05 | G99: Renders the Proceed to Step 2 button, enabled only after at least one TC has been reviewed, navigating to the Journey Proposal screen. | H99: • Renders the Proceed to Step 2 button, enabled only after at least one TC has been reviewed, navigating to the Journey Proposal screen. • Button is enabled only when at least one TC has been reviewed with accepted or rejected status. • On click, navigates the user to Phase 2 Journey Review screen. | I99: • Must render the Proceed to Step 2 button in a disabled state when zero TCs have been reviewed • Must enable the button when at least one TC has been reviewed with accepted or rejected status • Must navigate to the Journey Proposal screen on button click • Must display a hint label showing the count of reviewed TCs • Must reject navigation if the session state does not contain at least one reviewed TC | J99: Frontend Dev | K99: FR-013 / FE-01 | L99: 0.5 | M99: 0.25 | N99: =MAX(ROUND(M99*1.2/0.25,0)*0.25,0.25) -> 0.25 | O99: Cursor AI — component from mockup | P99: React · TypeScript · Tailwind CSS | Q99: WRITE (session) | R99: Redis + PostgreSQL (session only) | S99: session.checkpoint_data | T99: Navigation gate. No new session write — reads reviewed count from checkpoint_data. | U99: No API call. Reads session state to gate button. On click: jsGo(2) — navigate to Phase 2.
A100: 14 | B100: CLAP proposes journeys from the accepted TCs | C100: FR-014 | D100: Journey Stitcher - Journeys | E100: Proceed to Step 2 → (triggers dependency graph build) | F100: BE-01 | G100: Builds a dependency graph from the enriched accepted TCs to determine the natural sequence in which TCs flow into journeys. | H100: • Builds a dependency graph from the enriched accepted TCs to determine the natural sequence in which TCs flow into journeys. • ICE builds a directed TC dependency graph per module from enriched preconditions. • Dependency graph is stored in session data. | I100: • Must build a directed TC dependency graph per module from enriched preconditions of accepted TCs • Must detect and flag circular dependencies in the graph with a clear error or warning • Must represent isolated TCs with no dependencies as singleton nodes in the graph • Must generate correct directed edges from TC preconditions to dependent TCs • Must store the complete dependency graph in session.checkpoint_data | J100: Backend Dev | K100: BE-01 | L100: 5 | M100: 2 | N100: =MAX(ROUND(M100*1.2/0.25,0)*0.25,0.25) -> 2.5 | O100: LangGraph | P100: Java · JGraphT | Q100: WRITE (session) | R100: Redis + PostgreSQL (session only) | S100: session.checkpoint_data | T100: Dependency graph built from enriched preconditions. Stored in checkpoint_data.graph. | U100: ENDPOINT YOU CREATE: POST /api/v1/sessions/{id}/graph Request: {} (reads enriched TCs from session) Response 200: {nodes: [{tc_id, module}], edges: [{from_tc, to_tc, type}], cycles: [{tc_ids}] (warnings)} Errors: 400 enrichment not completed yet
...

Sheet Timeline Summary
B2: ICE 3.0 — Timeline Summary
B3: Change the blue cells to recalculate the timeline
B5: Team Configuration (change these — blue = input)
B6: Setting | C6: Value | D6: Unit | E6: Note
B7: BE developers | C7: 5 | D7: devs | E7: Handles BE + INT tasks
B8: FE developers | C8: 5 | D8: devs | E8: Handles FE tasks
C9: 0.8
C10: 1.15
B11: Working days / week | C11: 5 | D11: days | E11: Standard 5-day work week
B13: Raw Effort from Detailed Requirements (auto-calculated)
B14: Type | C14: With AI + Buffer (days) | D14: Without AI (days) | E14: Source
B15: Backend (BE) | C15: =SUMPRODUCT(('Detailed Requirements'!J$2:J$5000="Backend Dev")*ISNUMBER('Detailed Requirements'!N$2:N$5000)*IF(ISNUMBER('Detailed Requirements'!N$2:N$5000),'Detailed Requirements'!N$2:N$5000,0)) -> 356 | D15: =SUMPRODUCT(('Detailed Requirements'!J$2:J$5000="Backend Dev")*ISNUMBER('Detailed Requirements'!L$2:L$5000)*IF(ISNUMBER('Detailed Requirements'!L$2:L$5000),'Detailed Requirements'!L$2:L$5000,0)) -> 883 | E15: BE/FE col = 'Backend Dev'
B16: Frontend (FE) | C16: =SUMPRODUCT(('Detailed Requirements'!J$2:J$5000="Frontend Dev")*ISNUMBER('Detailed Requirements'!N$2:N$5000)*IF(ISNUMBER('Detailed Requirements'!N$2:N$5000),'Detailed Requirements'!N$2:N$5000,0)) -> 178.25 | D16: =SUMPRODUCT(('Detailed Requirements'!J$2:J$5000="Frontend Dev")*ISNUMBER('Detailed Requirements'!L$2:L$5000)*IF(ISNUMBER('Detailed Requirements'!L$2:L$5000),'Detailed Requirements'!L$2:L$5000,0)) -> 398.25 | E16: BE/FE col = 'Frontend Dev'
B17: Integration (INT) | C17: =SUMPRODUCT(('Detailed Requirements'!J$2:J$5000="QA / Both Devs")*ISNUMBER('Detailed Requirements'!N$2:N$5000)*IF(ISNUMBER('Detailed Requirements'!N$2:N$5000),'Detailed Requirements'!N$2:N$5000,0)) -> 125.5 | D17: =SUMPRODUCT(('Detailed Requirements'!J$2:J$5000="QA / Both Devs")*ISNUMBER('Detailed Requirements'!L$2:L$5000)*IF(ISNUMBER('Detailed Requirements'!L$2:L$5000),'Detailed Requirements'!L$2:L$5000,0)) -> 309 | E17: BE/FE col = 'QA / Both Devs'
B18: TOTAL | C18: =C15+C16+C17 -> 659.75 | D18: =D15+D16+D17 -> 1590.25 | E18: Sum
B20: Duration
C21: With AI (weeks) | D21: Without AI (weeks) | E21: How it's calculated
B22: Calendar weeks (BE+FE parallel per FR · FRs sequential) | C22: =ROUND('FR Schedule'!G68/C11,1) -> 20.9 | D22: =ROUND('FR Schedule'!H68/C11,1) -> 63.6 | E22: FR Schedule cumulative total ÷ working days per week
B26: Recommended (Realistic) Summary
C27: With AI | D27: Without AI
B28: Calendar weeks (w/ AI) | C28: ='Timeline Summary'!C22 -> 20.9 | D28: ='Timeline Summary'!D22 -> 63.6
B29: Calendar months (approx) | C29: =ROUND(C28/4.33,1) -> 4.8 | D29: =ROUND(D28/4.33,1) -> 14.7
B30: Calendar weeks (w/o AI) | C30: ='Timeline Summary'!D22 -> 63.6 | D30: ='Timeline Summary'!D22 -> 63.6
B31: AI saving (weeks) | C31: =C30-C28 -> 42.7 | D31: 0
B32: AI saving (%) | C32: =IF(C30>0,1-C28/C30,0) -> 0.67138365 | D32: N/A

Sheet FR Schedule
B1: ICE 3.0 — Per-FR Schedule (formulas pull from Detailed Requirements · team inputs in Timeline Summary)
B2: All durations in working days · FRs run sequentially · BE and FE parallel within each FR
B5: FR | C5: Description (from Detailed Requirements) | D5: BE wall (days) | E5: FE wall (days) | F5: INT wall (days) | G5: FR total (w/ AI) | H5: FR total (w/o AI) | I5: Cumulative (w/ AI)
B6: Design & Author
B7: FR-001 | C7: Uploading requirements | D7: =IFERROR(ROUND(SUMPRODUCT(('Detailed Requirements'!C$2:C$5000="FR-001")*('Detailed Requirements'!J$2:J$5000="Backend Dev")*IF(ISNUMBER('Detailed Requirements'!N$2:N$5000),'Detailed Requirements'!N$2:N$5000,0))/'Timeline Summary'!C7,1),0) -> 1.6 | E7: =IFERROR(ROUND(SUMPRODUCT(('Detailed Requirements'!C$2:C$5000="FR-001")*('Detailed Requirements'!J$2:J$5000="Frontend Dev")*IF(ISNUMBER('Detailed Requirements'!N$2:N$5000),'Detailed Requirements'!N$2:N$5000,0))/'Timeline Summary'!C8,1),0) -> 0.9 | F7: =IFERROR(ROUND(SUMPRODUCT(('Detailed Requirements'!C$2:C$5000="FR-001")*('Detailed Requirements'!J$2:J$5000="QA / Both Devs")*IF(ISNUMBER('Detailed Requirements'!N$2:N$5000),'Detailed Requirements'!N$2:N$5000,0))/'Timeline Summary'!C7,1),0) -> 0.5 | G7: =IFERROR(MAX(D7,E7)+F7,0) -> 2.1 | H7: =IFERROR(ROUND(SUMPRODUCT(('Detailed Requirements'!C$2:C$5000="FR-001")*('Detailed Requirements'!J$2:J$5000="Backend Dev")*IF(ISNUMBER('Detailed Requirements'!L$2:L$5000),'Detailed Requirements'!L$2:L$5000,0))/'Timeline Summary'!C7+SUMPRODUCT(('Detailed Requirements'!C$2:C$5000="FR-001")*('Detailed Requirements'!J$2:J$5000="Frontend Dev")*IF(ISNUMBER('Detailed Requirements'!L$2:L$5000),'Detailed Requirements'!L$2:L$5000,0))/'Timeline Summary'!C8+SUMPRODUCT(('Detailed Requirements'!C$2:C$5000="FR-001")*('Detailed Requirements'!J$2:J$5000="QA / Both Devs")*IF(ISNUMBER('Detailed Requirements'!L$2:L$5000),'Detailed Requirements'!L$2:L$5000,0))/'Timeline Summary'!C7,1),0) -> 9 | I7: =IFERROR(G7,0) -> 2.1
B8: FR-002 | C8: Extract, structure & load requirements to CLAP session | D8: =IFERROR(ROUND(SUMPRODUCT(('Detailed Requirements'!C$2:C$5000="FR-002")*('Detailed Requirements'!J$2:J$5000="Backend Dev")*IF(ISNUMBER('Detailed Requirements'!N$2:N$5000),'Detailed Requirements'!N$2:N$5000,0))/'Timeline Summary'!C7,1),0) -> 0.7 | E8: =IFERROR(ROUND(SUMPRODUCT(('Detailed Requirements'!C$2:C$5000="FR-002")*('Detailed Requirements'!J$2:J$5000="Frontend Dev")*IF(ISNUMBER('Detailed Requirements'!N$2:N$5000),'Detailed Requirements'!N$2:N$5000,0))/'Timeline Summary'!C8,1),0) -> 0 | F8: =IFERROR(ROUND(SUMPRODUCT(('Detailed Requirements'!C$2:C$5000="FR-002")*('Detailed Requirements'!J$2:J$5000="QA / Both Devs")*IF(ISNUMBER('Detailed Requirements'!N$2:N$5000),'Detailed Requirements'!N$2:N$5000,0))/'Timeline Summary'!C7,1),0) -> 0.2 | G8: =IFERROR(MAX(D8,E8)+F8,0) -> 0.9 | H8: =IFERROR(ROUND(SUMPRODUCT(('Detailed Requirements'!C$2:C$5000="FR-002")*('Detailed Requirements'!J$2:J$5000="Backend Dev")*IF(ISNUMBER('Detailed Requirements'!L$2:L$5000),'Detailed Requirements'!L$2:L$5000,0))/'Timeline Summary'!C7+SUMPRODUCT(('Detailed Requirements'!C$2:C$5000="FR-002")*('Detailed Requirements'!J$2:J$5000="Frontend Dev")*IF(ISNUMBER('Detailed Requirements'!L$2:L$5000),'Detailed Requirements'!L$2:L$5000,0))/'Timeline Summary'!C8+SUMPRODUCT(('Detailed Requirements'!C$2:C$5000="FR-002")*('Detailed Requirements'!J$2:J$5000="QA / Both Devs")*IF(ISNUMBER('Detailed Requirements'!L$2:L$5000),'Detailed Requirements'!L$2:L$5000,0))/'Timeline Summary'!C7,1),0) -> 2.8 | I8: =IFERROR(I7+G8,0) -> 3
B9: FR-003 | C9: ICE sends prompt to CLAP | D9: =IFERROR(ROUND(SUMPRODUCT(('Detailed Requirements'!C$2:C$5000="FR-003")*('Detailed Requirements'!J$2:J$5000="Backend Dev")*IF(ISNUMBER('Detailed Requirements'!N$2:N$5000),'Detailed Requirements'!N$2:N$5000,0))/'Timeline Summary'!C7,1),0) -> 2.3 | E9: =IFERROR(ROUND(SUMPRODUCT(('Detailed Requirements'!C$2:C$5000="FR-003")*('Detailed Requirements'!J$2:J$5000="Frontend Dev")*IF(ISNUMBER('Detailed Requirements'!N$2:N$5000),'Detailed Requirements'!N$2:N$5000,0))/'Timeline Summary'!C8,1),0) -> 0.4 | F9: =IFERROR(ROUND(SUMPRODUCT(('Detailed Requirements'!C$2:C$5000="FR-003")*('Detailed Requirements'!J$2:J$5000="QA / Both Devs")*IF(ISNUMBER('Detailed Requirements'!N$2:N$5000),'Detailed Requirements'!N$2:N$5000,0))/'Timeline Summary'!C7,1),0) -> 0.6 | G9: =IFERROR(MAX(D9,E9)+F9,0) -> 2.9 | H9: =IFERROR(ROUND(SUMPRODUCT(('Detailed Requirements'!C$2:C$5000="FR-003")*('Detailed Requirements'!J$2:J$5000="Backend Dev")*IF(ISNUMBER('Detailed Requirements'!L$2:L$5000),'Detailed Requirements'!L$2:L$5000,0))/'Timeline Summary'!C7+SUMPRODUCT(('Detailed Requirements'!C$2:C$5000="FR-003")*('Detailed Requirements'!J$2:J$5000="Frontend Dev")*IF(ISNUMBER('Detailed Requirements'!L$2:L$5000),'Detailed Requirements'!L$2:L$5000,0))/'Timeline Summary'!C8+SUMPRODUCT(('Detailed Requirements'!C$2:C$5000="FR-003")*('Detailed Requirements'!J$2:J$5000="QA / Both Devs")*IF(ISNUMBER('Detailed Requirements'!L$2:L$5000),'Detailed Requirements'!L$2:L$5000,0))/'Timeline Summary'!C7,1),0) -> 8 | I9: =IFERROR(I8+G9,0) -> 5.9
B10: FR-004 | C10: CLAP processes requirements & generates test cases | D10: =IFERROR(ROUND(SUMPRODUCT(('Detailed Requirements'!C$2:C$5000="FR-004")*('Detailed Requirements'!J$2:J$5000="Backend Dev")*IF(ISNUMBER('Detailed Requirements'!N$2:N$5000),'Detailed Requirements'!N$2:N$5000,0))/'Timeline Summary'!C7,1),0) -> 1.2 | E10: =IFERROR(ROUND(SUMPRODUCT(('Detailed Requirements'!C$2:C$5000="FR-004")*('Detailed Requirements'!J$2:J$5000="Frontend Dev")*IF(ISNUMBER('Detailed Requirements'!N$2:N$5000),'Detailed Requirements'!N$2:N$5000,0))/'Timeline Summary'!C8,1),0) -> 0.5 | F10: =IFERROR(ROUND(SUMPRODUCT(('Detailed Requirements'!C$2:C$5000="FR-004")*('Detailed Requirements'!J$2:J$5000="QA / Both Devs")*IF(ISNUMBER('Detailed Requirements'!N$2:N$5000),'Detailed Requirements'!N$2:N$5000,0))/'Timeline Summary'!C7,1),0) -> 0.6 | G10: =IFERROR(MAX(D10,E10)+F10,0) -> 1.8 | H10: =IFERROR(ROUND(SUMPRODUCT(('Detailed Requirements'!C$2:C$5000="FR-004")*('Detailed Requirements'!J$2:J$5000="Backend Dev")*IF(ISNUMBER('Detailed Requirements'!L$2:L$5000),'Detailed Requirements'!L$2:L$5000,0))/'Timeline Summary'!C7+SUMPRODUCT(('Detailed Requirements'!C$2:C$5000="FR-004")*('Detailed Requirements'!J$2:J$5000="Frontend Dev")*IF(ISNUMBER('Detailed Requirements'!L$2:L$5000),'Detailed Requirements'!L$2:L$5000,0))/'Timeline Summary'!C8+SUMPRODUCT(('Detailed Requirements'!C$2:C$5000="FR-004")*('Detailed Requirements'!J$2:J$5000="QA / Both Devs")*IF(ISNUMBER('Detailed Requirements'!L$2:L$5000),'Detailed Requirements'!L$2:L$5000,0))/'Timeline Summary'!C7,1),0) -> 6.6 | I10: =IFERROR(I9+G10,0) -> 7.7
B11: FR-005 | C11: ICE validates the CLAP response | D11: =IFERROR(ROUND(SUMPRODUCT(('Detailed Requirements'!C$2:C$5000="FR-005")*('Detailed Requirements'!J$2:J$5000="Backend Dev")*IF(ISNUMBER('Detailed Requirements'!N$2:N$5000),'Detailed Requirements'!N$2:N$5000,0))/'Timeline Summary'!C7,1),0) -> 0.5 | E11: =IFERROR(ROUND(SUMPRODUCT(('Detailed Requirements'!C$2:C$5000="FR-005")*('Detailed Requirements'!J$2:J$5000="Frontend Dev")*IF(ISNUMBER('Detailed Requirements'!N$2:N$5000),'Detailed Requirements'!N$2:N$5000,0))/'Timeline Summary'!C8,1),0) -> 0.3 | F11: =IFERROR(ROUND(SUMPRODUCT(('Detailed Requirements'!C$2:C$5000="FR-005")*('Detailed Requirements'!J$2:J$5000="QA / Both Devs")*IF(ISNUMBER('Detailed Requirements'!N$2:N$5000),'Detailed Requirements'!N$2:N$5000,0))/'Timeline Summary'!C7,1),0) -> 0.3 | G11: =IFERROR(MAX(D11,E11)+F11,0) -> 0.8 | H11: =IFERROR(ROUND(SUMPRODUCT(('Detailed Requirements'!C$2:C$5000="FR-005")*('Detailed Requirements'!J$2:J$5000="Backend Dev")*IF(ISNUMBER('Detailed Requirements'!L$2:L$5000),'Detailed Requirements'!L$2:L$5000,0))/'Timeline Summary'!C7+SUMPRODUCT(('Detailed Requirements'!C$2:C$5000="FR-005")*('Detailed Requirements'!J$2:J$5000="Frontend Dev")*IF(ISNUMBER('Detailed Requirements'!L$2:L$5000),'Detailed Requirements'!L$2:L$5000,0))/'Timeline Summary'!C8+SUMPRODUCT(('Detailed Requirements'!C$2:C$5000="FR-005")*('Detailed Requirements'!J$2:J$5000="QA / Both Devs")*IF(ISNUMBER('Detailed Requirements'!L$2:L$5000),'Detailed Requirements'!L$2:L$5000,0))/'Timeline Summary'!C7,1),0) -> 3.4 | I11: =IFERROR(I10+G11,0) -> 8.5
B12: FR-006 | C12: Rendering of test case pool table | D12: =IFERROR(ROUND(SUMPRODUCT(('Detailed Requirements'!C$2:C$5000="FR-006")*('Detailed Requirements'!J$2:J$5000="Backend Dev")*IF(ISNUMBER('Detailed Requirements'!N$2:N$5000),'Detailed Requirements'!N$2:N$5000,0))/'Timeline Summary'!C7,1),0) -> 0.5 | E12: =IFERROR(ROUND(SUMPRODUCT(('Detailed Requirements'!C$2:C$5000="FR-006")*('Detailed Requirements'!J$2:J$5000="Frontend Dev")*IF(ISNUMBER('Detailed Requirements'!N$2:N$5000),'Detailed Requirements'!N$2:N$5000,0))/'Timeline Summary'!C8,1),0) -> 2.1 | F12: =IFERROR(ROUND(SUMPRODUCT(('Detailed Requirements'!C$2:C$5000="FR-006")*('Detailed Requirements'!J$2:J$5000="QA / Both Devs")*IF(ISNUMBER('Detailed Requirements'!N$2:N$5000),'Detailed Requirements'!N$2:N$5000,0))/'Timeline Summary'!C7,1),0) -> 0.4 | G12: =IFERROR(MAX(D12,E12)+F12,0) -> 2.5 | H12: =IFERROR(ROUND(SUMPRODUCT(('Detailed Requirements'!C$2:C$5000="FR-006")*('Detailed Requirements'!J$2:J$5000="Backend Dev")*IF(ISNUMBER('Detailed Requirements'!L$2:L$5000),'Detailed Requirements'!L$2:L$5000,0))/'Timeline Summary'!C7+SUMPRODUCT(('Detailed Requirements'!C$2:C$5000="FR-006")*('Detailed Requirements'!J$2:J$5000="Frontend Dev")*IF(ISNUMBER('Detailed Requirements'!L$2:L$5000),'Detailed Requirements'!L$2:L$5000,0))/'Timeline Summary'!C8+SUMPRODUCT(('Detailed Requirements'!C$2:C$5000="FR-006")*('Detailed Requirements'!J$2:J$5000="QA / Both Devs")*IF(ISNUMBER('Detailed Requirements'!L$2:L$5000),'Detailed Requirements'!L$2:L$5000,0))/'Timeline Summary'!C7,1),0) -> 7.6 | I12: =IFERROR(I11+G12,0) -> 11
B13: FR-007 | C13: Adding / deleting / modifying test cases in the pool | D13: =IFERROR(ROUND(SUMPRODUCT(('Detailed Requirements'!C$2:C$5000="FR-007")*('Detailed Requirements'!J$2:J$5000="Backend Dev")*IF(ISNUMBER('Detailed Requirements'!N$2:N$5000),'Detailed Requirements'!N$2:N$5000,0))/'Timeline Summary'!C7,1),0) -> 0.3 | E13: =IFERROR(ROUND(SUMPRODUCT(('Detailed Requirements'!C$2:C$5000="FR-007")*('Detailed Requirements'!J$2:J$5000="Frontend Dev")*IF(ISNUMBER('Detailed Requirements'!N$2:N$5000),'Detailed Requirements'!N$2:N$5000,0))/'Timeline Summary'!C8,1),0) -> 0.3 | F13: =IFERROR(ROUND(SUMPRODUCT(('Detailed Requirements'!C$2:C$5000="FR-007")*('Detailed Requirements'!J$2:J$5000="QA / Both Devs")*IF(ISNUMBER('Detailed Requirements'!N$2:N$5000),'Detailed Requirements'!N$2:N$5000,0))/'Timeline Summary'!C7,1),0) -> 0.3 | G13: =IFERROR(MAX(D13,E13)+F13,0) -> 0.6 | H13: =IFERROR(ROUND(SUMPRODUCT(('Detailed Requirements'!C$2:C$5000="FR-007")*('Detailed Requirements'!J$2:J$5000="Backend Dev")*IF(ISNUMBER('Detailed Requirements'!L$2:L$5000),'Detailed Requirements'!L$2:L$5000,0))/'Timeline Summary'!C7+SUMPRODUCT(('Detailed Requirements'!C$2:C$5000="FR-007")*('Detailed Requirements'!J$2:J$5000="Frontend Dev")*IF(ISNUMBER('Detailed Requirements'!L$2:L$5000),'Detailed Requirements'!L$2:L$5000,0))/'Timeline Summary'!C8+SUMPRODUCT(('Detailed Requirements'!C$2:C$5000="FR-007")*('Detailed Requirements'!J$2:J$5000="QA / Both Devs")*IF(ISNUMBER('Detailed Requirements'!L$2:L$5000),'Detailed Requirements'!L$2:L$5000,0))/'Timeline Summary'!C7,1),0) -> 2.2 | I13: =IFERROR(I12+G13,0) -> 11.6
B14: Import & Export
B15: FR-008 | C15: Export generated test cases to Excel | D15: =IFERROR(ROUND(SUMPRODUCT(('Detailed Requirements'!C$2:C$5000="FR-008")*('Detailed Requirements'!J$2:J$5000="Backend Dev")*IF(ISNUMBER('Detailed Requirements'!N$2:N$5000),'Detailed Requirements'!N$2:N$5000,0))/'Timeline Summary'!C7,1),0) -> 0.1 | E15: =IFERROR(ROUND(SUMPRODUCT(('Detailed Requirements'!C$2:C$5000="FR-008")*('Detailed Requirements'!J$2:J$5000="Frontend Dev")*IF(ISNUMBER('Detailed Requirements'!N$2:N$5000),'Detailed Requirements'!N$2:N$5000,0))/'Timeline Summary'!C8,1),0) -> 0.1 | F15: =IFERROR(ROUND(SUMPRODUCT(('Detailed Requirements'!C$2:C$5000="FR-008")*('Detailed Requirements'!J$2:J$5000="QA / Both Devs")*IF(ISNUMBER('Detailed Requirements'!N$2:N$5000),'Detailed Requirements'!N$2:N$5000,0))/'Timeline Summary'!C7,1),0) -> 0.2 | G15: =IFERROR(MAX(D15,E15)+F15,0) -> 0.3 | H15: =IFERROR(ROUND(SUMPRODUCT(('Detailed Requirements'!C$2:C$5000="FR-008")*('Detailed Requirements'!J$2:J$5000="Backend Dev")*IF(ISNUMBER('Detailed Requirements'!L$2:L$5000),'Detailed Requirements'!L$2:L$5000,0))/'Timeline Summary'!C7+SUMPRODUCT(('Detailed Requirements'!C$2:C$5000="FR-008")*('Detailed Requirements'!J$2:J$5000="Frontend Dev")*IF(ISNUMBER('Detailed Requirements'!L$2:L$5000),'Detailed Requirements'!L$2:L$5000,0))/'Timeline Summary'!C8+SUMPRODUCT(('Detailed Requirements'!C$2:C$5000="FR-008")*('Detailed Requirements'!J$2:J$5000="QA / Both Devs")*IF(ISNUMBER('Detailed Requirements'!L$2:L$5000),'Detailed Requirements'!L$2:L$5000,0))/'Timeline Summary'!C7,1),0) -> 1.2 | I15: =IFERROR(I13+G15,0) -> 11.9
B16: FR-009 | C16: Export generated test cases to Xray | D16: =IFERROR(ROUND(SUMPRODUCT(('Detailed Requirements'!C$2:C$5000="FR-009")*('Detailed Requirements'!J$2:J$5000="Backend Dev")*IF(ISNUMBER('Detailed Requirements'!N$2:N$5000),'Detailed Requirements'!N$2:N$5000,0))/'Timeline Summary'!C7,1),0) -> 1.1 | E16: =IFERROR(ROUND(SUMPRODUCT(('Detailed Requirements'!C$2:C$5000="FR-009")*('Detailed Requirements'!J$2:J$5000="Frontend Dev")*IF(ISNUMBER('Detailed Requirements'!N$2:N$5000),'Detailed Requirements'!N$2:N$5000,0))/'Timeline Summary'!C8,1),0) -> 0.2 | F16: =IFERROR(ROUND(SUMPRODUCT(('Detailed Requirements'!C$2:C$5000="FR-009")*('Detailed Requirements'!J$2:J$5000="QA / Both Devs")*IF(ISNUMBER('Detailed Requirements'!N$2:N$5000),'Detailed Requirements'!N$2:N$5000,0))/'Timeline Summary'!C7,1),0) -> 0.3 | G16: =IFERROR(MAX(D16,E16)+F16,0) -> 1.4 | H16: =IFERROR(ROUND(SUMPRODUCT(('Detailed Requirements'!C$2:C$5000="FR-009")*('Detailed Requirements'!J$2:J$5000="Backend Dev")*IF(ISNUMBER('Detailed Requirements'!L$2:L$5000),'Detailed Requirements'!L$2:L$5000,0))/'Timeline Summary'!C7+SUMPRODUCT(('Detailed Requirements'!C$2:C$5000="FR-009")*('Detailed Requirements'!J$2:J$5000="Frontend Dev")*IF(ISNUMBER('Detailed Requirements'!L$2:L$5000),'Detailed Requirements'!L$2:L$5000,0))/'Timeline Summary'!C8+SUMPRODUCT(('Detailed Requirements'!C$2:C$5000="FR-009")*('Detailed Requirements'!J$2:J$5000="QA / Both Devs")*IF(ISNUMBER('Detailed Requirements'!L$2:L$5000),'Detailed Requirements'!L$2:L$5000,0))/'Timeline Summary'!C7,1),0) -> 5 | I16: =IFERROR(I15+G16,0) -> 13.3
B17: FR-010 | C17: Import test cases from Excel | D17: =IFERROR(ROUND(SUMPRODUCT(('Detailed Requirements'!C$2:C$5000="FR-010")*('Detailed Requirements'!J$2:J$5000="Backend Dev")*IF(ISNUMBER('Detailed Requirements'!N$2:N$5000),'Detailed Requirements'!N$2:N$5000,0))/'Timeline Summary'!C7,1),0) -> 0.7 | E17: =IFERROR(ROUND(SUMPRODUCT(('Detailed Requirements'!C$2:C$5000="FR-010")*('Detailed Requirements'!J$2:J$5000="Frontend Dev")*IF(ISNUMBER('Detailed Requirements'!N$2:N$5000),'Detailed Requirements'!N$2:N$5000,0))/'Timeline Summary'!C8,1),0) -> 0.2 | F17: =IFERROR(ROUND(SUMPRODUCT(('Detailed Requirements'!C$2:C$5000="FR-010")*('Detailed Requirements'!J$2:J$5000="QA / Both Devs")*IF(ISNUMBER('Detailed Requirements'!N$2:N$5000),'Detailed Requirements'!N$2:N$5000,0))/'Timeline Summary'!C7,1),0) -> 0.5 | G17: =IFERROR(MAX(D17,E17)+F17,0) -> 1.2 | H17: =IFERROR(ROUND(SUMPRODUCT(('Detailed Requirements'!C$2:C$5000="FR-010")*('Detailed Requirements'!J$2:J$5000="Backend Dev")*IF(ISNUMBER('Detailed Requirements'!L$2:L$5000),'Detailed Requirements'!L$2:L$5000,0))/'Timeline Summary'!C7+SUMPRODUCT(('Detailed Requirements'!C$2:C$5000="FR-010")*('Detailed Requirements'!J$2:J$5000="Frontend Dev")*IF(ISNUMBER('Detailed Requirements'!L$2:L$5000),'Detailed Requirements'!L$2:L$5000,0))/'Timeline Summary'!C8+SUMPRODUCT(('Detailed Requirements'!C$2:C$5000="FR-010")*('Detailed Requirements'!J$2:J$5000="QA / Both Devs")*IF(ISNUMBER('Detailed Requirements'!L$2:L$5000),'Detailed Requirements'!L$2:L$5000,0))/'Timeline Summary'!C7,1),0) -> 4.2 | I17: =IFERROR(I16+G17,0) -> 14.5
B18: FR-011 | C18: Import test cases from Xray | D18: =IFERROR(ROUND(SUMPRODUCT(('Detailed Requirements'!C$2:C$5000="FR-011")*('Detailed Requirements'!J$2:J$5000="Backend Dev")*IF(ISNUMBER('Detailed Requirements'!N$2:N$5000),'Detailed Requirements'!N$2:N$5000,0))/'Timeline Summary'!C7,1),0) -> 0.7 | E18: =IFERROR(ROUND(SUMPRODUCT(('Detailed Requirements'!C$2:C$5000="FR-011")*('Detailed Requirements'!J$2:J$5000="Frontend Dev")*IF(ISNUMBER('Detailed Requirements'!N$2:N$5000),'Detailed Requirements'!N$2:N$5000,0))/'Timeline Summary'!C8,1),0) -> 0.5 | F18: =IFERROR(ROUND(SUMPRODUCT(('Detailed Requirements'!C$2:C$5000="FR-011")*('Detailed Requirements'!J$2:J$5000="QA / Both Devs")*IF(ISNUMBER('Detailed Requirements'!N$2:N$5000),'Detailed Requirements'!N$2:N$5000,0))/'Timeline Summary'!C7,1),0) -> 0.3 | G18: =IFERROR(MAX(D18,E18)+F18,0) -> 1 | H18: =IFERROR(ROUND(SUMPRODUCT(('Detailed Requirements'!C$2:C$5000="FR-011")*('Detailed Requirements'!J$2:J$5000="Backend Dev")*IF(ISNUMBER('Detailed Requirements'!L$2:L$5000),'Detailed Requirements'!L$2:L$5000,0))/'Timeline Summary'!C7+SUMPRODUCT(('Detailed Requirements'!C$2:C$5000="FR-011")*('Detailed Requirements'!J$2:J$5000="Frontend Dev")*IF(ISNUMBER('Detailed Requirements'!L$2:L$5000),'Detailed Requirements'!L$2:L$5000,0))/'Timeline Summary'!C8+SUMPRODUCT(('Detailed Requirements'!C$2:C$5000="FR-011")*('Detailed Requirements'!J$2:J$5000="QA / Both Devs")*IF(ISNUMBER('Detailed Requirements'!L$2:L$5000),'Detailed Requirements'!L$2:L$5000,0))/'Timeline Summary'!C7,1),0) -> 4.6 | I18: =IFERROR(I17+G18,0) -> 15.5
B19: FR-012 | C19: Import validation service (FR-010 & FR-011) | D19: =IFERROR(ROUND(SUMPRODUCT(('Detailed Requirements'!C$2:C$5000="FR-012")*('Detailed Requirements'!J$2:J$5000="Backend Dev")*IF(ISNUMBER('Detailed Requirements'!N$2:N$5000),'Detailed Requirements'!N$2:N$5000,0))/'Timeline Summary'!C7,1),0) -> 0.4 | E19: =IFERROR(ROUND(SUMPRODUCT(('Detailed Requirements'!C$2:C$5000="FR-012")*('Detailed Requirements'!J$2:J$5000="Frontend Dev")*IF(ISNUMBER('Detailed Requirements'!N$2:N$5000),'Detailed Requirements'!N$2:N$5000,0))/'Timeline Summary'!C8,1),0) -> 0 | F19: =IFERROR(ROUND(SUMPRODUCT(('Detailed Requirements'!C$2:C$5000="FR-012")*('Detailed Requirements'!J$2:J$5000="QA / Both Devs")*IF(ISNUMBER('Detailed Requirements'!N$2:N$5000),'Detailed Requirements'!N$2:N$5000,0))/'Timeline Summary'!C7,1),0) -> 0.2 | G19: =IFERROR(MAX(D19,E19)+F19,0) -> 0.6 | H19: =IFERROR(ROUND(SUMPRODUCT(('Detailed Requirements'!C$2:C$5000="FR-012")*('Detailed Requirements'!J$2:J$5000="Backend Dev")*IF(ISNUMBER('Detailed Requirements'!L$2:L$5000),'Detailed Requirements'!L$2:L$5000,0))/'Timeline Summary'!C7+SUMPRODUCT(('Detailed Requirements'!C$2:C$5000="FR-012")*('Detailed Requirements'!J$2:J$5000="Frontend Dev")*IF(ISNUMBER('Detailed Requirements'!L$2:L$5000),'Detailed Requirements'!L$2:L$5000,0))/'Timeline Summary'!C8+SUMPRODUCT(('Detailed Requirements'!C$2:C$5000="FR-012")*('Detailed Requirements'!J$2:J$5000="QA / Both Devs")*IF(ISNUMBER('Detailed Requirements'!L$2:L$5000),'Detailed Requirements'!L$2:L$5000,0))/'Timeline Summary'!C7,1),0) -> 1.8 | I19: =IFERROR(I18+G19,0) -> 16.1
B20: Journey Stitcher
B21: FR-013 | C21: CLAP enrichment of test cases | D21: =IFERROR(ROUND(SUMPRODUCT(('Detailed Requirements'!C$2:C$5000="FR-013")*('Detailed Requirements'!J$2:J$5000="Backend Dev")*IF(ISNUMBER('Detailed Requirements'!N$2:N$5000),'Detailed Requirements'!N$2:N$5000,0))/'Timeline Summary'!C7,1),0) -> 0.5 | E21: =IFERROR(ROUND(SUMPRODUCT(('Detailed Requirements'!C$2:C$5000="FR-013")*('Detailed Requirements'!J$2:J$5000="Frontend Dev")*IF(ISNUMBER('Detailed Requirements'!N$2:N$5000),'Detailed Requirements'!N$2:N$5000,0))/'Timeline Summary'!C8,1),0) -> 0.7 | F21: =IFERROR(ROUND(SUMPRODUCT(('Detailed Requirements'!C$2:C$5000="FR-013")*('Detailed Requirements'!J$2:J$5000="QA / Both Devs")*IF(ISNUMBER('Detailed Requirements'!N$2:N$5000),'Detailed Requirements'!N$2:N$5000,0))/'Timeline Summary'!C7,1),0) -> 0 | G21: =IFERROR(MAX(D21,E21)+F21,0) -> 0.7 | H21: =IFERROR(ROUND(SUMPRODUCT(('Detailed Requirements'!C$2:C$5000="FR-013")*('Detailed Requirements'!J$2:J$5000="Backend Dev")*IF(ISNUMBER('Detailed Requirements'!L$2:L$5000),'Detailed Requirements'!L$2:L$5000,0))/'Timeline Summary'!C7+SUMPRODUCT(('Detailed Requirements'!C$2:C$5000="FR-013")*('Detailed Requirements'!J$2:J$5000="Frontend Dev")*IF(ISNUMBER('Detailed Requirements'!L$2:L$5000),'Detailed Requirements'!L$2:L$5000,0))/'Timeline Summary'!C8+SUMPRODUCT(('Detailed Requirements'!C$2:C$5000="FR-013")*('Detailed Requirements'!J$2:J$5000="QA / Both Devs")*IF(ISNUMBER('Detailed Requirements'!L$2:L$5000),'Detailed Requirements'!L$2:L$5000,0))/'Timeline Summary'!C7,1),0) -> 2.5 | I21: =IFERROR(I19+G21,0) -> 16.8
B22: FR-014 | C22: CLAP proposes journeys from accepted TCs | D22: =IFERROR(ROUND(SUMPRODUCT(('Detailed Requirements'!C$2:C$5000="FR-014")*('Detailed Requirements'!J$2:J$5000="Backend Dev")*IF(ISNUMBER('Detailed Requirements'!N$2:N$5000),'Detailed Requirements'!N$2:N$5000,0))/'Timeline Summary'!C7,1),0) -> 1.4 | E22: =IFERROR(ROUND(SUMPRODUCT(('Detailed Requirements'!C$2:C$5000="FR-014")*('Detailed Requirements'!J$2:J$5000="Frontend Dev")*IF(ISNUMBER('Detailed Requirements'!N$2:N$5000),'Detailed Requirements'!N$2:N$5000,0))/'Timeline Summary'!C8,1),0) -> 0.9 | F22: =IFERROR(ROUND(SUMPRODUCT(('Detailed Requirements'!C$2:C$5000="FR-014")*('Detailed Requirements'!J$2:J$5000="QA / Both Devs")*IF(ISNUMBER('Detailed Requirements'!N$2:N$5000),'Detailed Requirements'!N$2:N$5000,0))/'Timeline Summary'!C7,1),0) -> 0 | G22: =IFERROR(MAX(D22,E22)+F22,0) -> 1.4 | H22: =IFERROR(ROUND(SUMPRODUCT(('Detailed Requirements'!C$2:C$5000="FR-014")*('Detailed Requirements'!J$2:J$5000="Backend Dev")*IF(ISNUMBER('Detailed Requirements'!L$2:L$5000),'Detailed Requirements'!L$2:L$5000,0))/'Timeline Summary'!C7+SUMPRODUCT(('Detailed Requirements'!C$2:C$5000="FR-014")*('Detailed Requirements'!J$2:J$5000="Frontend Dev")*IF(ISNUMBER('Detailed Requirements'!L$2:L$5000),'Detailed Requirements'!L$2:L$5000,0))/'Timeline Summary'!C8+SUMPRODUCT(('Detailed Requirements'!C$2:C$5000="FR-014")*('Detailed Requirements'!J$2:J$5000="QA / Both Devs")*IF(ISNUMBER('Detailed Requirements'!L$2:L$5000),'Detailed Requirements'!L$2:L$5000,0))/'Timeline Summary'!C7,1),0) -> 4.9 | I22: =IFERROR(I21+G22,0) -> 18.2
